Workbook
Name AccionSobreActivo: Listas!$AC$3:$AC$6
Name AccionSobreActivo2: Listas!$AC$7:$AC$8
Name AccionSobreActivo3: Listas!$AC$9
Name AnalisisTecnico: Listas!$Y$3:$Y$4
Name AreaMinimaCIAI: Infraestructura!$AT$42:$AV$49
Name CD_calidad1: Listas!$H$17:$H$19
Name CD_calidad2: Listas!$H$20
Name CD_cobertura1: Listas!$H$21:$H$23
Name CD_cobertura2: Listas!$H$24
Name CI_calidad1.1: Listas!$M$17:$M$20
Name CI_calidad1.2: Listas!$M$21:$M$23
Name CI_calidad1.3: Listas!$M$24:$M$26
Name CI_calidad2.1: Listas!$M$27:$M$29
Name CI_cobertura1.1: Listas!$M$30:$M$33
Name CI_cobertura1.2: Listas!$M$34:$M$36
Name CI_cobertura1.3: Listas!$M$37:$M$39
Name CI_cobertura2.1: Listas!$M$40:$M$42
Name CumplimientoCondiciones: Listas!$W$3:$W$4
Name EstadoActual: Listas!$L$3:$L$6
Name ExposicionFragilidad: Listas!$AA$3:$AA$5
Name FactorProduccion: Listas!$AI$3:$AI$6
Name FuenteFinanciamiento: Listas!$AO$3:$AO$7
Name Impacto: Listas!$D$3:$D$7
Name Involucrados: Listas!$S$3:$S$6
Name MuroContencion: Listas!$N$3:$N$4
Name Naturaleza: Listas!$H$3:$H$6
Name NivelGobierno: Listas!$J$3:$J$5
Name Optimizar: Listas!$U$3:$U$5
Name PC_calidad: Listas!$F$17:$F$18
Name PC_cobertura: Listas!$F$19:$F$20
Name Probabilidad: Listas!$E$3:$E$7
Name Problematica: Listas!$D$16:$L$24
Name SaneamientoConProyecto: Listas!$AK$3:$AK$9
Name Si_No: Listas!$G$3:$G$4
Name SituacionSaneamientoLegal: Listas!$AE$3:$AE$8
Name TamañoCIAI: Infraestructura!$AQ$38:$AY$40
Name TipoCIAI: Listas!$P$3:$Q$10
Name TipoEjecucion: Listas!$AM$3:$AM$7
Name Titularidad: Listas!$AG$3:$AG$4
Name UBIGEO: UBIGEO!$A$3:$D$1876

Sheet Listas
D2: Impacto | E2: Probabilidad | G2: Si_No | H2: Naturaleza | J2: Nivel de gobierno | L2: Estado actual | N2: Muro de contención | P2: Tipo de CIAI | Q2: niño/as | S2: Involucrados | U2: Optimizar | W2: CumplimientoCondiciones | Y2: AnalisisTecnico | AA2: ExposicionFragilidad | AC2: AccionSobreActivo | AE2: SituacionSaneamientoLegal | AG2: Titularidad | AI2: FactorProduccion | AK2: SaneamientoConProyecto | AM2: TipoEjecucion | AO2: FuenteFinanciamiento
D3: 0.05 | E3: 0.9 | G3: Sí | H3: Mejoramiento | J3: Gobierno Nacional | L3: Bueno | N3: ML | P3: Tipo I-A | Q3: 20 | R3: 1 | S3: Cooperante | U3: EL CIAI existe, sin embargo, dadas las condiciones de la infraestructura, como factor de producción, no se puede optimizar la oferta actual. Para detalle, ver informe técnico de situación de infraestructura del CIAI | W3: Cumple | Y3: Se incluye en el PI | AA3: Bajo | AC3: Construcción | AE3: Inscrito en Registros Públicos a favor del PNCM | AG3: Propiedad del Estado | AI3: Infraestructura | AK3: Acta de facilitación de espacios físicos de bien inmueble, debidamente suscrita por el PNCM y el representante de la Institución Educativa, que contemplen espacios determinados dentro de las instalaciones de las Instituciones Educativas Públicas. | AM3: Administración directa | AO3: Recursos ordinarios
D4: 0.1 | E4: 0.7 | G4: No | H4: Ampliación | J4: Gobierno Regional | L4: Regular | N4: M3 | P4: Tipo I-B | Q4: 20 | R4: 2 | S4: Beneficiario | U4: El CIAI existe y se puede optimizar la oferta actual | W4: No Cumple | Y4: No se incluye en el PI | AA4: Medio | AC4: Reforzamiento | AE4: Caso Gobierno Regional: Resolución y/o acuerdo de consejo que aprueba la afectación a favor o transferencia a favor del PNCM | AG4: Propiedad de particulares (privados) | AI4: Mobiliario | AK4: Certificado literal de la partida registral donde se encuentre inscrita la Afectación en Uso a favor del Programa Nacional Cuna Más – PNCM. | AM4: Administración indirecta – por contrata | AO4: Recursos directamente recaudados | AP4: Marcar
D5: 0.2 | E5: 0.5 | H5: Mejoramiento y ampliación | J5: Gobierno Local | L5: Malo | P5: Tipo II-A | Q5: 32 | R5: 3 | S5: Oponente | AA5: Alto | AC5: Remodelación | AE5: Caso Municipalidad: Resolución de alcaldía y/o acuerdo de consejo que aprueba la transferencia o afectación en uso a favor del PNCM | AI5: Equipo | AK5: Constancia de Posesión otorgada por Municipalidad Distrital a favor del Programa Nacional Cuna Más. | AM5: Administración indirecta – Asociación Público Privado (APP) | AO5: Recursos por operaciones oficiales de crédito
D6: 0.4 | E6: 0.3 | H6: Recuperación | L6: No existe | P6: Tipo II-B | Q6: 40 | R6: 4 | S6: Perjudicado | AC6: Rehabilitación | AE6: Caso Comunidad: Acta de trasferencia o cesión en uso a favor del PNCM, o a favor de una municipalidad, o Gobierno Regional que posteriormente se comprometan a transferirlo a favor de PNCM. | AI6: Capacidades de Recursos Humanos | AK6: Contrato de Comodato suscrito entre el PNCM y el(los) propietario(s) del bien inmueble (Persona Natural), que contemplen el uso exclusivo del local para el Servicio de Cuidado Diurno. | AM6: Administración indirecta – Núcleo Ejecutor | AO6: Donaciones y transferencias
D7: 0.8 | E7: 0.1 | P7: Tipo III-A | Q7: 52 | R7: 5 | AC7: Adquisición | AE7: Carta de intención del propietario, declarando su voluntad de vender y se especifique el área y costo por m2, o una intención de donación | AK7: Convenio de Cesión/Afectación en Uso, suscrito entre el PNCM y una Entidad Pública (Municipalidad, Gobierno Regional, Ministerios entre otras) o privada (Asentamiento Humanos, Comités, Urbanizaciones, etc.); Entidades Religiosas, Sociedad Civiles Sin Fines de Lucro, Comunidades Campesinas y Nativas. | AM7: Administración indirecta – Ley 29230 (Obras por Impuestos) | AO7: Recursos determinados
P8: Tipo III-B | Q8: 60 | R8: 6 | AC8: Reposición | AE8: Acta de compromiso de la UEI de gestionar el Saneamiento Físico Legal del Terreno antes del inicio de la elaboración del Expediente Técnico | AK8: Resolución de Afectación en Uso del bien inmueble emitida por Autoridad Pública competente y con arreglo a Ley.
P9: Tipo IV-A | Q9: 72 | R9: 7 | AC9: Implementación de capacidades | AK9: Otra
P10: Tipo IV-B | Q10: 82 | R10: 8
D16: Problema central | E16: ID_PC | F16: Causas directas | G16: ID Causas directas | H16: Causas indirectas | J16: Objetivo central | K16: Medios de primer nivel | L16: Medios fundamentales | M16: Acciones | N16: Indicador | O16: Descripción | P16: Naturaleza
C17: Mejoramiento | D17: =+"Niños y niñas, entre 6 y 36 meses de edad, acceden a una inadecuada prestación del servicio de cuidado diurno en la localidad de "&'Unidad Productora'!L20&", distrito de "&'Unidad Productora'!J20&", provincia de "&'Unidad Productora'!H20&", departamento de "&'Unidad Productora'!E20 -> Niños y niñas, entre 6 y 36 meses de edad, acceden a una inadecuada prestación del servicio de cuidado diurno en la localidad de , distrito de , provincia de , departamento de | E17: PC_calidad | F17: Inadecuadas condiciones físicas para brindar el servicio de cuidado diurno | G17: CD_calidad1 | H17: Infraestructura del CIAI no cumple con los estándares de calidad | I17: CI_calidad1.1 | J17: =+"Niños y niñas, entre 6 y 36 meses de edad, acceden a una adecuada prestación del servicio de cuidado diurno en la localidad de "&'Unidad Productora'!L20&", distrito de "&'Unidad Productora'!J20&", provincia de "&'Unidad Productora'!H20&", departamento de "&'Unidad Productora'!E20 -> Niños y niñas, entre 6 y 36 meses de edad, acceden a una adecuada prestación del servicio de cuidado diurno en la localidad de , distrito de , provincia de , departamento de | K17: Adecuadas condiciones físicas para brindar el servicio de cuidado diurno | L17: Infraestructura del CIAI cumple con los estándares de calidad | M17: Acción 1.1.1. Construcción de infraestructura del CIAI, que cumpla con los estándares de calidad | N17: Porcentaje de centros infantiles de atención integral que brindan el servicio de cuidado integral en condición inadecuada. (PCIAICI) | O17: El indicador representa la proporción de centros infantiles de atención integral (CIAI) respecto al total a nivel nacional, que tienen al menos un factor productivo que no se encuentra de acuerdo con lo establecido en la normativa del PNCM | P17: Mejoramiento
C18: Ampliación | D18: =+"Niños y niñas, entre 6 y 36 meses de edad, acceden a una inadecuada prestación del servicio de cuidado diurno en la localidad de "&'Unidad Productora'!L20&", distrito de "&'Unidad Productora'!J20&", provincia de "&'Unidad Productora'!H20&", departamento de "&'Unidad Productora'!E20 -> Niños y niñas, entre 6 y 36 meses de edad, acceden a una inadecuada prestación del servicio de cuidado diurno en la localidad de , distrito de , provincia de , departamento de | E18: PC_calidad | F18: Insuficiente capacidad para la gestión y atención del servicio de cuidado diurno | G18: CD_calidad2 | H18: Equipos del CIAI no cumplen con los estándares de calidad | I18: CI_calidad1.2 | J18: =+"Niños y niñas, entre 6 y 36 meses de edad, acceden a una adecuada prestación del servicio de cuidado diurno en la localidad de "&'Unidad Productora'!L20&", distrito de "&'Unidad Productora'!J20&", provincia de "&'Unidad Productora'!H20&", departamento de "&'Unidad Productora'!E20 -> Niños y niñas, entre 6 y 36 meses de edad, acceden a una adecuada prestación del servicio de cuidado diurno en la localidad de , distrito de , provincia de , departamento de | K18: Suficiente capacidad para la gestión y atención del servicio de cuidado diurno | L18: Equipos del CIAI cumplen con los estándares de calidad | M18: Acción 1.1.2 Reforzamiento de infraestructura del CIAI, que cumpla con los estándares de calidad | N18: Porcentaje de centros infantiles de atención integral que brindan el servicio de cuidado integral en condición inadecuada. (PCIAICI) | O18: El indicador representa la proporción de centros infantiles de atención integral (CIAI) respecto al total a nivel nacional, que tienen al menos un factor productivo que no se encuentra de acuerdo con lo establecido en la normativa del PNCM | P18: Ampliación
C19: Mejoramiento y ampliación | D19: =+"Niños y niñas, entre 6 y 36 meses de edad, acceden a una inadecuada prestación del servicio de cuidado diurno en la localidad de "&'Unidad Productora'!L20&", distrito de "&'Unidad Productora'!J20&", provincia de "&'Unidad Productora'!H20&", departamento de "&'Unidad Productora'!E20 -> Niños y niñas, entre 6 y 36 meses de edad, acceden a una inadecuada prestación del servicio de cuidado diurno en la localidad de , distrito de , provincia de , departamento de | E19: PC_calidad | F19: Condiciones físicas inexistentes para brindar el servicio de cuidado diurno | G19: CD_cobertura1 | H19: Mobiliario del CIAI no cumple con los estándares de calidad | I19: CI_calidad1.3 | J19: =+"Niños y niñas, entre 6 y 36 meses de edad, acceden a una adecuada prestación del servicio de cuidado diurno en la localidad de "&'Unidad Productora'!L20&", distrito de "&'Unidad Productora'!J20&", provincia de "&'Unidad Productora'!H20&", departamento de "&'Unidad Productora'!E20 -> Niños y niñas, entre 6 y 36 meses de edad, acceden a una adecuada prestación del servicio de cuidado diurno en la localidad de , distrito de , provincia de , departamento de | K19: Condiciones físicas existentes para brindar el servicio de cuidado diurno | L19: Mobiliario del CIAI cumple con los estándares de calidad | M19: Acción 1.1.3 Remodelación de infraestructura del CIAI, que cumpla con los estándares de calidad | N19: Porcentaje de centros infantiles de atención integral que brindan el servicio de cuidado integral en condición inadecuada. (PCIAICI) | O19: El indicador representa la proporción de centros infantiles de atención integral (CIAI) respecto al total a nivel nacional, que tienen al menos un factor productivo que no se encuentra de acuerdo con lo establecido en la normativa del PNCM | P19: Mejoramiento y ampliación
C20: Recuperación | D20: =+"Niños y niñas, entre 6 y 36 meses de edad, acceden a una inadecuada prestación del servicio de cuidado diurno en la localidad de "&'Unidad Productora'!L20&", distrito de "&'Unidad Productora'!J20&", provincia de "&'Unidad Productora'!H20&", departamento de "&'Unidad Productora'!E20 -> Niños y niñas, entre 6 y 36 meses de edad, acceden a una inadecuada prestación del servicio de cuidado diurno en la localidad de , distrito de , provincia de , departamento de | E20: PC_calidad | F20: Limitadas capacidades para la gestión y para la atención del servicio de cuidado diurno | G20: CD_cobertura2 | H20: Insuficiente capacitación de recursos humanos que operan en el CIAI | I20: CI_calidad2.1 | J20: =+"Niños y niñas, entre 6 y 36 meses de edad, acceden a una adecuada prestación del servicio de cuidado diurno en la localidad de "&'Unidad Productora'!L20&", distrito de "&'Unidad Productora'!J20&", provincia de "&'Unidad Productora'!H20&", departamento de "&'Unidad Productora'!E20 -> Niños y niñas, entre 6 y 36 meses de edad, acceden a una adecuada prestación del servicio de cuidado diurno en la localidad de , distrito de , provincia de , departamento de | K20: Adecuadas capacidades para la gestión y para la atención del servicio de cuidado diurno | L20: Suficientes capacidades organizacionales de los recursos humanos que operan en el CIAI | M20: Acción 1.1.4 Rehabilitación de infraestructura del CIAI, que cumpla con los estándares de calidad | N20: Porcentaje de centros infantiles de atención integral que brindan el servicio de cuidado integral en condición inadecuada. (PCIAICI) | O20: El indicador representa la proporción de centros infantiles de atención integral (CIAI) respecto al total a nivel nacional, que tienen al menos un factor productivo que no se encuentra de acuerdo con lo establecido en la normativa del PNCM | P20: Recuperación
C21: Creación | D21: =+"Niños y niñas, entre 6 y 36 meses de edad, no acceden al servicio de cuidado diurno en la localidad de "&'Unidad Productora'!L20&", distrito de "&'Unidad Productora'!J20&", provincia de "&'Unidad Productora'!H20&", departamento de "&'Unidad Productora'!E20 -> Niños y niñas, entre 6 y 36 meses de edad, no acceden al servicio de cuidado diurno en la localidad de , distrito de , provincia de , departamento de | E21: PC_cobertura | J21: =+"Niños y niñas, entre 6 y 36 meses de edad, acceden al servicio de cuidado diurno en la localidad de "&'Unidad Productora'!L20&", distrito de "&'Unidad Productora'!J20&", provincia de "&'Unidad Productora'!H20&", departamento de "&'Unidad Productora'!E20 -> Niños y niñas, entre 6 y 36 meses de edad, acceden al servicio de cuidado diurno en la localidad de , distrito de , provincia de , departamento de | L21: Se cuenta con infraestructura para brindar el servicio | M21: Acción 1.2.1 Adquisición y/o reposición de equipos para el CIAI, de acuerdo a los estándares definidos por el PNCM. | N21: Porcentaje de centros infantiles de atención integral por implementar. (PCIAIPI) | O21: El indicador determina el déficit de Centros Infantiles de Cuidado Diurno para cubrir las necesidades de niños y niñas entre 6 y 36 meses de edad, que viven en zonas de pobreza y pobreza extrema, considerados como población objetivo, según los criterios de focalización del PNCM. | P21: Creación
L22: Se cuenta con equipos para brindar el servicio
L23: Se cuenta con mobiliario para brindar el servicio
L24: Suficientes capacidades de los recursos humanos para el cuidado integral | M24: Acción 1.3.1 Adquisición y/o reposición de mobiliario para el CIAI, de acuerdo a los estándares definidos por el PNCM.
M27: Acción 2.1.1 Implementación de capacidades humanas a los actores comunitarios que operan el CIAI
M28: Acción 2.1.2 Implementación de capacidades organizacionales a los actores comunitarios que operarán el CIAI.
M30: Acción 1.1.1. Construcción de infraestructura del CIAI, que cumpla con los estándares de calidad
M31: Acción 1.1.2 Reforzamiento de infraestructura del CIAI, que cumpla con los estándares de calidad
M32: Acción 1.1.3 Remodelación de infraestructura del CIAI, que cumpla con los estándares de calidad
M33: Acción 1.1.4 Rehabilitación de infraestructura del CIAI, que cumpla con los estándares de calidad
M34: Acción 1.2.1 Adquisición y/o reposición de equipos para el CIAI, de acuerdo a los estándares definidos por el PNCM.
M37: Acción 1.3.1 Adquisición y/o reposición de mobiliario para el CIAI, de acuerdo a los estándares definidos por el PNCM.
M40: Acción 2.1.1 Implementación de capacidades organizacionales a los actores comunitarios que operarán el CIAI
M41: Acción 2.1.2 cobertura
M42: Acción 2.1.3 cobertura
D44: =+VLOOKUP('Problema-Objetivo'!B8,D17:E21,2,FALSE) -> #N/A
C48: =+VLOOKUP('Problema-Objetivo'!F12,$H$17:$I$24,2,FALSE) -> #N/A | D48: =+VLOOKUP('Problema-Objetivo'!B12,F17:G20,2,FALSE) -> #N/A
C49: =+VLOOKUP('Problema-Objetivo'!F13,$H$17:$I$24,2,FALSE) -> #N/A
C50: =+VLOOKUP('Problema-Objetivo'!F14,$H$17:$I$24,2,FALSE) -> #N/A
C51: =+VLOOKUP('Problema-Objetivo'!F15,$H$17:$I$24,2,FALSE) -> #N/A | D51: =+VLOOKUP('Problema-Objetivo'!B15,F17:G20,2,FALSE) -> #N/A
J54: Caso Gobierno Regional: Resolución y/o acuerdo de consejo que aprueba la afectación a favor o transferencia a favor del PNCM
J55: Caso Municipalidad: Resolución de alcaldía y/o acuerdo de consejo que aprueba la transferencia o afectación en uso
J56: Caso Comunidad: Acta de trasferencia o cesión en uso a favor del PNCM, o a favor de una municipalidad, o Gobierno Regional que posteriormente se comprometan a transferirlo a favor de PNCM.
J57: Acta de compromiso de la UEI de gestionar el Saneamiento Físico Legal del Terreno antes del inicio de la elaboración del Expediente Técnico

Sheet Infraestructura
A1: Anexo 01: Centro Infantil de Atención Integral, Tipo I-A | F1: Anexo 02: Centro Infantil de Atención Integral, Tipo I-B | K1: Anexo 03: Centro Infantil de Atención Integral, Tipo II-A | P1: Anexo 04: Centro Infantil de Atención Integral, Tipo II-B | BI1: Equivalencias: activos estratégicos y ambientes del CIAI
U2: Anexo 05: Centro Infantil de Atencion Integral, Tipo III-A | Z2: Anexo 06: Centro Infantil de Atencion Integral, Tipo III-B | AE2: Anexo 07: Centro Infantil de Atencion Integral, Tipo IV-A | AJ2: Anexo 08: Centro Infantil de Atencion Integral, Tipo IV-B | AR2: Tipo I-A | AS2: Tipo I-B | AT2: Tipo II-A | AU2: Tipo II-B | AV2: Tipo III-A | AW2: Tipo III-B | AX2: Tipo IV-A | AY2: Tipo IV-B | BB2: SA | BI2: Activo estratégico | BJ2: Descripción | BK2: Ambiente según directiva | BL2: =+AR2 -> Tipo I-A | BM2: =+AS2 -> Tipo I-B | BN2: =+AT2 -> Tipo II-A | BO2: =+AU2 -> Tipo II-B | BP2: =+AV2 -> Tipo III-A | BQ2: =+AW2 -> Tipo III-B | BR2: =+AX2 -> Tipo IV-A | BS2: =+AY2 -> Tipo IV-B
B3: ESPACIO | C3: Área Mínima (m2) | D3: Número de niñas/os | G3: ESPACIO | H3: Área Mínima (m2) | I3: Número de niñas/os | L3: ESPACIO | M3: Área Mínima (m2) | N3: Número de niñas/os | Q3: ESPACIO | R3: Área Mínima (m2) | S3: Número de niñas/os | V3: ESPACIO | W3: Área Minima (m2) | X3: Número de niñas/os | AA3: ESPACIO | AB3: Área Mínima (m2) | AC3: Número de niñas/os | AF3: ESPACIO | AG3: Área Minima (m2) | AH3: Número de niñas/os | AK3: ESPACIO | AL3: Área Mínima (m2) | AM3: Número de niñas/os | AO3: Área | AP3: ID | AQ3: Ambiente | AR3: M2 | AS3: M2 | AT3: M2 | AU3: M2 | AV3: M2 | AW3: M2 | AX3: M2 | AY3: M2 | BB3: Área de preparación (cocina) | BE3: 20 | BI3: Sala de cuidado diurno | BJ3: =+'Análisis Técnico'!G56 -> Espacio físico donde se brinda la atención integral a los niños (bebes, gateadores y caminantes), en este espacio se encuentran organizados las áreas de juego y cuidado. | BK3: Sala mixta | BL3: =+AR4 -> 50.4 | BM3: =+AS4 -> 50.4 | BN3: =+AT4 -> 50.4 | BO3: =+AU4 -> 50.4 | BP3: =+AV4 -> 50.4 | BQ3: =+AW4 -> 50.4 | BR3: =+AX4 -> 50.4 | BS3: =+AY4 -> 50.4
A4: CIUDADANO DIURNO | B4: SALA MIXTA 1 | C4: 50.4 | D4: 20 | F4: CIUDADANO DIURNO | G4: SALA MIXTA 1 | H4: 50.4 | I4: 20 | K4: CIUDADANO DIURNO | L4: SALA MIXTA 1 | M4: 50.4 | N4: 20 | P4: CIUDADANO DIURNO | Q4: SALA MIXTA 1 | R4: 50.4 | S4: 20 | U4: CUIDADO DIURNO | V4: SALA MIXTA 1 | W4: 50.4 | X4: 20 | Z4: CUIDADO DIURNO | AA4: SALA MIXTA 1 | AB4: 50.4 | AC4: 20 | AE4: CUIDADO DIURNO | AF4: SALA MIXTA 1 | AG4: 50.4 | AH4: 20 | AJ4: CUIDADO DIURINO | AK4: SALA MIXTA 1 | AL4: 50.4 | AM4: 20 | AO4: Cuidado diurno | AP4: A1 | AQ4: SALA MIXTA 1 | AR4: =+_xlfn.IFNA(VLOOKUP($AQ4,$B$4:$C$30,2,FALSE),"") -> 50.4 | AS4: =+_xlfn.IFNA(VLOOKUP($AQ4,$G$4:$H$30,2,FALSE),"") -> 50.4 | AT4: =+_xlfn.IFNA(VLOOKUP($AQ4,$L$4:$M$30,2,FALSE),"") -> 50.4 | AU4: =+_xlfn.IFNA(VLOOKUP($AQ4,$Q$4:$R$30,2,FALSE),"") -> 50.4 | AV4: =+_xlfn.IFNA(VLOOKUP($AQ4,$V$4:$W$30,2,FALSE),"") -> 50.4 | AW4: =+_xlfn.IFNA(VLOOKUP($AQ4,$AA$4:$AB$30,2,FALSE),"") -> 50.4 | AX4: =+_xlfn.IFNA(VLOOKUP($AQ4,$AF$4:$AG$30,2,FALSE),"") -> 50.4 | AY4: =+_xlfn.IFNA(VLOOKUP($AQ4,$AK$4:$AL$30,2,FALSE),"") -> 50.4 | BB4: Almacén de alimentos | BE4: 9 | BI4: Sala de usos múltiples | BJ4: =+'Análisis Técnico'!G57 -> Espacio donde se realizan los juegos de los niños y actividades lúdicas, este espacio también es utilizado como comedor para la atención alimentaria de los niños . | BK4: Plaza de usos múltiples / comedor | BL4: =+AR16 -> 0 | BM4: =+AS16 -> 15 | BN4: =+AT16 -> 24 | BO4: =+AU16 -> 30 | BP4: =+AV16 -> 39 | BQ4: =+AW16 -> 45 | BR4: =+AX16 -> 54 | BS4: =+AY16 -> 60
B5: Servicios Higiénicos (un inodoro y un lavatorio por cada 8 niños) incluye Pañalera | C5: 8.2 | D5: - | G5: Servicios Higiénicos (un inodoro y un lavatorio por cada 8 niños) incluye Pañalera | H5: 8.2 | I5: - | L5: Servicios Higiénicos (un inodoro y un lavatorio por cada 8 niños) incluye Pañalera | M5: 8.2 | N5: - | Q5: Servicios Higiénicos (un inodoro y un lavatorio por cada 8 niños) incluye Pañalera | R5: 8.2 | S5: - | V5: Servicios Higiénicos (un inodoro y un lavatorio por cada 8 niños) incluye Peñalera | W5: 8.2 | X5: - | AA5: Servicios Higiénicos (un inodoro y un lavatorio por cada 8 niños) incluye Pañalera | AB5: 8.2 | AC5: - | AF5: Servicios Higiénicos (un inodoro y un lavatorio por cada 8 niños) incluye Pañalera | AG5: 8.2 | AH5: - | AK5: Servicios Higiénicos (un inodoro y un lavatorio por cada 8 niños) incluye Pañalera | AL5: 8.2 | AM5: - | AO5: Cuidado diurno | AP5: A2 | AQ5: Servicios Higiénicos (un inodoro y un lavatorio por cada 8 niños) incluye Pañalera | AR5: =+_xlfn.IFNA(VLOOKUP($AQ5,$B$4:$C$30,2,FALSE),"") -> 8.2 | AS5: =+_xlfn.IFNA(VLOOKUP($AQ5,$G$4:$H$30,2,FALSE),"") -> 8.2 | AT5: =+_xlfn.IFNA(VLOOKUP($AQ5,$L$4:$M$30,2,FALSE),"") -> 8.2 | AU5: =+_xlfn.IFNA(VLOOKUP($AQ5,$Q$4:$R$30,2,FALSE),"") -> 8.2 | AV5: =+_xlfn.IFNA(VLOOKUP($AQ5,$V$4:$W$30,2,FALSE),"") -> 8.2 | AW5: =+_xlfn.IFNA(VLOOKUP($AQ5,$AA$4:$AB$30,2,FALSE),"") -> 8.2 | AX5: =+_xlfn.IFNA(VLOOKUP($AQ5,$AF$4:$AG$30,2,FALSE),"") -> 8.2 | AY5: =+_xlfn.IFNA(VLOOKUP($AQ5,$AK$4:$AL$30,2,FALSE),"") -> 8.2 | BB5: Hall de servicio alimentario | BE5: 2.5 | BI5: Ambiente de recreación activa | BJ5: =+'Análisis Técnico'!G58 -> Espacio exterior destinado al encuentro y recreación activa entre niñas y niños, cuidadoras, así como de familias usuarias, organizado y equipado para las actividades. | BK5: Espacio de juego al aire libre | BL5: =+AR24 -> 20.16 | BM5: =+AS24 -> 20.16 | BN5: =+AT24 -> 32.64 | BO5: =+AU24 -> 40.32 | BP5: =+AV24 -> 52.8 | BQ5: =+AW24 -> 60.48 | BR5: =+AX24 -> 72.96 | BS5: =+AY24 -> 80.64
B6: Closet para colchoneta | C6: 1 | D6: - | G6: Closet para colchoneta | H6: 1 | I6: - | L6: Closet para colchoneta | M6: 1 | N6: - | Q6: Closet para colchoneta | R6: 1 | S6: - | V6: Closet para colchoneta | W6: 1 | X6: - | AA6: Closet para colchoneta | AB6: 1 | AC6: - | AF6: Closet para colchoneta | AG6: 1 | AH6: - | AK6: Closet para colchoneta | AL6: 1 | AM6: - | AO6: Cuidado diurno | AP6: A3 | AQ6: Closet para colchoneta | AR6: =+_xlfn.IFNA(VLOOKUP($AQ6,$B$4:$C$30,2,FALSE),"") -> 1 | AS6: =+_xlfn.IFNA(VLOOKUP($AQ6,$G$4:$H$30,2,FALSE),"") -> 1 | AT6: =+_xlfn.IFNA(VLOOKUP($AQ6,$L$4:$M$30,2,FALSE),"") -> 1 | AU6: =+_xlfn.IFNA(VLOOKUP($AQ6,$Q$4:$R$30,2,FALSE),"") -> 1 | AV6: =+_xlfn.IFNA(VLOOKUP($AQ6,$V$4:$W$30,2,FALSE),"") -> 1 | AW6: =+_xlfn.IFNA(VLOOKUP($AQ6,$AA$4:$AB$30,2,FALSE),"") -> 1 | AX6: =+_xlfn.IFNA(VLOOKUP($AQ6,$AF$4:$AG$30,2,FALSE),"") -> 1 | AY6: =+_xlfn.IFNA(VLOOKUP($AQ6,$AK$4:$AL$30,2,FALSE),"") -> 1 | BB6: Espacio para cestos | BE6: 1 | BI6: Ambiente de servicios generales | BJ6: =+'Análisis Técnico'!G59 -> Espacios destinados a actividades de apoyo a las funciones que se realizan en el establecimiento, tales como: área para tanque séptico y pozo percolador, depósito de materiales, patio de servicio, cuarto de tableros, caseta de vigilancia, área de guardado para coches para bebes, espacio de cambio de pañales). | BK6: Servicios complementarios (Área de lavado de vajilla; Servicios higiénicos de adultos (1/2 baño acondicionado para personas con discapacidad); Depósito de material educativo; Cubículo de Bomba de Agua; Closet de Limpieza; Lavandería; Patio Tendal) | BL6: =+AR17+AR18+AR19+AR20+AR21+AR22+AR23 -> 20.52 | BM6: =+AS17+AS18+AS19+AS20+AS21+AS22+AS23 -> 22.32 | BN6: =+AT17+AT18+AT19+AT20+AT21+AT22+AT23 -> 25.32 | BO6: =+AU17+AU18+AU19+AU20+AU21+AU22+AU23 -> 25.32 | BP6: =+AV17+AV18+AV19+AV20+AV21+AV22+AV23 -> 28.32 | BQ6: =+AW17+AW18+AW19+AW20+AW21+AW22+AW23 -> 28.32 | BR6: =+AX17+AX18+AX19+AX20+AX21+AX22+AX23 -> 31.32 | BS6: =+AY17+AY18+AY19+AY20+AY21+AY22+AY23 -> 31.32
A7: SERVICIOS COMPLEMENTARIOS | B7: Área de lavado de vajilla | C7: 1.8 | D7: - | G7: PLAZA DE USOS MULTIPLES/COMEDOR (mínimo 0.75 m2 por total de niños) | H7: 15 | L7: SALA MIXTA 2 | M7: 31.2 | N7: 12 | Q7: SALA MIXTA 2 | R7: 50.4 | S7: 20 | V7: SALA MIXTA 2 | W7: 50.4 | X7: 20 | AA7: SALA MIXTA 2 | AB7: 50.4 | AC7: 20 | AF7: SALA MIXTA 2 | AG7: 50.4 | AH7: 20 | AK7: SALA MIXTA 2 | AL7: 50.4 | AM7: 20 | AO7: Cuidado diurno | AP7: A4 | AQ7: SALA MIXTA 2 | AT7: =+_xlfn.IFNA(VLOOKUP($AQ7,$L$4:$M$30,2,FALSE),"") -> 31.2 | AU7: =+_xlfn.IFNA(VLOOKUP($AQ7,$Q$4:$R$30,2,FALSE),"") -> 50.4 | AV7: =+_xlfn.IFNA(VLOOKUP($AQ7,$V$4:$W$30,2,FALSE),"") -> 50.4 | AW7: =+_xlfn.IFNA(VLOOKUP($AQ7,$AA$4:$AB$30,2,FALSE),"") -> 50.4 | AX7: =+_xlfn.IFNA(VLOOKUP($AQ7,$AF$4:$AG$30,2,FALSE),"") -> 50.4 | AY7: =+_xlfn.IFNA(VLOOKUP($AQ7,$AK$4:$AL$30,2,FALSE),"") -> 50.4 | BB7: Vestidor para socias de cocina | BE7: 2.5 | BI7: Ambiente de preparación y expendio de alimentos | BJ7: =+'Análisis Técnico'!G60 -> Espacio físico utilizado para la preparación de raciones alimenticias de los usuarios. | BK7: Servicio alimentario (Área de preparación (cocina); Vestidor para socias de cocina; Servicios higiénicos de adultos (baño completo); Closet de limpieza; Lavadero; Cubículo de bomba de agua) | BL7: =+BE3+BE7+BE8+BE9+BE10+BE11 -> 28.92 | BM7: =+BL7 -> 28.92 | BN7: =+BM7 -> 28.92 | BO7: =+BN7 -> 28.92 | BP7: =+BO7 -> 28.92 | BQ7: =+BP7 -> 28.92 | BR7: =+BQ7 -> 28.92 | BS7: =+BR7 -> 28.92
B8: Servicios higiénicos de adultos (1/2 baño acondicionado para personas con discapacidad) | C8: 4 | D8: - | F8: SERVICIOS COMPLEMENTARIOS | G8: Área de lavado de vajilla | H8: 2.7 | I8: - | L8: Servicios Higiénicos (un inodoro y un lavatorio por cada 8 niños) incluye Pañalera | M8: 6.4 | N8: - | Q8: Servicios Higiénicos (un inodoro y un lavatorio por cada 8 niños) incluye Pañalera | R8: 8.2 | S8: - | V8: Servicios Higiénicos (un inodoro y un lavatorio por cada 8 niños) incluye Pañalera | W8: 8.2 | X8: - | AA8: Servicios Higiénicos (un inodoro y un lavatorio por cada 8 niños) incluye Pañalera | AB8: 8.2 | AC8: - | AF8: Servicios Higiénicos (un inodoro y un lavatorio por cada 8 niños) incluye Pañalera. | AG8: 8.2 | AH8: - | AK8: Servicios Higiénicos (un inodoro y un lavatorio por cada 8 niños) incluye Pañalera | AL8: 8.2 | AM8: - | AO8: Cuidado diurno | AP8: A5 | AQ8: Servicios Higiénicos (un inodoro y un lavatorio por cada 8 niños) incluye Pañalera | AT8: =+M8 -> 6.4 | AU8: =+_xlfn.IFNA(VLOOKUP($AQ8,$Q$4:$R$30,2,FALSE),"") -> 8.2 | AV8: =+_xlfn.IFNA(VLOOKUP($AQ8,$V$4:$W$30,2,FALSE),"") -> 8.2 | AW8: =+_xlfn.IFNA(VLOOKUP($AQ8,$AA$4:$AB$30,2,FALSE),"") -> 8.2 | AX8: =+_xlfn.IFNA(VLOOKUP($AQ8,$AF$4:$AG$30,2,FALSE),"") -> 8.2 | AY8: =+_xlfn.IFNA(VLOOKUP($AQ8,$AK$4:$AL$30,2,FALSE),"") -> 8.2 | BB8: Servicios higiénicos de adultos (baño completo) | BE8: 3 | BI8: Almacén | BJ8: =+'Análisis Técnico'!G61 -> Espacio físico destinado para el acopio de los insumos alimenticios dentro de la cadena de suministros. | BK8: Almacén de alimentos; Hall de servicio alimentario; Espacio para cestos; | BL8: =+BE4+BE5+BE6 -> 12.5 | BM8: =+BL8 -> 12.5 | BN8: =+BM8 -> 12.5 | BO8: =+BN8 -> 12.5 | BP8: =+BO8 -> 12.5 | BQ8: =+BP8 -> 12.5 | BR8: =+BQ8 -> 12.5 | BS8: =+BR8 -> 12.5
B9: Depósito de material educativo | C9: 3 | D9: - | G9: Servicios higiénicos de adultos (1/2 baño acondicionado para personas con discapacidad) | H9: 4 | I9: - | L9: Closet para colchoneta | M9: 1 | N9: - | Q9: Closet para colchoneta | R9: 1 | S9: - | V9: Closet para colchoneta | W9: 1 | X9: - | AA9: Closet para colchoneta | AB9: 1 | AC9: - | AF9: Closet para colchoneta | AG9: 1 | AH9: - | AK9: Closet para colchoneta | AL9: 1 | AM9: - | AO9: Cuidado diurno | AP9: A6 | AQ9: Closet para colchoneta | AT9: =+_xlfn.IFNA(VLOOKUP($AQ9,$L$4:$M$30,2,FALSE),"") -> 1 | AU9: =+_xlfn.IFNA(VLOOKUP($AQ9,$Q$4:$R$30,2,FALSE),"") -> 1 | AV9: =+_xlfn.IFNA(VLOOKUP($AQ9,$V$4:$W$30,2,FALSE),"") -> 1 | AW9: =+_xlfn.IFNA(VLOOKUP($AQ9,$AA$4:$AB$30,2,FALSE),"") -> 1 | AX9: =+_xlfn.IFNA(VLOOKUP($AQ9,$AF$4:$AG$30,2,FALSE),"") -> 1 | AY9: =+_xlfn.IFNA(VLOOKUP($AQ9,$AK$4:$AL$30,2,FALSE),"") -> 1 | BB9: Closet de limpieza | BE9: 0.72 | BI9: Cerco perimétrico | BJ9: =+'Análisis Técnico'!G62 -> Activo para la protección de la unidad productora. Elemento fijo y seguro que rodea y delimita la propiedad o sus sectores. Cuenta con espacios de acceso al interior del mismo.
B10: Cubículo de Bomba de Agua | C10: 1.2 | D10: - | G10: Depósito de material educativo | H10: 3 | I10: - | L10: PLAZA DE USOS MULTIPLES/COMEDOR (mínimo 0.75 m2 por total de niños) | M10: 24 | N10: - | Q10: PLAZA DE USOS MULTIPLES/COMEDOR (mínimo 0.75 m2 por total de niños) | R10: 30 | S10: - | V10: SALA MIXTA 3 | W10: 31.2 | X10: 12 | AA10: SALA MIXTA 3 | AB10: 50.4 | AC10: 20 | AF10: SALA MIXTA 3 | AG10: 50.4 | AH10: 20 | AK10: SALA MIXTA 3 | AL10: 50.4 | AM10: 20 | AO10: Cuidado diurno | AP10: A7 | AQ10: SALA MIXTA 3 | AV10: =+_xlfn.IFNA(VLOOKUP($AQ10,$V$4:$W$30,2,FALSE),"") -> 31.2 | AW10: =+_xlfn.IFNA(VLOOKUP($AQ10,$AA$4:$AB$30,2,FALSE),"") -> 50.4 | AX10: =+_xlfn.IFNA(VLOOKUP($AQ10,$AF$4:$AG$30,2,FALSE),"") -> 50.4 | AY10: =+_xlfn.IFNA(VLOOKUP($AQ10,$AK$4:$AL$30,2,FALSE),"") -> 50.4 | BB10: Lavadero | BE10: 1.5 | BI10: Muro de contención | BJ10: =+'Análisis Técnico'!G63 -> Activo para la protección de la unidad productora. Estructura rígida destinada a contener masas de suelo u otros materiales sueltos proporcionando estabilidad.
B11: Closet de Limpieza | C11: 0.72 | D11: - | G11: Cubículo de Bomba de Agua | H11: 1.2 | I11: - | K11: SERVICIOS COMPLEMENTARIOS | L11: Área de lavado de vajilla | M11: 2.7 | N11: - | P11: SERVICIOS COMPLEMENTARIOS | Q11: Área de lavado de vajilla | R11: 2.7 | S11: - | V11: Servicios Higiénicos (un inodoro y un lavatono por cada 8 ninos) incluye Pañalera | W11: 6.4 | AA11: Servicios Higiénicos (un inodoro y un lavatono por cada 8 ninos) incluye Pañalera | AB11: 8.2 | AC11: - | AF11: Servicios Higiénicos (un inodoro y un lavatono por cada 8 ninos) incluye Pañalera | AG11: 8.2 | AH11: - | AK11: Servicios Higiénicos (un inodoro y un lavatono por cada 8 ninos) incluye Pañalera | AL11: 8.2 | AM11: - | AO11: Cuidado diurno | AP11: A8 | AQ11: Servicios Higiénicos (un inodoro y un lavatono por cada 8 ninos) incluye Pañalera | AV11: =+_xlfn.IFNA(VLOOKUP($AQ11,$V$4:$W$30,2,FALSE),"") -> 6.4 | AW11: =+_xlfn.IFNA(VLOOKUP($AQ11,$AA$4:$AB$30,2,FALSE),"") -> 8.2 | AX11: =+_xlfn.IFNA(VLOOKUP($AQ11,$AF$4:$AG$30,2,FALSE),"") -> 8.2 | AY11: =+_xlfn.IFNA(VLOOKUP($AQ11,$AK$4:$AL$30,2,FALSE),"") -> 8.2 | BB11: Cubículo de bomba de agua | BE11: 1.2 | BI11: Otros ambientes complementarios | BJ11: =+'Análisis Técnico'!G64 -> 0 | BK11: Servicios higiénicos; clóset | BL11: =+AR5+AR6+AR8+AR9+AR11+AR12+AR14+AR15 -> 9.2 | BM11: =+AS5+AS6+AS8+AS9+AS11+AS12+AS14+AS15 -> 9.2 | BN11: =+AT5+AT6+AT8+AT9+AT11+AT12+AT14+AT15 -> 16.6 | BO11: =+AU5+AU6+AU8+AU9+AU11+AU12+AU14+AU15 -> 18.4 | BP11: =+AV5+AV6+AV8+AV9+AV11+AV12+AV14+AV15 -> 25.8 | BQ11: =+AW5+AW6+AW8+AW9+AW11+AW12+AW14+AW15 -> 27.6 | BR11: =+AX5+AX6+AX8+AX9+AX11+AX12+AX14+AX15 -> 35 | BS11: =+AY5+AY6+AY8+AY9+AY11+AY12+AY14+AY15 -> 36.8
B12: Lavandería | C12: 1.8 | D12: - | G12: Closet de Limpieza | H12: 0.72 | I12: - | L12: Servicios higiénicos de adultos (1/2 baño acondicionado para personas con discapacidad) | M12: 4 | N12: - | Q12: Servicios higiénicos de adultos (1/2 baño acondicionado para personas con discapacidad) | R12: 4 | S12: - | V12: Closet para colchoneta | W12: 1 | X12: - | AA12: Closet para colchoneta | AB12: 1 | AC12: - | AF12: Closet para colchoneta | AG12: 1 | AH12: - | AK12: Closet para colchoneta | AL12: 1 | AM12: - | AO12: Cuidado diurno | AP12: A9 | AQ12: Closet para colchoneta | AV12: =+_xlfn.IFNA(VLOOKUP($AQ12,$V$4:$W$30,2,FALSE),"") -> 1 | AW12: =+_xlfn.IFNA(VLOOKUP($AQ12,$AA$4:$AB$30,2,FALSE),"") -> 1 | AX12: =+_xlfn.IFNA(VLOOKUP($AQ12,$AF$4:$AG$30,2,FALSE),"") -> 1 | AY12: =+_xlfn.IFNA(VLOOKUP($AQ12,$AK$4:$AL$30,2,FALSE),"") -> 1 | BE12: =SUM(BE3:BE11) -> 41.42
B13: Patio Tendal | C13: 8 | D13: - | G13: Lavandería | H13: 2.7 | I13: - | L13: Depósito de material educativo | M13: 6 | N13: - | Q13: Depósito de material educativo | R13: 6 | S13: - | V13: PLAZA DE USOS MULTIPLES/COMEDOR (mínimo 0.75 m2 por total de niños) | W13: 39 | X13: - | AA13: PLAZA DE USOS MULTIPLES/COMEDOR (mínimo 0.75 m2 por total de niños) | AB13: 45 | AC13: - | AF13: SALA MIXTA 4 | AG13: 31.2 | AH13: 12 | AK13: SALA MIXTA 4 | AL13: 50.4 | AM13: 20 | AO13: Cuidado diurno | AP13: A10 | AQ13: SALA MIXTA 4 | AX13: =+_xlfn.IFNA(VLOOKUP($AQ13,$AF$4:$AG$30,2,FALSE),"") -> 31.2 | AY13: =+_xlfn.IFNA(VLOOKUP($AQ13,$AK$4:$AL$30,2,FALSE),"") -> 50.4
B14: Espacio de juego al aire libre (mínimo 40% del área neta de las salas) | C14: 20.16 | G14: Patio Tendal | H14: 8 | I14: - | L14: Cubículo de Bomba de Agua | M14: 1.2 | N14: - | Q14: Cubículo de Bomba de Agua | R14: 1.2 | S14: - | U14: SERVICIOS COMPLEMENTARIOS | V14: Área de lavado de vajilla | W14: 2.7 | X14: - | Z14: SERVICIOS COMPLEMENTARIOS | AA14: Área de lavado de vajilla | AB14: 2.7 | AC14: - | AF14: Servicios Higiénicos (un inodoro y un lavatorio por cada 8 niños) incluye Pañalera. | AG14: 6.4 | AH14: - | AK14: Servicios Higiénicos (un inodoro y un lavatorio por cada 8 niños) incluye Pañalera | AL14: 8.2 | AM14: - | AO14: Cuidado diurno | AP14: A11 | AQ14: Servicios Higiénicos (un inodoro y un lavatorio por cada 8 niños) incluye Pañalera | AX14: =+AG14 -> 6.4 | AY14: =+_xlfn.IFNA(VLOOKUP($AQ14,$AK$4:$AL$30,2,FALSE),"") -> 8.2 | BB14: SALA MIXTA
G15: Espacio de juego al aire libre (mínimo 40% del área neta de las salas) | H15: 20.16 | L15: Closet de Limpieza | M15: 0.72 | N15: - | Q15: Closet de Limpieza | R15: 0.72 | S15: - | V15: Servicios higiénicos de adultos (1/2 baño acondicionado para personas con discapacidad) | W15: 4 | X15: - | AA15: Servicios higiénicos de adultos (1/2 baño acondicionado para personas con discapacidad) | AB15: 4 | AC15: - | AF15: Closet para colchoneta | AG15: 1 | AH15: - | AK15: Closet para colchoneta | AL15: 1 | AM15: - | AO15: Cuidado diurno | AP15: A12 | AQ15: Closet para colchoneta | AX15: =+_xlfn.IFNA(VLOOKUP($AQ15,$AF$4:$AG$30,2,FALSE),"") -> 1 | AY15: =+_xlfn.IFNA(VLOOKUP($AQ15,$AK$4:$AL$30,2,FALSE),"") -> 1 | BB15: Servicios Higiénicos (un inodoro y un lavatorio por cada 8 niños) incluye Pañalera
B16: Área Neta de Ambientes | C16: 72.12 | L16: Lavandería | M16: 2.7 | N16: - | Q16: Lavandería | R16: 2.7 | S16: - | V16: Depósito de material educativo | W16: 9 | X16: - | AA16: Depósito de material educativo | AB16: 9 | AC16: - | AF16: PLAZA DE USOS MULTIPLES/COMEDOR (mínimo 0.75 m2 por total de niños) | AG16: 54 | AH16: - | AK16: PLAZA DE USOS MULTIPLES/COMEDOR (mínimo 0.75 m2 por total de niños) | AL16: 60 | AM16: - | AO16: Cuidado diurno | AP16: A13 | AQ16: PLAZA DE USOS MULTIPLES/COMEDOR (mínimo 0.75 m2 por total de niños) | AS16: =+_xlfn.IFNA(VLOOKUP($AQ16,$G$4:$H$30,2,FALSE),"") -> 15 | AT16: =+_xlfn.IFNA(VLOOKUP($AQ16,$L$4:$M$30,2,FALSE),"") -> 24 | AU16: =+_xlfn.IFNA(VLOOKUP($AQ16,$Q$4:$R$30,2,FALSE),"") -> 30 | AV16: =+_xlfn.IFNA(VLOOKUP($AQ16,$V$4:$W$30,2,FALSE),"") -> 39 | AW16: =+_xlfn.IFNA(VLOOKUP($AQ16,$AA$4:$AB$30,2,FALSE),"") -> 45 | AX16: =+_xlfn.IFNA(VLOOKUP($AQ16,$AF$4:$AG$30,2,FALSE),"") -> 54 | AY16: =+_xlfn.IFNA(VLOOKUP($AQ16,$AK$4:$AL$30,2,FALSE),"") -> 60 | BB16: Closet para colchoneta
B17: % de circulación de muros (20%) | C17: 14.42 | G17: Área Neta de Ambientes | H17: 88.92 | L17: Patio Tendal | M17: 8 | N17: - | Q17: Patio Tendal | R17: 8 | S17: - | V17: Cubículo de Bomba de Agua | W17: 1.2 | X17: - | AA17: Cubículo de Bomba de Agua | AB17: 1.2 | AC17: - | AE17: SERVICIOS COMPLEMENTARIOS | AF17: Área de lavado de vajilla | AG17: 2.7 | AH17: - | AJ17: SERVICIOS COMPLEMENTARIOS | AK17: Área de lavado de vajilla | AL17: 2.7 | AM17: - | AO17: Servicios complementarios | AP17: A14 | AQ17: Área de lavado de vajilla | AR17: =+_xlfn.IFNA(VLOOKUP($AQ17,$B$4:$C$30,2,FALSE),"") -> 1.8 | AS17: =+_xlfn.IFNA(VLOOKUP($AQ17,$G$4:$H$30,2,FALSE),"") -> 2.7 | AT17: =+_xlfn.IFNA(VLOOKUP($AQ17,$L$4:$M$30,2,FALSE),"") -> 2.7 | AU17: =+_xlfn.IFNA(VLOOKUP($AQ17,$Q$4:$R$30,2,FALSE),"") -> 2.7 | AV17: =+_xlfn.IFNA(VLOOKUP($AQ17,$V$4:$W$30,2,FALSE),"") -> 2.7 | AW17: =+_xlfn.IFNA(VLOOKUP($AQ17,$AA$4:$AB$30,2,FALSE),"") -> 2.7 | AX17: =+_xlfn.IFNA(VLOOKUP($AQ17,$AF$4:$AG$30,2,FALSE),"") -> 2.7 | AY17: =+_xlfn.IFNA(VLOOKUP($AQ17,$AK$4:$AL$30,2,FALSE),"") -> 2.7 | BB17: Closet para colchoneta
B18: Área Techada Total | C18: 86.54 | G18: % de circulación de muros (20%) | H18: 17.78 | L18: Espacio de juego al aire libre (mínimo 40% del área neta de las salas) | M18: 32.64 | Q18: Espacio de juego al aire libre (mínimo 40% del área neta de las salas) | R18: 40.32 | V18: Closet de Limpieza | W18: 0.72 | X18: - | AA18: Closet de Limpieza | AB18: 0.72 | AC18: - | AF18: Servicios higiénicos de adultos (1/2 baño acondicionado para personas con discapacidad) | AG18: 4 | AH18: - | AK18: Servicios higiénicos de adultos (1/2 baño acondicionado para personas con discapacidad) | AL18: 4 | AM18: - | AO18: Servicios complementarios | AP18: A15 | AQ18: Servicios higiénicos de adultos (1/2 baño acondicionado para personas con discapacidad) | AR18: =+_xlfn.IFNA(VLOOKUP($AQ18,$B$4:$C$30,2,FALSE),"") -> 4 | AS18: =+_xlfn.IFNA(VLOOKUP($AQ18,$G$4:$H$30,2,FALSE),"") -> 4 | AT18: =+_xlfn.IFNA(VLOOKUP($AQ18,$L$4:$M$30,2,FALSE),"") -> 4 | AU18: =+_xlfn.IFNA(VLOOKUP($AQ18,$Q$4:$R$30,2,FALSE),"") -> 4 | AV18: =+_xlfn.IFNA(VLOOKUP($AQ18,$V$4:$W$30,2,FALSE),"") -> 4 | AW18: =+_xlfn.IFNA(VLOOKUP($AQ18,$AA$4:$AB$30,2,FALSE),"") -> 4 | AX18: =+_xlfn.IFNA(VLOOKUP($AQ18,$AF$4:$AG$30,2,FALSE),"") -> 4 | AY18: =+_xlfn.IFNA(VLOOKUP($AQ18,$AK$4:$AL$30,2,FALSE),"") -> 4 | BB18: PLAZA DE USOS MULTIPLES/COMEDOR (mínimo 0.75 m2 por total de niños)
B19: Área libre mínima (30% del área del terreno) | C19: 37.09 | G19: Área Techada Total | H19: 106.7 | V19: Lavandería | W19: 2.7 | X19: - | AA19: Lavandería | AB19: 2.7 | AC19: - | AF19: Depósito de material educativo | AG19: 12 | AH19: - | AK19: Depósito de material educativo | AL19: 12 | AM19: - | AO19: Servicios complementarios | AP19: A16 | AQ19: Depósito de material educativo | AR19: =+_xlfn.IFNA(VLOOKUP($AQ19,$B$4:$C$30,2,FALSE),"") -> 3 | AS19: =+_xlfn.IFNA(VLOOKUP($AQ19,$G$4:$H$30,2,FALSE),"") -> 3 | AT19: =+_xlfn.IFNA(VLOOKUP($AQ19,$L$4:$M$30,2,FALSE),"") -> 6 | AU19: =+_xlfn.IFNA(VLOOKUP($AQ19,$Q$4:$R$30,2,FALSE),"") -> 6 | AV19: =+_xlfn.IFNA(VLOOKUP($AQ19,$V$4:$W$30,2,FALSE),"") -> 9 | AW19: =+_xlfn.IFNA(VLOOKUP($AQ19,$AA$4:$AB$30,2,FALSE),"") -> 9 | AX19: =+_xlfn.IFNA(VLOOKUP($AQ19,$AF$4:$AG$30,2,FALSE),"") -> 12 | AY19: =+_xlfn.IFNA(VLOOKUP($AQ19,$AK$4:$AL$30,2,FALSE),"") -> 12 | BB19: Área de lavado de vajilla
B20: Área de Terreno mínima | C20: 123.63 | G20: Área libre mínima (30% del área del terreno) | H20: 45.73 | L20: Área Neta de Ambientes | M20: 139.52 | Q20: Área Neta de Ambientes | R20: 166.52 | V20: Patio Tendal | W20: 8 | X20: - | AA20: Patio Tendal | AB20: 8 | AC20: - | AF20: Cubículo de Bomba de Agua | AG20: 1.2 | AH20: - | AK20: Cubículo de Bomba de Agua | AL20: 1.2 | AM20: - | AO20: Servicios complementarios | AP20: A17 | AQ20: Cubículo de Bomba de Agua | AR20: =+_xlfn.IFNA(VLOOKUP($AQ20,$B$4:$C$30,2,FALSE),"") -> 1.2 | AS20: =+_xlfn.IFNA(VLOOKUP($AQ20,$G$4:$H$30,2,FALSE),"") -> 1.2 | AT20: =+_xlfn.IFNA(VLOOKUP($AQ20,$L$4:$M$30,2,FALSE),"") -> 1.2 | AU20: =+_xlfn.IFNA(VLOOKUP($AQ20,$Q$4:$R$30,2,FALSE),"") -> 1.2 | AV20: =+_xlfn.IFNA(VLOOKUP($AQ20,$V$4:$W$30,2,FALSE),"") -> 1.2 | AW20: =+_xlfn.IFNA(VLOOKUP($AQ20,$AA$4:$AB$30,2,FALSE),"") -> 1.2 | AX20: =+_xlfn.IFNA(VLOOKUP($AQ20,$AF$4:$AG$30,2,FALSE),"") -> 1.2 | AY20: =+_xlfn.IFNA(VLOOKUP($AQ20,$AK$4:$AL$30,2,FALSE),"") -> 1.2 | BB20: Servicios higiénicos de adultos (1/2 baño acondicionado para personas con discapacidad)
G21: Área de Terreno mínima | H21: 152.43 | L21: % de circulación de muros (20%) | M21: 27.9 | Q21: % de circulación de muros (20%) | R21: 33.3 | V21: Espacio de juego al aire libre (mínimo 40% del área neta de las salas) | W21: 52.8 | AA21: Espacio de juego al aire libre (mínimo 40% del área neta de las salas) | AB21: 60.48 | AC21: - | AF21: Closet de Limpieza | AG21: 0.72 | AH21: - | AK21: Closet de Limpieza | AL21: 0.72 | AM21: - | AO21: Servicios complementarios | AP21: A18 | AQ21: Closet de Limpieza | AR21: =+_xlfn.IFNA(VLOOKUP($AQ21,$B$4:$C$30,2,FALSE),"") -> 0.72 | AS21: =+_xlfn.IFNA(VLOOKUP($AQ21,$G$4:$H$30,2,FALSE),"") -> 0.72 | AT21: =+_xlfn.IFNA(VLOOKUP($AQ21,$L$4:$M$30,2,FALSE),"") -> 0.72 | AU21: =+_xlfn.IFNA(VLOOKUP($AQ21,$Q$4:$R$30,2,FALSE),"") -> 0.72 | AV21: =+_xlfn.IFNA(VLOOKUP($AQ21,$V$4:$W$30,2,FALSE),"") -> 0.72 | AW21: =+_xlfn.IFNA(VLOOKUP($AQ21,$AA$4:$AB$30,2,FALSE),"") -> 0.72 | AX21: =+_xlfn.IFNA(VLOOKUP($AQ21,$AF$4:$AG$30,2,FALSE),"") -> 0.72 | AY21: =+_xlfn.IFNA(VLOOKUP($AQ21,$AK$4:$AL$30,2,FALSE),"") -> 0.72 | BB21: Depósito de material educativo
L22: Área Techada Total | M22: 167.42 | Q22: Área Techada Total | R22: 199.82 | AF22: Lavandería | AG22: 2.7 | AH22: - | AK22: Lavandería | AL22: 2.7 | AM22: - | AO22: Servicios complementarios | AP22: A19 | AQ22: Lavandería | AR22: =+_xlfn.IFNA(VLOOKUP($AQ22,$B$4:$C$30,2,FALSE),"") -> 1.8 | AS22: =+_xlfn.IFNA(VLOOKUP($AQ22,$G$4:$H$30,2,FALSE),"") -> 2.7 | AT22: =+_xlfn.IFNA(VLOOKUP($AQ22,$L$4:$M$30,2,FALSE),"") -> 2.7 | AU22: =+_xlfn.IFNA(VLOOKUP($AQ22,$Q$4:$R$30,2,FALSE),"") -> 2.7 | AV22: =+_xlfn.IFNA(VLOOKUP($AQ22,$V$4:$W$30,2,FALSE),"") -> 2.7 | AW22: =+_xlfn.IFNA(VLOOKUP($AQ22,$AA$4:$AB$30,2,FALSE),"") -> 2.7 | AX22: =+_xlfn.IFNA(VLOOKUP($AQ22,$AF$4:$AG$30,2,FALSE),"") -> 2.7 | AY22: =+_xlfn.IFNA(VLOOKUP($AQ22,$AK$4:$AL$30,2,FALSE),"") -> 2.7 | BB22: Cubículo de Bomba de Agua
L23: Área libre mínima (30% del área del terreno) | M23: 71.15 | Q23: Área libre mínima (30% del área del terreno) | R23: 85.64 | V23: Área Neta de Ambientes | W23: 217.12 | AA23: Área Neta de Ambientes | AB23: 244.12 | AF23: Patio Tendal | AG23: 8 | AH23: - | AK23: Patio Tendal | AL23: 8 | AM23: - | AO23: Servicios complementarios | AP23: A20 | AQ23: Patio Tendal | AR23: =+_xlfn.IFNA(VLOOKUP($AQ23,$B$4:$C$30,2,FALSE),"") -> 8 | AS23: =+_xlfn.IFNA(VLOOKUP($AQ23,$G$4:$H$30,2,FALSE),"") -> 8 | AT23: =+_xlfn.IFNA(VLOOKUP($AQ23,$L$4:$M$30,2,FALSE),"") -> 8 | AU23: =+_xlfn.IFNA(VLOOKUP($AQ23,$Q$4:$R$30,2,FALSE),"") -> 8 | AV23: =+_xlfn.IFNA(VLOOKUP($AQ23,$V$4:$W$30,2,FALSE),"") -> 8 | AW23: =+_xlfn.IFNA(VLOOKUP($AQ23,$AA$4:$AB$30,2,FALSE),"") -> 8 | AX23: =+_xlfn.IFNA(VLOOKUP($AQ23,$AF$4:$AG$30,2,FALSE),"") -> 8 | AY23: =+_xlfn.IFNA(VLOOKUP($AQ23,$AK$4:$AL$30,2,FALSE),"") -> 8 | BB23: Closet de Limpieza
L24: Área de Terreno mínima | M24: 239.17 | Q24: Área de Terreno mínima | R24: 285.46 | V24: % de circulación de muros (20%) | W24: 43.42 | AA24: % de circulación de muros (20%) | AB24: 48.82 | AF24: Espacio de juego al aire libre (mínimo 40% del área neta de las salas) | AG24: 72.96 | AH24: - | AK24: Espacio de juego al aire libre (mínimo 40% del área neta de las salas) | AL24: 80.64 | AM24: - | AO24: Servicios complementarios | AP24: A21 | AQ24: Espacio de juego al aire libre (mínimo 40% del área neta de las salas) | AR24: =+_xlfn.IFNA(VLOOKUP($AQ24,$B$4:$C$30,2,FALSE),"") -> 20.16 | AS24: =+_xlfn.IFNA(VLOOKUP($AQ24,$G$4:$H$30,2,FALSE),"") -> 20.16 | AT24: =+_xlfn.IFNA(VLOOKUP($AQ24,$L$4:$M$30,2,FALSE),"") -> 32.64 | AU24: =+_xlfn.IFNA(VLOOKUP($AQ24,$Q$4:$R$30,2,FALSE),"") -> 40.32 | AV24: =+_xlfn.IFNA(VLOOKUP($AQ24,$V$4:$W$30,2,FALSE),"") -> 52.8 | AW24: =+_xlfn.IFNA(VLOOKUP($AQ24,$AA$4:$AB$30,2,FALSE),"") -> 60.48 | AX24: =+_xlfn.IFNA(VLOOKUP($AQ24,$AF$4:$AG$30,2,FALSE),"") -> 72.96 | AY24: =+_xlfn.IFNA(VLOOKUP($AQ24,$AK$4:$AL$30,2,FALSE),"") -> 80.64 | BB24: Lavandería
V25: Área Techada Total | W25: 260.54 | AA25: Área Techada Total | AB25: 292.94 | AR25: =+_xlfn.IFNA(VLOOKUP(AQ25,$B$4:$C$30,2,FALSE),"") | AS25: =+_xlfn.IFNA(VLOOKUP($AQ25,$G$4:$H$30,2,FALSE),"") | AT25: =+_xlfn.IFNA(VLOOKUP($AQ25,$L$4:$M$30,2,FALSE),"") | AU25: =+_xlfn.IFNA(VLOOKUP($AQ25,$Q$4:$R$30,2,FALSE),"") | AV25: =+_xlfn.IFNA(VLOOKUP($AQ25,$V$4:$W$30,2,FALSE),"") | AW25: =+_xlfn.IFNA(VLOOKUP($AQ25,$AA$4:$AB$30,2,FALSE),"") | AX25: =+_xlfn.IFNA(VLOOKUP($AQ25,$AF$4:$AG$30,2,FALSE),"") | AY25: =+_xlfn.IFNA(VLOOKUP($AQ25,$AK$4:$AL$30,2,FALSE),"")
V26: Área libre mínima (30% del área del terreno) | W26: 111.66 | AA26: Área libre mínima (30% del área del terreno) | AB26: 125.55 | AF26: Área Neta de Ambientes | AG26: 294.72 | AK26: Área Neta de Ambientes | AL26: 321.72 | AQ26: Área Neta de Ambientes | AR26: =+_xlfn.IFNA(VLOOKUP(AQ26,$B$4:$C$30,2,FALSE),"") -> 72.12 | AS26: =+_xlfn.IFNA(VLOOKUP($AQ26,$G$4:$H$30,2,FALSE),"") -> 88.92 | AT26: =+_xlfn.IFNA(VLOOKUP($AQ26,$L$4:$M$30,2,FALSE),"") -> 139.52 | AU26: =+_xlfn.IFNA(VLOOKUP($AQ26,$Q$4:$R$30,2,FALSE),"") -> 166.52 | AV26: =+_xlfn.IFNA(VLOOKUP($AQ26,$V$4:$W$30,2,FALSE),"") -> 217.12 | AW26: =+_xlfn.IFNA(VLOOKUP($AQ26,$AA$4:$AB$30,2,FALSE),"") -> 244.12 | AX26: =+_xlfn.IFNA(VLOOKUP($AQ26,$AF$4:$AG$30,2,FALSE),"") -> 294.72 | AY26: =+_xlfn.IFNA(VLOOKUP($AQ26,$AK$4:$AL$30,2,FALSE),"") -> 321.72
V27: Área de Terreno mínima | W27: 372.2 | AA27: Área de Terreno mínima | AB27: 418.49 | AF27: % de circulación de muros (20%) | AG27: 58.94 | AK27: % de circulación de muros (20%) | AL27: 64.34 | AQ27: % de circulación de muros (20%) | AR27: =+_xlfn.IFNA(VLOOKUP(AQ27,$B$4:$C$30,2,FALSE),"") -> 14.42 | AS27: =+_xlfn.IFNA(VLOOKUP($AQ27,$G$4:$H$30,2,FALSE),"") -> 17.78 | AT27: =+_xlfn.IFNA(VLOOKUP($AQ27,$L$4:$M$30,2,FALSE),"") -> 27.9 | AU27: =+_xlfn.IFNA(VLOOKUP($AQ27,$Q$4:$R$30,2,FALSE),"") -> 33.3 | AV27: =+_xlfn.IFNA(VLOOKUP($AQ27,$V$4:$W$30,2,FALSE),"") -> 43.42 | AW27: =+_xlfn.IFNA(VLOOKUP($AQ27,$AA$4:$AB$30,2,FALSE),"") -> 48.82 | AX27: =+_xlfn.IFNA(VLOOKUP($AQ27,$AF$4:$AG$30,2,FALSE),"") -> 58.94 | AY27: =+_xlfn.IFNA(VLOOKUP($AQ27,$AK$4:$AL$30,2,FALSE),"") -> 64.34
AF28: Área Techada Total | AG28: 353.66 | AK28: Área Techada Total | AL28: 385.06 | AQ28: Área Techada Total | AR28: =+_xlfn.IFNA(VLOOKUP(AQ28,$B$4:$C$30,2,FALSE),"") -> 86.54 | AS28: =+_xlfn.IFNA(VLOOKUP($AQ28,$G$4:$H$30,2,FALSE),"") -> 106.7 | AT28: =+_xlfn.IFNA(VLOOKUP($AQ28,$L$4:$M$30,2,FALSE),"") -> 167.42 | AU28: =+_xlfn.IFNA(VLOOKUP($AQ28,$Q$4:$R$30,2,FALSE),"") -> 199.82 | AV28: =+_xlfn.IFNA(VLOOKUP($AQ28,$V$4:$W$30,2,FALSE),"") -> 260.54 | AW28: =+_xlfn.IFNA(VLOOKUP($AQ28,$AA$4:$AB$30,2,FALSE),"") -> 292.94 | AX28: =+_xlfn.IFNA(VLOOKUP($AQ28,$AF$4:$AG$30,2,FALSE),"") -> 353.66 | AY28: =+_xlfn.IFNA(VLOOKUP($AQ28,$AK$4:$AL$30,2,FALSE),"") -> 385.06
AF29: Área libre mínima (30% del área del terreno) | AG29: 151.57 | AK29: Área libre mínima (30% del área del terreno) | AL29: 165.45 | AO29: 0.428 | AQ29: Área libre mínima (30% del área del terreno) | AR29: =+_xlfn.IFNA(VLOOKUP(AQ29,$B$4:$C$30,2,FALSE),"") -> 37.09 | AS29: =+_xlfn.IFNA(VLOOKUP($AQ29,$G$4:$H$30,2,FALSE),"") -> 45.73 | AT29: =+_xlfn.IFNA(VLOOKUP($AQ29,$L$4:$M$30,2,FALSE),"") -> 71.15 | AU29: =+_xlfn.IFNA(VLOOKUP($AQ29,$Q$4:$R$30,2,FALSE),"") -> 85.64 | AV29: =+_xlfn.IFNA(VLOOKUP($AQ29,$V$4:$W$30,2,FALSE),"") -> 111.66 | AW29: =+_xlfn.IFNA(VLOOKUP($AQ29,$AA$4:$AB$30,2,FALSE),"") -> 125.55 | AX29: =+_xlfn.IFNA(VLOOKUP($AQ29,$AF$4:$AG$30,2,FALSE),"") -> 151.57 | AY29: =+_xlfn.IFNA(VLOOKUP($AQ29,$AK$4:$AL$30,2,FALSE),"") -> 165.45
AF30: Área de Terreno mínima | AG30: 505.23 | AK30: Área de Terreno mínima | AL30: 551.51 | AQ30: Área de Terreno mínima | AR30: =+_xlfn.IFNA(VLOOKUP(AQ30,$B$4:$C$30,2,FALSE),"") -> 123.63 | AS30: =+_xlfn.IFNA(VLOOKUP($AQ30,$G$4:$H$30,2,FALSE),"") -> 152.43 | AT30: =+_xlfn.IFNA(VLOOKUP($AQ30,$L$4:$M$30,2,FALSE),"") -> 239.17 | AU30: =+_xlfn.IFNA(VLOOKUP($AQ30,$Q$4:$R$30,2,FALSE),"") -> 285.46 | AV30: =+_xlfn.IFNA(VLOOKUP($AQ30,$V$4:$W$30,2,FALSE),"") -> 372.2 | AW30: =+_xlfn.IFNA(VLOOKUP($AQ30,$AA$4:$AB$30,2,FALSE),"") -> 418.49 | AX30: =+_xlfn.IFNA(VLOOKUP($AQ30,$AF$4:$AG$30,2,FALSE),"") -> 505.23 | AY30: =+_xlfn.IFNA(VLOOKUP($AQ30,$AK$4:$AL$30,2,FALSE),"") -> 551.51
AR38: Tipo I-A | AS38: Tipo I-B | AT38: Tipo II-A | AU38: Tipo II-B | AV38: Tipo III-A | AW38: Tipo III-B | AX38: Tipo IV-A | AY38: Tipo IV-B
AQ39: Capacidad de atención (niños y niñas) | AR39: 20 | AS39: 20 | AT39: 32 | AU39: 40 | AV39: 52 | AW39: 60 | AX39: 72 | AY39: 82
AQ40: =+AQ30 -> Área de Terreno mínima | AR40: 123.63 | AS40: 152.43 | AT40: 239.17 | AU40: 285.46 | AV40: 372.2 | AW40: 418.49 | AX40: 505.23 | AY40: 551.51
AT41: Área insuficiente | AV41: 0 | AW41: Área insuficiente
AS42: 20 | AT42: Tipo I-A | AV42: 123.63 | AW42: Tipo I-A | AX42: 1
AS43: 20 | AT43: Tipo I-B | AV43: 152.43 | AW43: Tipo I-B | AX43: 2
AS44: 32 | AT44: Tipo II-A | AV44: 239.17 | AW44: Tipo II-A | AX44: 3
AS45: 40 | AT45: Tipo II-B | AV45: 285.46 | AW45: Tipo II-B | AX45: 4
AS46: 52 | AT46: Tipo III-A | AV46: 372.2 | AW46: Tipo III-A | AX46: 5
AS47: 60 | AT47: Tipo III-B | AV47: 418.49 | AW47: Tipo III-B | AX47: 6
AS48: 72 | AT48: Tipo IV-A | AV48: 505.23 | AW48: Tipo IV-A | AX48: 7
AS49: 82 | AT49: Tipo IV-B | AV49: 551.51 | AW49: Tipo IV-B | AX49: 8

Sheet Datos Generales
B2: SECCIÓN N°01: DATOS GENERALES DEL PROYECTO
B4: 1.01 Institucionalidad
B6: UNIDAD FORMULADORA (UF)
B8: Nivel de gobierno :
B10: Entidad :
B12: Nombre de la UF:
B14: Responsable de la UF:
B16: UNIDAD EJECUTORA DE INVERSIONES (UEI)
B18: Nivel de gobierno :
B20: Entidad :
B22: Nombre de la UEI:
B24: Responsable de la UEI:
B27: 1.02 Responsabilidad funcional y tipología del proyecto de inversión
B29: Función | H29: 23 PROTECCIÓN SOCIAL
B31: División funcional | H31: 051 ASISTENCIA SOCIAL
B33: Grupo funcional | H33: 0115 PROTECCIÓN DE POBLACIONES EN RIESGO
B35: Sector responsable | H35: DESARROLLO E INCLUSION SOCIAL
B37: Tipología de proyecto | H37: CENTRO INFANTIL DE ATENCIÓN INTEGRAL
B40: 1.03 Nombre del proyecto de inversión
B42: Naturaleza de intervención | F42: Objeto de intervención | K42: Localización
F44: =+IF(B44="","","del Servicio de Cuidado Infantil en el Centro Infantil de Atención Integral (CIAI)") | K44: =+IF(B44="","","en la localidad de "&'Unidad Productora'!L20&", distrito de "&'Unidad Productora'!J20&", provincia de "&'Unidad Productora'!H20&", departamento de "&'Unidad Productora'!E20)
B47: 1.04 Alineamiento y contribución al cierre de una brecha prioritaria
B49: Servicios públicos con brecha identificada y priorizada | M49: =+IF(B44="","","Servicio de cuidado diurno")
B51: Nombre del Indicador de brecha de acceso a servicios | J51: Unidad de medida | N51: Espacio geográfico | R51: Año | T51: Valor
B53: =+'Problema-Objetivo'!F8 | J53: =+IF(B44="","","Centro Infantil de Atención Integral (CIAI)") | N53: =+IF(B44="","","Distrito de "&'Unidad Productora'!J20) | R53: =IF(B44="","",TODAY())
B55: Contribución del Cierre de Brecha (Valor) | F55: Valor:

Sheet Territorio
B2: SECCIÓN N°02: DIAGNÓSTICO DEL TERRITORIO
B4: 2.01 Localización del área de estudio del proyecto
B6: N° | C6: Ubigeo | G6: Departamento | K6: Provincia | L6: Provincia | O6: Distrito | S6: Localidad/Centro poblado
B7: 1 | G7: =+IF(C7="","",VLOOKUP(C7,UBIGEO,4,FALSE)) | K7: =+IF(C7="","",VLOOKUP(C7,UBIGEO,3,FALSE)) | O7: =+IF(C7="","",VLOOKUP(C7,UBIGEO,2,FALSE))
B8: 2 | G8: =+IF(C8="","",VLOOKUP(C8,UBIGEO,4,FALSE)) | K8: =+IF(C8="","",VLOOKUP(C8,UBIGEO,3,FALSE)) | O8: =+IF(C8="","",VLOOKUP(C8,UBIGEO,2,FALSE))
B9: 3 | G9: =+IF(C9="","",VLOOKUP(C9,UBIGEO,4,FALSE)) | K9: =+IF(C9="","",VLOOKUP(C9,UBIGEO,3,FALSE)) | O9: =+IF(C9="","",VLOOKUP(C9,UBIGEO,2,FALSE))
B10: 4 | G10: =+IF(C10="","",VLOOKUP(C10,UBIGEO,4,FALSE)) | K10: =+IF(C10="","",VLOOKUP(C10,UBIGEO,3,FALSE)) | O10: =+IF(C10="","",VLOOKUP(C10,UBIGEO,2,FALSE))
B11: 5 | G11: =+IF(C11="","",VLOOKUP(C11,UBIGEO,4,FALSE)) | K11: =+IF(C11="","",VLOOKUP(C11,UBIGEO,3,FALSE)) | O11: =+IF(C11="","",VLOOKUP(C11,UBIGEO,2,FALSE))
B12: Nota: Considerar el espacio geográfico donde se localiza la población afectada y el área donde se ubica el CIAI
B15: 2.02 Localización del área de influencia del proyecto
B17: N° | C17: Ubigeo | G17: Departamento | K17: Provincia | L17: Provincia | O17: Distrito | S17: Localidad/Centro poblado
B18: 1 | G18: =+IF(C18="","",VLOOKUP(C18,UBIGEO,4,FALSE)) | K18: =+IF(C18="","",VLOOKUP(C18,UBIGEO,3,FALSE)) | O18: =+IF(C18="","",VLOOKUP(C18,UBIGEO,2,FALSE))
B19: 2 | G19: =+IF(C19="","",VLOOKUP(C19,UBIGEO,4,FALSE)) | K19: =+IF(C19="","",VLOOKUP(C19,UBIGEO,3,FALSE)) | O19: =+IF(C19="","",VLOOKUP(C19,UBIGEO,2,FALSE))
B20: 3 | G20: =+IF(C20="","",VLOOKUP(C20,UBIGEO,4,FALSE)) | K20: =+IF(C20="","",VLOOKUP(C20,UBIGEO,3,FALSE)) | O20: =+IF(C20="","",VLOOKUP(C20,UBIGEO,2,FALSE))
B21: 4 | G21: =+IF(C21="","",VLOOKUP(C21,UBIGEO,4,FALSE)) | K21: =+IF(C21="","",VLOOKUP(C21,UBIGEO,3,FALSE)) | O21: =+IF(C21="","",VLOOKUP(C21,UBIGEO,2,FALSE))
B22: 5 | G22: =+IF(C22="","",VLOOKUP(C22,UBIGEO,4,FALSE)) | K22: =+IF(C22="","",VLOOKUP(C22,UBIGEO,3,FALSE)) | O22: =+IF(C22="","",VLOOKUP(C22,UBIGEO,2,FALSE))
B23: Nota: Considerar el espacio geográfico donde se ubica la población afectada
B26: 2.03 Macro y micro localización del área de estudio
R28: =+"Leyenda Mapa de macrolocalización del CIAI de la localidad/centro poblado de "&S7&", del distrito de "&O7&", provincia de "&K7&", departamento de "&G7 -> Leyenda Mapa de macrolocalización del CIAI de la localidad/centro poblado de , del distrito de , provincia de , departamento de
B29: Nota: Para la macrolocalización, puede utilizar la fuente: | J29: https://estadist.inei.gob.pe/map
J30: https://www.cunamas.gob.pe/inicio/cobertura-de-servicios/
R32: =+"Leyenda Mapa de microlocalización del CIAI de la localidad/centro poblado de "&S7&", del distrito de "&O7&", provincia de "&K7&", departamento de "&G7 -> Leyenda Mapa de microlocalización del CIAI de la localidad/centro poblado de , del distrito de , provincia de , departamento de
B33: Fuente de información:
B34: Nota: Para la microlocalización, puede utilizar las fuentes: | J34: https://earth.google.com/web/
J35: https://www.cunamas.gob.pe/inicio/cobertura-de-servicios/
B37: 2.04 Análisis de las características del distrito donde se ubica o ubicará el CIAI
B39: A. Datos generales del distrito
B40: Altitud | E40: Temperatura media anual | I40: Humedad | L40: Precipitación media anual | O40: Coordenadas geográficas en decimales Latitud y Longitud.
B43: Fuente: | E43: https://www.senamhi.gob.pe/?&p=estaciones
B45: B. Características de: i) accesibilidad al distrito; ii) condiciones de pobreza; y, iii) principales características sociales y económicas
B46: Accesibilidad
B48: Condiciones de pobreza
B50: Principales características sociales y económicas
B53: C. Acceso a servicios públicos en el distrito
B54: Servicio público | H54: Porcentaje de viviendas con acceso | L54: Año de información | O54: Fuente de información (incluir enlace)
B55: Abastecimiento de agua por red pública dentro de la vivienda
B56: Servicio higiénico conectado a red pública de desagüe dentro de la vivienda
B57: Cuenta con alumbrado eléctrico conectado a una red pública
B58: Cuenta con servicio de internet
B59: Fuente: | H59: https://censos2017.inei.gob.pe/redatam/
B61: 2.05 Identificar los peligros que pueden ocurrir en el área de estudio
B63: Peligros | G63: ¿Existen antecedentes de ocurrencia en el área de estudio? | O63: ¿Existe información que indique futuros cambios en las características del peligro o los nuevos peligros?
G64: Sí / No | H64: Características (Intensidad, frecuencia, área de impacto, otros) | O64: Sí/No | P64: Características de los cambios o los nuevos peligros
B66: Inundaciones
B67: Movimientos en masa
B68: Lluvias intensas
B69: Helada
B70: Nevadas
B71: Friaje
B72: Sismos
B73: Sequías
B74: Vulcanismo
B75: Tsunamis
B76: Incendios forestales
B77: Erosión
... B81: Otros
B82: Fuente | G82: https://sigrid.cenepred.gob.pe/sigridv3/

Sheet Unidad Productora
B2: SECCIÓN N°03: DIAGNÓSTICO DE LA UNIDAD PRODUCTORA
B4: LA UNIDAD PRODUCTORA DE BIENES Y SERVICIOS
B7: 3.01 Nombre de la Unidad Productora:
B12: 3.02 Código de identificación del CIAI (Local ID) y tipo de CIAI
C14: Código de CIAI
B17: 3.03 Localización geográfica de la Unidad Productora
B19: N° | C19: UBIGEO | E19: Departamento | H19: Provincia | J19: Distrito | L19: Localidad / Centro poblado | N19: Coordenadas geográficas en decimales Latitud y Longitud.
B20: 1 | E20: =+IF(C20="","",VLOOKUP(C20,UBIGEO,4,FALSE)) | H20: =+IF(C20="","",VLOOKUP(C20,UBIGEO,3,FALSE)) | J20: =+IF(C20="","",VLOOKUP(C20,UBIGEO,2,FALSE))
B21: Nota: Para buscar las coordenadas geográficas, puede utilizar la fuente: | L21: https://www.google.com/maps
B24: 3.04 Diagnóstico de procesos de la Unidad Productora
B26: N° | C26: Caracterización de los procesos de producción del CIAI
C27: Servicio y sus procesos de producción | F27: Descripción ¿En qué consiste el proceso? | I27: Situación actual
B28: 1 | C28: Servicio de cuidado diurno | D28: Aprendizaje Infantil: Cuidado y Juego | F28: Consiste en fortalecer las habilidades sensoriales, motrices, comunicativas, cognitivas y socioemocionales de las niñas y los niños, que les permite el desarrollo de su identidad, autonomía, lenguaje, pensamiento y adaptación al medio, protegiéndoles de los posibles efectos de entornos adversos a su desarrollo. | R28: Anexo: informe técnico de la situación actual - contenido mínimo
B29: 2 | D29: Cuidado de la salud infantil en el CIAI | F29: Consiste en brindar cuidados a las niñas/niños en el CIAI como el lavado de manos, la higiene bucal, el uso y consumo de agua segura, el suministro de suplementos con hierro, la lactancia materna, como estrategias de prevención de la enfermedad y promoción de la salud. Asimismo, fortalece en las niñas y los niños la autonomía como en el control de esfínteres, descanso y sueño, cambio de ropa, orden del ambiente, entre otros, según el desarrollo y la edad de la niña y el niño.
B30: 3 | D30: Atención alimentaria y nutricional | F30: Consiste en atender las necesidades básicas de alimentación y nutrición mediante la dotación de una alimentación balanceada, saludable e inocua, de acuerdo a sus necesidades nutricionales según grupo etario de las niñas y los niños, que contribuyen con un adecuado estado nutricional para favorecer su óptimo crecimiento y desarrollo.
B31: 4 | D31: Fortalecimiento de Prácticas de cuidado saludable y aprendizaje en la familia usuaria | F31: Consiste en fortalecer las prácticas de cuidado saludable y aprendizaje (interacción, juego y comunicación) de la madre, padre u otro/a cuidador/a principal que permita dar una respuesta flexible, adecuada y pertinente de acuerdo a las necesidades e intereses de las niñas y los niños, a fin de favorecer su desarrollo integral. En las actividades se promueve la participación de uno o más miembros de la familia se encargan o son responsables del cuidado de la niña o el niño.
B32: Nota: Incluir informe de situación actual de las condiciones en las que se brinda el servicio
B35: 3.05 Diagnóstico de los activos de la UP
B38: Servicio y procesos de producción | D38: Tipo de Factor productivo | E38: Activos estratégicos | G38: Cumple con los estándares de calidad del PNCM | J38: Estado Situacional
G39: Norma técnica | I39: Sí / No
B41: Servicio de cuidado diurno: Procesos: 1. Aprendizaje Infantil 2. Cuidado y JuegoCuidado de la salud infantil en el CIAI 3. Atención alimentaria y nutricional 4. Fortalecimiento de Prácticas de cuidado saludable y aprendizaje en la familia usuaria | D41: Infraestructura | E41: Sala de cuidado diurno
E42: Sala de usos múltiples
E43: Ambiente de recreación activa
E44: Ambiente de servicios generales
E45: Ambiente de preparación y expendio de alimentos
E46: Almacén
E47: Cerco perimétrico
E48: Muro de contención
D49: Mobiliario | E49: Mobiliario de sala de cuidado diurno
E50: Mobiliario de ambiente de preparación y expendio de alimentos- Cuna Más
D51: Equipo | E51: Equipo de ambiente de preparación y expendio de alimentos - Cuna Más
B54: 3.06 Condiciones técnicas del local del CIAI
B56: A. Condiciones técnicas del local
B58: Condiciones actuales del entorno del CIAI
B60: ¿El CIAI está alejado de agentes contaminantes o peligros que no puedan ser mitigados? | J60: =+IF(I60="","",IF(I60="No","EL CIAI no cumple con esta condición técnica del Local, en relación a su entorno","")) | T60: EL CIAI no cumple con esta condición técnica del Local, en relación a su entorno
B62: ¿El CIAI está a una distancia no menor de 50 metros de estaciones de expendio de combustible? | J62: =+IF(I62="","",IF(I62="No","EL CIAI no cumple con esta condición técnica del Local, en relación a su entorno",""))
B64: ¿El CIAI está a una distancia no menor a 25 metros de una línea de alta tensión eléctrica? | J64: =+IF(I64="","",IF(I64="No","EL CIAI no cumple con esta condición técnica del Local, en relación a su entorno",""))
B66: ¿El CIAI es colindante con hospitales, centros médicos, centros de atención de salud, o similares, de categoría I-3, categoría I-4, categoría II o categoría III? | J66: =+IF(I66="","",IF(I66="Sí","EL CIAI no cumple con esta condición técnica del Local, en relación a su entorno",""))
B68: ¿Las salas del CIAI se ubican en el primer piso? | J68: =+IF(I68="","",IF(I68="No","EL CIAI no cumple con esta condición técnica del Local, en relación a su entorno",""))
B70: ¿Las puertas de ingreso y salida del CIAI están orientados directamente a una vía de alto tránsito vehicular? | J70: =+IF(I70="","",IF(I70="Sí","EL CIAI no cumple con esta condición técnica del Local, en relación a su entorno",""))
B72: Condiciones del CIAI
B74: Abastecimiento de Agua: El CIAI cuenta con conexión a una red pública | J74: =+IF(I74="","",IF(I74="No","EL CIAI no cumple con esta condición técnica del Local, en relación a su entorno",""))
B76: Desagüe: El CIAI cuenta con conexión a una red pública de alcantarillado | J76: =+IF(I76="","",IF(I76="No","EL CIAI no cumple con esta condición técnica del Local, en relación a su entorno",""))
B78: Energía eléctrica: El CIAI cuenta con conexión a la red pública de abastecimiento de energía eléctrica. | J78: =+IF(I78="","",IF(I78="No","EL CIAI no cumple con esta condición técnica del Local, en relación a su entorno",""))
B80: B. Situación actual del saneamiento físico legal del local
B83: Titularidad del local donde funciona el CIAI
B85: Situación actual del saneamiento físico legal o arreglo institucional | J85: =+IF(G85="Otra","Precisar",0) -> 0
B88: 3.07 Detallar las prácticas de operación y mantenimiento del CIAI, en la situación actual
B90: a. Personal
B91: Detalle | F91: Costos anual | I91: Descripción de las prácticas de operación, en la situación sin proyecto
F92: Cantidad | G92: Costo | H92: Total
B94: · Actores comunales: | H94: =SUM(H95:H104) -> 0
B95: o Madre cuidadora | H95: =+G95*F95 -> 0
B96: o Madre guía | H96: =+G96*F96 -> 0
B97: o Guía de Familia | H97: =+G97*F97 -> 0
B98: o Socia de cocina | H98: =+G98*F98 -> 0
B99: o Repartidor | H99: =+G99*F99 -> 0
B100: o Apoyo de Limpieza y Vigilancia | H100: =+G100*F100 -> 0
B101: · Equipo técnico profesional del PNCM: | H101: =+G101*F101 -> 0
B102: o Acompañantes técnicos (AT) | H102: =+G102*F102 -> 0
B103: o Especialistas integrales | H103: =+G103*F103 -> 0
B104: o Especialistas en nutrición | H104: =+G104*F104 -> 0
B106: b. Servicios y mantenimiento
B107: Detalle | F107: Costos anual | I107: Descripción de las condiciones del mantenimiento y los servicios del CIAI, en la situación sin proyecto
F108: Cantidad | G108: Costo | H108: Total
B110: · Servicios | H110: =SUM(H111:H115) -> 0
B111: o Agua y alcantarillado | H111: =+G111*F111 -> 0
B112: o Energía eléctirca | H112: =+G112*F112 -> 0
B113: o Internet | H113: =+G113*F113 -> 0
B114: o Seguridad | H114: =+G114*F114 -> 0
B115: o Mantenimiento | H115: =+G115*F115 -> 0
B117: 3.08 Evolución del nivel de producción de servicio de cuidado diurno provisto en el CIAI
B119: Servicios | E119: Unidad de Medida | F119: Año -5 | G119: Año -4 | H119: Año -3 | I119: Año -2 | J119: Año -1
B121: Servicio de cuidado diurno | E121: Niñas y niños
B123: 3.09 Estimar la exposición de la UP frente a los peligros identificados en el diagnóstico del área de estudio
B125: Peligros | G125: ¿Cuál es el nivel de exposición del CIAI al peligro? | H125: ¿Cuál es el nivel de fragilidad del CIAI ante la ocurrencia del peligro? | I125: ¿Se cuenta con un plan de contingencia ante la interrupción o alteración del servicio ocasionado por el peligro?
B128: =+IF(Territorio!G66="Sí",Territorio!B66,"")
B129: =+IF(Territorio!G67="Sí",Territorio!B67,"")
B130: =+IF(Territorio!G68="Sí",Territorio!B68,"")
B131: =+IF(Territorio!G69="Sí",Territorio!B69,"")
B132: =+IF(Territorio!G70="Sí",Territorio!B70,"")
B133: =+IF(Territorio!G71="Sí",Territorio!B71,"")
B134: =+IF(Territorio!G72="Sí",Territorio!B72,"")
B135: =+IF(Territorio!G73="Sí",Territorio!B73,"")
B136: =+IF(Territorio!G74="Sí",Territorio!B74,"")
B137: =+IF(Territorio!G75="Sí",Territorio!B75,"")
B138: =+IF(Territorio!G76="Sí",Territorio!B76,"")
B139: =+IF(Territorio!G77="Sí",Territorio!B77,"")
... B143: =+IF(Territorio!G81="Sí",Territorio!B81,"")

Sheet Involucrados
B2: SECCIÓN N°04: DIAGNÓSTICO DE LOS INVOLUCRADOS
B4: 4.01 Descripción de la población afectada
B6: Tipo de población | H6: Unidad de medida | I6: Cantidad | J6: %
B8: =+Brecha!B15 -> Población Total | D8: Es la población total del área de influencia definida en el diagnóstico. Se debe considerar la información de la población de los distritos identificados en el punto Localización del área de influencia del proyecto. | H8: Persona | J8: Población del distrito de San Sebastián, al año 2023. Fuente: INEI
B9: =+Brecha!B16 -> Población de Referencia | D9: Es la proporción de la población total, vinculada con el objetivo central del proyecto de inversión, es decir, que está dentro del grupo etario (de 6 a 36 meses) que podría recibir el Servicio de Cuidado Diurno, que brinda el PNCM. Para su estimación, se considera la población de dicho rango de edad, de la población total. | H9: Niños y niñas | J9: =+IF(I8>0,I9/I8,"") | K9: de la población total
B10: =+Brecha!B17 -> Población Demandante Potencial | D10: Es el segmento de la población de referencia, que cumple con los criterios de focalización que utiliza el PNCM. | H10: Niños y niñas | J10: =+IF(I9>0,I10/I9,"") | K10: de la población de referencia
B11: =+Brecha!B18 -> Población Demandante Efectiva | D11: Es el segmento de la población demandante potencial, que busca atención del SCD en un CIAI y accede de forma inadecuada o no accede al servicio, es decir, que es afectada por el problema central. | H11: Niños y niñas | J11: =+IF(I10>0,I11/I10,"") | K11: de la población demandante potencial
B12: =+Brecha!B19 -> Población Objetivo | D12: Es aquella parte de la población demandante efectiva que el proyecto está en condiciones de atender de forma integral en un CIAI, considerando la política de focalización del Sector, la definición de la meta correspondiente o alguna restricción que imposibilite la atención del total de la población demandante potencial. La población objetivo es determinada por el PNCM | H12: Niños y niñas | J12: =+IF(I11>0,I12/I11,"") | K12: de la población demandante efectiva
B13: Tasa de crecimiento de la población del área de influencia | H13: Tasa
B14: Importante: recoger información en estudio de campo
B17: 4.02 Caracterización de la población afectada
B19: Niños y niñas que comprenden la población demandante potencial
B20: Variables /indicadores | E20: Categorías | G20: Número de niños | H20: Número de niñas | I20: % respecto a la población demandante efectiva | J20: Fuente
B22: Edad | E22: de 6 a 12 meses | I22: =IF($I$11>0,SUM(G22:H22)/$I$11,"")
E23: de 13 a 24 meses | I23: =IF($I$11>0,SUM(G23:H23)/$I$11,"")
E24: de 25 a 36 meses | I24: =IF($I$11>0,SUM(G24:H24)/$I$11,"")
B25: Género | I25: =IF($I$11>0,SUM(G25:H25)/$I$11,"")
B26: Niños y niñas con desnutrición | E26: Cantidad de niños y niñas | I26: =IF($I$11>0,SUM(G26:H26)/$I$11,"")
B27: Niños y niñas con anemia | E27: Cantidad de niños y niñas | I27: =IF($I$11>0,SUM(G27:H27)/$I$11,"")
B28: Niños y niñas que acceden a Servicio de Cuidado Diurno en el CIAI | E28: Cantidad de niños y niñas | I28: =IF($I$11>0,SUM(G28:H28)/$I$11,"")
B29: Niños y niñas que acceden al Servicio Alimentario en el CIAI | E29: Cantidad de niños y niñas | I29: =IF($I$11>0,SUM(G29:H29)/$I$11,"")
B30: Niños y niñas con adecuado nivel de desarrollo cognitivo, en base a su edad | E30: Cantidad de niños y niñas | I30: =IF($I$11>0,SUM(G30:H30)/$I$11,"")
B31: Niños y niñas que cumplen con su control CRED | E31: Cantidad de niños y niñas | I31: =IF($I$11>0,SUM(G31:H31)/$I$11,"")
B34: 4.03 Matriz de involucrados
B36: Grupos involucrados | D36: Posición (Cooperante, Beneficiario, Oponente, Perjudicado) | E36: Situación negativa percibida | H36: Intereses o expectativas | K36: Estrategias del Proyecto de Inversión | N36: Acuerdos y compromisos

Sheet Problema-Objetivo
B2: SECCIÓN N° 05: PROBLEMA/OBJETIVO
B4: 5.01 Definición del problema, sus causas y efectos
B6: Descripción del problema central | F6: Indicador | J6: Descripción del indicador | M6: UM | N6: Valor
B8: =+IF('Datos Generales'!B44="","",VLOOKUP('Datos Generales'!B44:D44,Listas!C17:D21,2,FALSE)) | F8: =+IF(B8="","",VLOOKUP(B8,Listas!D17:N21,11,FALSE)) | J8: =+IF(B8="","",VLOOKUP(F8,Listas!N17:O21,2,FALSE)) | M8: CIAI | N8: =+'Datos Generales'!T53 -> 0
B10: Causas Directas (CD) | F10: Causas indirectas (CI) | J10: Evidencias
B17: Efectos Directos (ED) | F17: Sustento (evidencias) | J17: Sustento (evidencias)
B19: Efecto directo 1: Menor participación en experiencias de aprendizaje infantil de niñas y niños de 6 a 36 meses | F19: Efecto indirecto 1: Inadecuado desarrollo cognitivo de niñas y niños de 6 a 36 meses
B22: Efecto directo 2: Menor acceso de niñas y niños de 6 a 36 meses, a raciones alimentarias y suplemento con hierro | F22: Efecto indirecto 2: Ingesta inadecuada de nutrientes por parte de niñas y niños de 6 a 36 meses
B25: Efecto directo 3: Niñas y niños de 6 a 36 meses reciben insuficiente seguimiento al control CRED
B29: 5.02 Definición de los objetivos del proyecto
B31: Descripción del objetivo central | F31: Indicador* | J31: Descripción del indicador* | M31: UM* | N31: Valor*
B33: =+IF('Problema-Objetivo'!B8="","",VLOOKUP('Problema-Objetivo'!B8,Problematica,7,FALSE)) | F33: =+'Problema-Objetivo'!F8 | J33: =+J8 | M33: =+M8 -> CIAI | N33: =+'Datos Generales'!M55 -> 0
B34: * Esta información proviene de la información registrada en la tabla 1.04
B36: Medios fundamentales
B38: N° | C38: Medios fundamentales (componentes) | G38: Acciones
B40: 1 | C40: =+IF('Problema-Objetivo'!F12="","",VLOOKUP('Problema-Objetivo'!F12,Listas!$H$17:$L$24,5,FALSE))
B44: 2 | C44: =+IF('Problema-Objetivo'!F13="","",VLOOKUP('Problema-Objetivo'!F13,Listas!$H$17:$L$24,5,FALSE))
B45: 3 | C45: =+IF('Problema-Objetivo'!F14="","",VLOOKUP('Problema-Objetivo'!F14,Listas!$H$17:$L$24,5,FALSE))
B46: 4 | C46: =+IF('Problema-Objetivo'!F15="","",VLOOKUP('Problema-Objetivo'!F15,Listas!$H$17:$L$24,5,FALSE))
B50: Fines directos (FD) | F50: Fines Indirectos (FI)
B52: Fin directo 1: Mayor participación en experiencias de aprendizaje infantil de niñas y niños de 6 a 36 meses | F52: Fin indirecto 1: Adecuado desarrollo cognitivo de niñas y niños de 6 a 36 meses
B55: Fin directo 2: Mayor acceso de niñas y niños de 6 a 36 meses, a raciones alimentarias y suplemento con hierro | F55: Fin indirecto 2: Ingesta adecuada de nutrientes por parte de niñas y niños de 6 a 36 meses
B58: Fin directo 3: Niñas y niños de 6 a 36 meses reciben suficiente seguimiento al control CRED
B63: 5.03 Descripción de la alternativa de solución al problema
B65: Alternativa de solución | F65: =+G40&", "&G41&", "&G42&", "&G43&", "&G44&", "&G45&", "&G46&", "&G47 -> , , , , , , ,

Sheet Horizonte
B2: SECCIÓN N° 06: HORIZONTE DE EVALUACIÓN
B4: 6.01 Horizonte de evaluación
I6: Fecha de inicio | K6: Fecha de finalización
C8: Fecha prevista para declarar viabilidad del PI
L9: =+TODAY() -> 45531
C10: Fechas previstas para el proceso de contratación para elaboración del Expediente Técnico
L11: =+TODAY() -> 45531
C12: Fechas previstas para inicio de elaboración y aprobación del Expediente Técnico
L13: =+TODAY() -> 45531
C14: Fechas previstas para el proceso de contratación para ejecución física del proyecto
C16: Fechas previstas para ejecución física
C18: Fecha prevista para la fase de Funcionamiento
C21: Total de horizonte de evaluación (años) | I21: =+I23+I25 -> 10
G23: Fase de Ejecución | I23: =+(K16-MIN(I10,I12,I14,I16))/365 -> 0
G25: Fase de Funcionamiento | I25: 10
H29: =+I18+3650 -> 3650
C31: Contratación de Expediente Técnico | E31: =+I10 -> 0 | F31: =+K10 -> 0 | G31: =+F31-E31 -> 0
C32: Expediente técnico del PI de CIAI | E32: =+I12 -> 0 | F32: =+K12 -> 0 | G32: =+F32-E32 -> 0
C33: Contratación de ejecución física | E33: =+I14 -> 0 | F33: =+K14 -> 0 | G33: =+F33-E33 -> 0
C34: Ejecución física del PI del CIAI | E34: =+I16 -> 0 | F34: =+K16 -> 0 | G34: =+F34-E34 -> 0
C35: Operación del CIAI | E35: =+I18 -> 0 | F35: =+H29 -> 3650 | G35: =+F35-E35 -> 3650

Sheet Brecha
B2: SECCIÓN N°07: ANÁLISIS DE MERCADO
B4: 7.01 Definición y caracterización del Servicio de Cuidado Diurno
B6: El Servicio de Cuidado Diuirno consiste en brindar atención integral a niños entre 6 y 36 meses de edad, que viven en zonas de pobreza y pobreza extrema, y requieren de atención en sus necesidades básicas de salud, nutrición, seguridad, protección, afecto, descanso, juego, aprendizaje y desarrollo de habilidades. Comprende: - Aprendizaje Infantil: Cuidado y Juego. - Promoción de prácticas en el cuidado de la salud en la niña o niño. - Atención alimentaria y nutricional. - Fortalecimiento de prácticas de cuidado saludable y aprendizaje en la familia usuaria. La unidad de medida del servicio es: niños y niñas atendidos en el CIAI
B9: 7.02 Análisis y proyección de la demanda del servicio
B11: Tipo de población | D11: Año
D12: Año 0 | E12: Año 1 | F12: Año 2 | G12: Año 3 | H12: Año 4 | I12: Año 5 | J12: Año 6 | K12: Año 7 | L12: Año 8 | M12: Año 9 | N12: Año 10
D13: =+IF(Horizonte!K8>0,Horizonte!K8,"") | E13: =+IF(Horizonte!$K$8>0,D13+365,"") | F13: =+IF(Horizonte!$K$8>0,E13+365,"") | G13: =+IF(Horizonte!$K$8>0,F13+365,"") | H13: =+IF(Horizonte!$K$8>0,G13+365,"") | I13: =+IF(Horizonte!$K$8>0,H13+365,"") | J13: =+IF(Horizonte!$K$8>0,I13+365,"") | K13: =+IF(Horizonte!$K$8>0,J13+365,"") | L13: =+IF(Horizonte!$K$8>0,K13+365,"") | ... N13: =+IF(Horizonte!$K$8>0,M13+365,"")
B15: Población Total | D15: =+Involucrados!I8 -> 0 | E15: =+D15*(1+Involucrados!$I$13) -> 0 | F15: =+E15*(1+Involucrados!$I$13) -> 0 | G15: =+F15*(1+Involucrados!$I$13) -> 0 | H15: =+G15*(1+Involucrados!$I$13) -> 0 | I15: =+H15*(1+Involucrados!$I$13) -> 0 | J15: =+I15*(1+Involucrados!$I$13) -> 0 | K15: =+J15*(1+Involucrados!$I$13) -> 0 | L15: =+K15*(1+Involucrados!$I$13) -> 0 | ... N15: =+M15*(1+Involucrados!$I$13) -> 0
B16: Población de Referencia | D16: =+Involucrados!I9 -> 0 | E16: =+D16*(1+Involucrados!$I$13) -> 0 | F16: =+E16*(1+Involucrados!$I$13) -> 0 | G16: =+F16*(1+Involucrados!$I$13) -> 0 | H16: =+G16*(1+Involucrados!$I$13) -> 0 | I16: =+H16*(1+Involucrados!$I$13) -> 0 | J16: =+I16*(1+Involucrados!$I$13) -> 0 | K16: =+J16*(1+Involucrados!$I$13) -> 0 | L16: =+K16*(1+Involucrados!$I$13) -> 0 | ... N16: =+M16*(1+Involucrados!$I$13) -> 0
B17: Población Demandante Potencial | D17: =+Involucrados!I10 -> 0 | E17: =+D17*(1+Involucrados!$I$13) -> 0 | F17: =+E17*(1+Involucrados!$I$13) -> 0 | G17: =+F17*(1+Involucrados!$I$13) -> 0 | H17: =+G17*(1+Involucrados!$I$13) -> 0 | I17: =+H17*(1+Involucrados!$I$13) -> 0 | J17: =+I17*(1+Involucrados!$I$13) -> 0 | K17: =+J17*(1+Involucrados!$I$13) -> 0 | L17: =+K17*(1+Involucrados!$I$13) -> 0 | ... N17: =+M17*(1+Involucrados!$I$13) -> 0
B18: Población Demandante Efectiva | D18: =+Involucrados!I11 -> 0 | E18: =+D18*(1+Involucrados!$I$13) -> 0 | F18: =+E18*(1+Involucrados!$I$13) -> 0 | G18: =+F18*(1+Involucrados!$I$13) -> 0 | H18: =+G18*(1+Involucrados!$I$13) -> 0 | I18: =+H18*(1+Involucrados!$I$13) -> 0 | J18: =+I18*(1+Involucrados!$I$13) -> 0 | K18: =+J18*(1+Involucrados!$I$13) -> 0 | L18: =+K18*(1+Involucrados!$I$13) -> 0 | ... N18: =+M18*(1+Involucrados!$I$13) -> 0
B19: Población Objetivo | D19: =+Involucrados!I12 -> 0 | E19: =+D19 -> 0 | F19: =+E19 -> 0 | G19: =+F19 -> 0 | H19: =+G19 -> 0 | I19: =+H19 -> 0 | J19: =+I19 -> 0 | K19: =+J19 -> 0 | L19: =+K19 -> 0 | ... N19: =+M19 -> 0
B21: Consideraciones para definir la demanda del servicio
B22: Población Total: es la población total del área de influencia definida en el diagnóstico. Población de Referencia: es la proporción de la población total, vinculada con el objetivo central del proyecto de inversión, es decir, que está dentro del grupo etario que podría recibir el Servicio de Cuidado Diurno. Población Demandante Potencial: es el segmento de la población de referencia, que es afectada por el problema central, que no accede al Servicio de Cuidado Diurno o accede de forma inadecuada. Población Demandante Efectiva: es el segmento de la población demandante potencial que cumple con los criterios de focalización definidos por el Sector para acceder al Servicio de Cuidado Diurno, en un CIAI. Población Objetivo: es aquella parte de la población demandante efectiva que el proyecto está en condiciones de atender de forma integral en un CIAI, considerando la política de focalización del Sector y la definición de la meta correspondiente. Es definida por el Programa Nacional Cuna Más.
B25: 7.03 Proyección de la demanda del Servicio de Cuidado Diurno
B27: Detalle | C27: Unidad de Medida | D27: =+D13 | E27: =+E13 | F27: =+F13 | G27: =+G13 | H27: =+H13 | I27: =+I13 | J27: =+J13 | K27: =+K13 | ... N27: =+N13
B29: =+B18 -> Población Demandante Efectiva | C29: Niños y niñas | D29: =+D18 -> 0 | E29: =+E18 -> 0 | F29: =+F18 -> 0 | G29: =+G18 -> 0 | H29: =+H18 -> 0 | I29: =+I18 -> 0 | J29: =+J18 -> 0 | K29: =+K18 -> 0 | ... N29: =+N18 -> 0
B30: =+B19 -> Población Objetivo | C30: Niños y niñas | D30: =+D19 -> 0 | E30: =+E19 -> 0 | F30: =+F19 -> 0 | G30: =+G19 -> 0 | H30: =+H19 -> 0 | I30: =+I19 -> 0 | J30: =+J19 -> 0 | K30: =+K19 -> 0 | ... N30: =+N19 -> 0
B31: Nivel de cobertura de la población demandante efectiva | D31: =+IF(D29>0,D30/D29,"") | E31: =+IF(E29>0,E30/E29,"") | F31: =+IF(F29>0,F30/F29,"") | G31: =+IF(G29>0,G30/G29,"") | H31: =+IF(H29>0,H30/H29,"") | I31: =+IF(I29>0,I30/I29,"") | J31: =+IF(J29>0,J30/J29,"") | K31: =+IF(K29>0,K30/K29,"") | ... N31: =+IF(N29>0,N30/N29,"")
B34: 7.04 Estimación de la oferta optimizada (sin proyecto)
B36: Condiciones para optimización de la oferta | G36: Capacidad actual del CIAI | H36: Acciones de optimización (solo en caso de que se pueda optimizar la oferta actual) | N36: Capacidad optimizada del CIAI
H37: Factor de producción a optimizar | J37: Acción para optimizar la oferta actual
B45: 7.05 Proyección de la oferta del Servicio de Cuidado Diurno
B47: Detalle | C47: Unidad de Medida | D47: =+D27 | E47: =+E27 | F47: =+F27 | G47: =+G27 | H47: =+H27 | I47: =+I27 | J47: =+J27 | K47: =+K27 | ... N47: =+N27
B49: Servicio de Cuidado Diurno | C49: Niños y niñas | D49: =+MAX(G39,N39) -> 0 | E49: =+D49 -> 0 | F49: =+E49 -> 0 | G49: =+F49 -> 0 | H49: =+G49 -> 0 | I49: =+H49 -> 0 | J49: =+I49 -> 0 | K49: =+J49 -> 0 | L49: =+K49 -> 0 | ... N49: =+M49 -> 0
B52: 7.06 Brecha del Servicio de Cuidado Diurno
B54: Detalle | C54: Unidad de Medida | D54: =+D47 | E54: =+E47 | F54: =+F47 | G54: =+G47 | H54: =+H47 | I54: =+I47 | J54: =+J47 | K54: =+K47 | ... N54: =+N47
B56: =+B29 -> Población Demandante Efectiva | C56: Niños y niñas | D56: =+D18 -> 0 | E56: =+E18 -> 0 | F56: =+F18 -> 0 | G56: =+G18 -> 0 | H56: =+H18 -> 0 | I56: =+I18 -> 0 | J56: =+J18 -> 0 | K56: =+K18 -> 0 | ... N56: =+N18 -> 0
B57: Oferta | C57: Niños y niñas | D57: =+D49 -> 0 | E57: =+E49 -> 0 | F57: =+F49 -> 0 | G57: =+G49 -> 0 | H57: =+H49 -> 0 | I57: =+I49 -> 0 | J57: =+J49 -> 0 | K57: =+K49 -> 0 | ... N57: =+N49 -> 0
B58: Brecha | C58: Niños y niñas | D58: =+D57-D56 -> 0 | E58: =+E57-E56 -> 0 | F58: =+F57-F56 -> 0 | G58: =+G57-G56 -> 0 | H58: =+H57-H56 -> 0 | I58: =+I57-I56 -> 0 | J58: =+J57-J56 -> 0 | K58: =+K57-K56 -> 0 | ... N58: =+N57-N56 -> 0

Sheet Análisis Técnico
B2: SECCIÓN N°08: ANÁLISIS TÉCNICO
B4: 8.01 ANÁLISIS DE TAMAÑO (¿Cuánto producir?)
B5: Factores condicionantes del tamaño del proyecto.
B7: Se considera como factor condicionante, para la determinación del tamaño del proyecto de inversión del CIAI, la definición de la meta prevista por el PNCM.
B9: N° | C9: Factor condicionante | F9: Unidad de Medida | G9: Valor | H9: Tamaño (tipo) de CIAI, según factor condicionante | J9: Área mínima requerida del CIAI, no incluye Servicio Alimentario (m2) 1/ | K9: Área mínima requerida del CIAI, incluye Servicio Alimentario (m2) 1/
B11: 1 | C11: Meta prevista por el PNCM, para el CIAI. | F11: Niños y niñas | G11: =+Brecha!D19 -> 0 | H11: =+IF(G11>0,VLOOKUP(G11,Infraestructura!AS42:AT49,2,TRUE),"") | J11: =+IF(G11>0,VLOOKUP(H11,Infraestructura!AT42:AV49,3,FALSE),"") | K11: =+IF(G11>0,J11+Infraestructura!BE12,"") | L11: =+VLOOKUP(H11,Infraestructura!AW42:AX49,2,FALSE)+3 -> #N/A
B12: Tamaño de CIAI a implementar con el proyecto de inversión | H12: =+H11
B13: 1/: Según directiva de infraestructura del PNCM
B15: 8.02 ANÁLISIS DE LOCALIZACIÓN (¿Dónde producir?)
B17: Factores condicionantes de la localización del proyecto.
B18: La localización del CIAI debe responder a las condiciones técnicas del entorno del CIAI y sus características propias, precisadas en la directiva de infraestructura del PNCM, las que se presentan en el literal A de este numeral:
B20: A. Verificación del cumplimiento de las condiciones técnicas del local
B21: =+'Unidad Productora'!B59 -> 0 | I21: =+'Unidad Productora'!B73 -> 0
B23: Importante: El CIAI propuesto, para la situación con proyecto, debe cumplir todas las condiciones técnicas del local
B25: El CIAI está alejado de agentes contaminantes o peligros que no puedan ser mitigados | I25: Las puertas de ingreso y salida del CIAI están orientados directamente a una vía de alto tránsito vehicular
B27: El CIAI está a una distancia no menor de 50 metros de estaciones de expendio de combustible | I27: Abastecimiento de Agua: El CIAI cuenta o contará con conexión a una red pública
B29: El CIAI está a una distancia no menor a 25 metros de una línea de alta tensión eléctrica | I29: Desagüe: El CIAI cuenta o contará con conexión a una red pública de alcantarillado
B31: El CIAI es colindante con hospitales, centros médicos, centros de atención de salud, o similares, de categoría I-3, categoría I-4, categoría II o categoría III | I31: Energía eléctrica: El CIAI cuenta o contará con conexión a la red pública de abastecimiento de energía eléctrica.
B33: B. Situación del saneamiento físico legal del local, para la ejecución del proyecto
B37: Titularidad del local donde funciona el CIAI
B39: Situación del saneamiento físico legal o arreglo institucional, prevista para la implementación del proyecto | J39: =+IF(G39="Otra","Precisar. Solo en el caso del PNCM",0) -> 0
B41: C. Ubicación del CIAI
B43: N° | C43: Departamento | E43: Provincia | G43: Distrito | I43: Localidad/Centro poblado | K43: Coordenadas geográficas en decimales Latitud y Longitud.
B44: 1 | C44: =+'Unidad Productora'!E20 | E44: =+'Unidad Productora'!H20 | G44: =+'Unidad Productora'!J20 | I44: =+'Unidad Productora'!L20 -> 0 | K44: =+'Unidad Productora'!N20 -> 0
B47: 8.03 ANÁLISIS DE TECNOLOGÍA (¿Cómo producir?)
B49: Importante: En la Ficha Técnica, para el análisis técnico de la tecnología se utilizará ingeniería conceptual. (ver nota)
B51: Descripción del proceso de producción del servicio (con proyecto)
B53: Servicio | C53: Tipo de Factor productivo | E53: Activo del CIAI | G53: Descripción | L53: ¿Se incluye como parte del PI? | M53: Normativa aplicable (del PNCM o RNE, según corresponda)
B56: Servicio de Cuidado Diuirno | C56: Infraestructura | E56: Sala de cuidado diurno | G56: Espacio físico donde se brinda la atención integral a los niños (bebes, gateadores y caminantes), en este espacio se encuentran organizados las áreas de juego y cuidado.
E57: Sala de usos múltiples | G57: Espacio donde se realizan los juegos de los niños y actividades lúdicas, este espacio también es utilizado como comedor para la atención alimentaria de los niños .
E58: Ambiente de recreación activa | G58: Espacio exterior destinado al encuentro y recreación activa entre niñas y niños, cuidadoras, así como de familias usuarias, organizado y equipado para las actividades.
E59: Ambiente de servicios generales | G59: Espacios destinados a actividades de apoyo a las funciones que se realizan en el establecimiento, tales como: área para tanque séptico y pozo percolador, depósito de materiales, patio de servicio, cuarto de tableros, caseta de vigilancia, área de guardado para coches para bebes, espacio de cambio de pañales).
E60: Ambiente de preparación y expendio de alimentos | G60: Espacio físico utilizado para la preparación de raciones alimenticias de los usuarios.
E61: Almacén | G61: Espacio físico destinado para el acopio de los insumos alimenticios dentro de la cadena de suministros.
E62: Cerco perimétrico | G62: Activo para la protección de la unidad productora. Elemento fijo y seguro que rodea y delimita la propiedad o sus sectores. Cuenta con espacios de acceso al interior del mismo.
E63: Muro de contención | G63: Activo para la protección de la unidad productora. Estructura rígida destinada a contener masas de suelo u otros materiales sueltos proporcionando estabilidad.
E64: Otros ambientes complementarios
C65: Equipo | E65: Equipo de ambiente de preparación y expendio de alimentos - Cuna Más | G65: Equipo utilizado en el servicio de atención alimentaria: cocina industrial, campana extractora, licuadora semi industrial, refrigeradora, extractor de aire. Solo su adquisición en conjunto significa una inversión en el marco del SNPMGI.
C66: Mobiliario | E66: =+'Unidad Productora'!E49:F49 -> Mobiliario de sala de cuidado diurno | G66: Mobiliario utilizado para la sala de cuidado diurno: cambiadores de pañales, cunas, esquinero-mueble-repisa, estantes, mesas rectangulares, porta colchonetas, sillas para lactancia, estantes aéreos Solo su adquisición en conjunto significa una inversión en el marco del SNPMGI.
E67: =+'Unidad Productora'!E50:F50 -> Mobiliario de ambiente de preparación y expendio de alimentos- Cuna Más | G67: Mobiliario utilizado en la preparación y expendio de alimentos: mesas auxiliares de acero, mesa de trabajo de acero, estante de acero, estante para cestos. Solo su adquisición en conjunto significa una inversión en el marco del SNPMGI.
C68: Intangibles | E68: Recursos humanos | G68: Actores comunales capacitados para la co-gestión en la fase de funcionamiento y prestación del Servicio de Cuidado Diurno en el CIAI
B70: 8.04 IDENTIFICACIÓN DE MEDIDAS DE REDUCCIÓN DEL RIESGO DE DESASTRES
B72: Descripción de las medidas de reducción del riesgo de desastres, en función al análisis de la exposición y fragilidad del CIAI
B74: Peligros | D74: Exposición | E74: Fragilidad | F74: Resiliencia | G74: Descripción de las medidas de reducción del riesgo de desastres, en función al resultado del análisis de la exposición y fragilidad del CIAI (proponer medidas en los casos que el resultado sea "Alto" o "Medio")
B76: =+'Unidad Productora'!B128:F128 | D76: =+'Unidad Productora'!G128 -> 0 | E76: =+'Unidad Productora'!H128 -> 0 | F76: =+IF('Unidad Productora'!I128="","",IF('Unidad Productora'!I128="No","Alto","Bajo"))
B77: =+'Unidad Productora'!B129:F129 | D77: =+'Unidad Productora'!G129 -> 0 | E77: =+'Unidad Productora'!H129 -> 0 | F77: =+IF('Unidad Productora'!I129="","",IF('Unidad Productora'!I129="No","Alto","Bajo"))
B78: =+'Unidad Productora'!B130:F130 | D78: =+'Unidad Productora'!G130 -> 0 | E78: =+'Unidad Productora'!H130 -> 0 | F78: =+IF('Unidad Productora'!I130="","",IF('Unidad Productora'!I130="No","Alto","Bajo"))
B79: =+'Unidad Productora'!B131:F131 | D79: =+'Unidad Productora'!G131 -> 0 | E79: =+'Unidad Productora'!H131 -> 0 | F79: =+IF('Unidad Productora'!I131="","",IF('Unidad Productora'!I131="No","Alto","Bajo"))
B80: =+'Unidad Productora'!B132:F132 | D80: =+'Unidad Productora'!G132 -> 0 | E80: =+'Unidad Productora'!H132 -> 0 | F80: =+IF('Unidad Productora'!I132="","",IF('Unidad Productora'!I132="No","Alto","Bajo"))
B81: =+'Unidad Productora'!B133:F133 | D81: =+'Unidad Productora'!G133 -> 0 | E81: =+'Unidad Productora'!H133 -> 0 | F81: =+IF('Unidad Productora'!I133="","",IF('Unidad Productora'!I133="No","Alto","Bajo"))
B82: =+'Unidad Productora'!B134:F134 | D82: =+'Unidad Productora'!G134 -> 0 | E82: =+'Unidad Productora'!H134 -> 0 | F82: =+IF('Unidad Productora'!I134="","",IF('Unidad Productora'!I134="No","Alto","Bajo"))
B83: =+'Unidad Productora'!B135:F135 | D83: =+'Unidad Productora'!G135 -> 0 | E83: =+'Unidad Productora'!H135 -> 0 | F83: =+IF('Unidad Productora'!I135="","",IF('Unidad Productora'!I135="No","Alto","Bajo"))
B84: =+'Unidad Productora'!B136:F136 | D84: =+'Unidad Productora'!G136 -> 0 | E84: =+'Unidad Productora'!H136 -> 0 | F84: =+IF('Unidad Productora'!I136="","",IF('Unidad Productora'!I136="No","Alto","Bajo"))
B85: =+'Unidad Productora'!B137:F137 | D85: =+'Unidad Productora'!G137 -> 0 | E85: =+'Unidad Productora'!H137 -> 0 | F85: =+IF('Unidad Productora'!I137="","",IF('Unidad Productora'!I137="No","Alto","Bajo"))
B86: =+'Unidad Productora'!B138:F138 | D86: =+'Unidad Productora'!G138 -> 0 | E86: =+'Unidad Productora'!H138 -> 0 | F86: =+IF('Unidad Productora'!I138="","",IF('Unidad Productora'!I138="No","Alto","Bajo"))
B87: =+'Unidad Productora'!B139:F139 | D87: =+'Unidad Productora'!G139 -> 0 | E87: =+'Unidad Productora'!H139 -> 0 | F87: =+IF('Unidad Productora'!I139="","",IF('Unidad Productora'!I139="No","Alto","Bajo"))
... B91: =+'Unidad Productora'!B143:F143 | D91: =+'Unidad Productora'!G143 -> 0 | E91: =+'Unidad Productora'!H143 -> 0 | F91: =+IF('Unidad Productora'!I143="","",IF('Unidad Productora'!I143="No","Alto","Bajo"))
B93: 8.05 RESUMEN DE LAS ALTERNATIVAS TÉCNICAS
B95: Descripción de alternativas técnicas | D95: Alternativas técnicas
D96: Tamaño | F96: Localización | H96: Descripción de la tecnología
B98: Alternativa técnica 1 | D98: =+H12&", "&G11&" niños y niñas" -> , 0 niños y niñas | F98: =+I44&", Coordenadas: "&K44 -> 0, Coordenadas: 0
B99: Alternativa técnica 2 | D99: =+D98 -> , 0 niños y niñas | F99: =+F98 -> 0, Coordenadas: 0
B100: Alternativa técnica 3 | D100: =+D99 -> , 0 niños y niñas | F100: =+F99 -> 0, Coordenadas: 0
B103: 8.06 METAS FíSICAS DE LOS ACTIVOS QUE SE BUSCAN CREAR O INTERVENIR CON EL PROYECTO
B105: Componente 1 | D105: =+'Problema-Objetivo'!C40
B107: Servicio de Cuidado Diurno
B108: Acción sobre el activo | D108: Tipo de factor productivo | E108: Activos | J108: Área normativa mínima requerida por unidad física (m2) | K108: Unidad Física | M108: Dimensión física
K109: Unidad de medida | L109: Cantidad | M109: Unidad de medida | N109: Cantidad
D110: Infraestructura | E110: =+E56 -> Sala de cuidado diurno | J110: =+IF($H$11="","",VLOOKUP(E110,Infraestructura!$BI$3:$BS$11,$L$11,FALSE)) | K110: Sala | M110: m2
D111: Infraestructura | E111: =+E57 -> Sala de usos múltiples | J111: =+IF($H$11="","",VLOOKUP(E111,Infraestructura!$BI$3:$BS$11,$L$11,FALSE)) | K111: Sala | M111: m2
D112: Infraestructura | E112: =+E58 -> Ambiente de recreación activa | J112: =+IF($H$11="","",VLOOKUP(E112,Infraestructura!$BI$3:$BS$11,$L$11,FALSE)) | K112: Ambiente | M112: m2
D113: Infraestructura | E113: =+E59 -> Ambiente de servicios generales | J113: =+IF($H$11="","",VLOOKUP(E113,Infraestructura!$BI$3:$BS$11,$L$11,FALSE)) | K113: Ambiente | M113: m2
D114: Infraestructura | E114: =+E60 -> Ambiente de preparación y expendio de alimentos | J114: =+IF($H$11="","",VLOOKUP(E114,Infraestructura!$BI$3:$BS$11,$L$11,FALSE)) | K114: Ambiente | M114: m2
D115: Infraestructura | E115: =+E61 -> Almacén | J115: =+IF($H$11="","",VLOOKUP(E115,Infraestructura!$BI$3:$BS$11,$L$11,FALSE)) | K115: Almacén | M115: m2
D116: Infraestructura | E116: =+E62 -> Cerco perimétrico | K116: Unidad | M116: ml
D117: Infraestructura | E117: =+E63 -> Muro de contención | K117: Unidad | M117: ml o m3
D118: Infraestructura | E118: =+E64 -> Otros ambientes complementarios | J118: =+IF($H$11="","",VLOOKUP(E118,Infraestructura!$BI$3:$BS$11,$L$11,FALSE)) | K118: Unidad
B120: Componente 2 | D120: =+'Problema-Objetivo'!C44
B122: =+B108 -> Acción sobre el activo | D122: Tipo de factor productivo | E122: Activos | J122: Unidad Física
J123: Unidad de medida | L123: Cantidad
D124: Equipos | E124: =+E65 -> Equipo de ambiente de preparación y expendio de alimentos - Cuna Más | J124: Número de equipos
B127: Componente 3 | D127: =+'Problema-Objetivo'!C45
B129: =+B122 -> Acción sobre el activo | D129: Tipo de factor productivo | E129: Activos | J129: Unidad Física
J130: Unidad de medida | L130: Cantidad
D131: Mobiliario | E131: =+E66 -> Mobiliario de sala de cuidado diurno | J131: Número de mobiliario
D132: Mobiliario | E132: =+E67 -> Mobiliario de ambiente de preparación y expendio de alimentos- Cuna Más | J132: Número de mobiliario
B134: Componente 4 | D134: =+'Problema-Objetivo'!C46
B136: =+B129 -> Acción sobre el activo | D136: Tipo de factor productivo | E136: Activos | J136: Unidad Física
J137: Unidad de medida | L137: Cantidad
D138: Intangibles | E138: =+E68 -> Recursos humanos | J138: Número de eventos de capacitación
B140: Nota: De acuerdo a lo precisado en la Guía General para la Identificación, Formulación y Evaluación de Proyectos de Inversión (MEF, 2022), la Ingeniería Conceptual tiene por objetivo fundamental identificar la viabilidad técnica y económica de la/las alternativas técnicas del proyecto así como establecer las pautas para el desarrollo de las etapas posteriores de ingeniería básica y de detalle, razón por la cual comprende como paso previo el desarrollo de alternativas técnicas propias la visualización. Permite formular apreciaciones técnicas y económicas de carácter estratégico. En este nivel se establecen en términos globales los requerimientos del proyecto, para lo cual se estudia, de acuerdo con el tipo de bien o servicio a entregar, la capacidad a instalar, los procesos de producción del bien o servicio, los requerimientos de recursos en las fases de ejecución y funcionamiento. Se incluye una descripción de las instalaciones, diagramas distribución del espacio, diagrama de procesos básicos, de instalación de equipos, así como estudios preliminares de tamaño, localización y tecnología.

Sheet CostosAlt1
B2: SECCIÓN N°09: COSTOS DEL PROYECTO - ALTERNATIVA 1
B4: 9.01 Costo de ejecución física de las acciones
B6: Componente 1 | D6: =+'Problema-Objetivo'!C40
B8: Servicio de Cuidado Diurno
B9: Acción sobre el activo | D9: Tipo de factor productivo | E9: Activos | J9: Unidad Física | L9: Dimensión física | N9: Costo unitario | O9: Costo total
J10: Unidad de medida | K10: Cantidad | L10: Unidad de medida | M10: Cantidad
B11: =+'Análisis Técnico'!B110:C110 -> 0 | D11: =+'Análisis Técnico'!D110 -> Infraestructura | E11: =+'Análisis Técnico'!E110 -> Sala de cuidado diurno | F11: =+'Análisis Técnico'!F110 -> 0 | G11: =+'Análisis Técnico'!G110 -> 0 | H11: =+'Análisis Técnico'!H110 -> 0 | I11: =+'Análisis Técnico'!I110 -> 0 | J11: =+'Análisis Técnico'!K110 -> Sala | K11: =+'Análisis Técnico'!L110 -> 0 | L11: =+'Análisis Técnico'!M110 -> m2 | M11: =+'Análisis Técnico'!N110 -> 0 | O11: =+N11*M11 -> 0
B12: =+'Análisis Técnico'!B111:C111 -> 0 | D12: =+'Análisis Técnico'!D111 -> Infraestructura | E12: =+'Análisis Técnico'!E111 -> Sala de usos múltiples | F12: =+'Análisis Técnico'!F111 -> 0 | G12: =+'Análisis Técnico'!G111 -> 0 | H12: =+'Análisis Técnico'!H111 -> 0 | I12: =+'Análisis Técnico'!I111 -> 0 | J12: =+'Análisis Técnico'!K111 -> Sala | K12: =+'Análisis Técnico'!L111 -> 0 | L12: =+'Análisis Técnico'!M111 -> m2 | M12: =+'Análisis Técnico'!N111 -> 0 | O12: =+N12*M12 -> 0
B13: =+'Análisis Técnico'!B112:C112 -> 0 | D13: =+'Análisis Técnico'!D112 -> Infraestructura | E13: =+'Análisis Técnico'!E112 -> Ambiente de recreación activa | F13: =+'Análisis Técnico'!F112 -> 0 | G13: =+'Análisis Técnico'!G112 -> 0 | H13: =+'Análisis Técnico'!H112 -> 0 | I13: =+'Análisis Técnico'!I112 -> 0 | J13: =+'Análisis Técnico'!K112 -> Ambiente | K13: =+'Análisis Técnico'!L112 -> 0 | L13: =+'Análisis Técnico'!M112 -> m2 | M13: =+'Análisis Técnico'!N112 -> 0 | O13: =+N13*M13 -> 0
B14: =+'Análisis Técnico'!B113:C113 -> 0 | D14: =+'Análisis Técnico'!D113 -> Infraestructura | E14: =+'Análisis Técnico'!E113 -> Ambiente de servicios generales | F14: =+'Análisis Técnico'!F113 -> 0 | G14: =+'Análisis Técnico'!G113 -> 0 | H14: =+'Análisis Técnico'!H113 -> 0 | I14: =+'Análisis Técnico'!I113 -> 0 | J14: =+'Análisis Técnico'!K113 -> Ambiente | K14: =+'Análisis Técnico'!L113 -> 0 | L14: =+'Análisis Técnico'!M113 -> m2 | M14: =+'Análisis Técnico'!N113 -> 0 | O14: =+N14*M14 -> 0
B15: =+'Análisis Técnico'!B114:C114 -> 0 | D15: =+'Análisis Técnico'!D114 -> Infraestructura | E15: =+'Análisis Técnico'!E114 -> Ambiente de preparación y expendio de alimentos | F15: =+'Análisis Técnico'!F114 -> 0 | G15: =+'Análisis Técnico'!G114 -> 0 | H15: =+'Análisis Técnico'!H114 -> 0 | I15: =+'Análisis Técnico'!I114 -> 0 | J15: =+'Análisis Técnico'!K114 -> Ambiente | K15: =+'Análisis Técnico'!L114 -> 0 | L15: =+'Análisis Técnico'!M114 -> m2 | M15: =+'Análisis Técnico'!N114 -> 0 | O15: =+N15*M15 -> 0
B16: =+'Análisis Técnico'!B115:C115 -> 0 | D16: =+'Análisis Técnico'!D115 -> Infraestructura | E16: =+'Análisis Técnico'!E115 -> Almacén | F16: =+'Análisis Técnico'!F115 -> 0 | G16: =+'Análisis Técnico'!G115 -> 0 | H16: =+'Análisis Técnico'!H115 -> 0 | I16: =+'Análisis Técnico'!I115 -> 0 | J16: =+'Análisis Técnico'!K115 -> Almacén | K16: =+'Análisis Técnico'!L115 -> 0 | L16: =+'Análisis Técnico'!M115 -> m2 | M16: =+'Análisis Técnico'!N115 -> 0 | O16: =+N16*M16 -> 0
B17: =+'Análisis Técnico'!B116:C116 -> 0 | D17: =+'Análisis Técnico'!D116 -> Infraestructura | E17: =+'Análisis Técnico'!E116 -> Cerco perimétrico | F17: =+'Análisis Técnico'!F116 -> 0 | G17: =+'Análisis Técnico'!G116 -> 0 | H17: =+'Análisis Técnico'!H116 -> 0 | I17: =+'Análisis Técnico'!I116 -> 0 | J17: =+'Análisis Técnico'!K116 -> Unidad | K17: =+'Análisis Técnico'!L116 -> 0 | L17: =+'Análisis Técnico'!M116 -> ml | M17: =+'Análisis Técnico'!N116 -> 0 | O17: =+N17*M17 -> 0
B18: =+'Análisis Técnico'!B117:C117 -> 0 | D18: =+'Análisis Técnico'!D117 -> Infraestructura | E18: =+'Análisis Técnico'!E117 -> Muro de contención | F18: =+'Análisis Técnico'!F117 -> 0 | G18: =+'Análisis Técnico'!G117 -> 0 | H18: =+'Análisis Técnico'!H117 -> 0 | I18: =+'Análisis Técnico'!I117 -> 0 | J18: =+'Análisis Técnico'!K117 -> Unidad | K18: =+'Análisis Técnico'!L117 -> 0 | L18: =+'Análisis Técnico'!M117 -> ml o m3 | M18: =+'Análisis Técnico'!N117 -> 0 | O18: =+N18*M18 -> 0
B19: =+'Análisis Técnico'!B118:C118 -> 0 | D19: =+'Análisis Técnico'!D118 -> Infraestructura | E19: =+'Análisis Técnico'!E118 -> Otros ambientes complementarios | F19: =+'Análisis Técnico'!F118 -> 0 | G19: =+'Análisis Técnico'!G118 -> 0 | H19: =+'Análisis Técnico'!H118 -> 0 | I19: =+'Análisis Técnico'!I118 -> 0 | J19: =+'Análisis Técnico'!K118 -> Unidad | K19: =+'Análisis Técnico'!L118 -> 0 | L19: m2 | M19: =+'Análisis Técnico'!N118 -> 0 | O19: =+N19*M19 -> 0
B21: Componente 2 | D21: =+'Problema-Objetivo'!C44
B23: =+B9 -> Acción sobre el activo | D23: Tipo de factor productivo | E23: Activos | J23: Unidad Física | M23: Costo total
J24: Unidad de medida | L24: Cantidad
B25: =+'Análisis Técnico'!B124:C124 -> 0 | D25: =+'Análisis Técnico'!D124 -> Equipos | E25: =+'Análisis Técnico'!E124 -> Equipo de ambiente de preparación y expendio de alimentos - Cuna Más | F25: =+'Análisis Técnico'!F124 -> 0 | G25: =+'Análisis Técnico'!G124 -> 0 | H25: =+'Análisis Técnico'!H124 -> 0 | I25: =+'Análisis Técnico'!I124 -> 0 | J25: =+'Análisis Técnico'!J124 -> Número de equipos | K25: =+'Análisis Técnico'!K124 -> 0 | L25: =+'Análisis Técnico'!L124 -> 0
B28: Componente 3 | D28: =+'Problema-Objetivo'!C45
B30: =+B23 -> Acción sobre el activo | D30: Tipo de factor productivo | E30: Activos | J30: Unidad Física | M30: Costo total
J31: Unidad de medida | L31: Cantidad
B32: =+'Análisis Técnico'!B131 -> 0 | D32: =+'Análisis Técnico'!D131 -> Mobiliario | E32: =+'Análisis Técnico'!E131 -> Mobiliario de sala de cuidado diurno | F32: =+'Análisis Técnico'!F131 -> 0 | G32: =+'Análisis Técnico'!G131 -> 0 | H32: =+'Análisis Técnico'!H131 -> 0 | I32: =+'Análisis Técnico'!I131 -> 0 | J32: =+'Análisis Técnico'!J131 -> Número de mobiliario | K32: =+'Análisis Técnico'!K131 -> 0 | L32: =+'Análisis Técnico'!L131 -> 0
B33: =+'Análisis Técnico'!B132 -> 0 | D33: =+'Análisis Técnico'!D132 -> Mobiliario | E33: =+'Análisis Técnico'!E132 -> Mobiliario de ambiente de preparación y expendio de alimentos- Cuna Más | F33: =+'Análisis Técnico'!F132 -> 0 | G33: =+'Análisis Técnico'!G132 -> 0 | H33: =+'Análisis Técnico'!H132 -> 0 | I33: =+'Análisis Técnico'!I132 -> 0 | J33: =+'Análisis Técnico'!J132 -> Número de mobiliario | K33: =+'Análisis Técnico'!K132 -> 0 | L33: =+'Análisis Técnico'!L132 -> 0
B36: Componente 4 | D36: =+'Problema-Objetivo'!C46
B38: =+B30 -> Acción sobre el activo | D38: Tipo de factor productivo | E38: Activos | J38: Unidad Física | M38: Costo total
J39: Unidad de medida | L39: Cantidad
B40: =+'Análisis Técnico'!B138 -> 0 | D40: =+'Análisis Técnico'!D138 -> Intangibles | E40: =+'Análisis Técnico'!E138 -> Recursos humanos | F40: =+'Análisis Técnico'!F138 -> 0 | G40: =+'Análisis Técnico'!G138 -> 0 | H40: =+'Análisis Técnico'!H138 -> 0 | I40: =+'Análisis Técnico'!I138 -> 0 | J40: =+'Análisis Técnico'!J138 -> Número de eventos de capacitación | K40: =+'Análisis Técnico'!K138 -> 0 | L40: =+'Análisis Técnico'!L138 -> 0
B42: =+B46 -> Medidas de reducción del riesgo de desastre y mitigación ambiental
B44: =+B37 -> 0 | E44: Activos | J44: Unidad Física | M44: Costo unitario | N44: Costo total
J45: Unidad de medida | L45: Cantidad
B46: Medidas de reducción del riesgo de desastre y mitigación ambiental
B47: =+'Análisis Técnico'!G76 -> 0
B48: =+'Análisis Técnico'!G77 -> 0
B49: =+'Análisis Técnico'!G78 -> 0
B50: =+'Análisis Técnico'!G79 -> 0
B51: =+'Análisis Técnico'!G80 -> 0
B52: =+'Análisis Técnico'!G81 -> 0
B53: =+'Análisis Técnico'!G82 -> 0
B54: =+'Análisis Técnico'!G83 -> 0
B55: =+'Análisis Técnico'!G84 -> 0
B56: =+'Análisis Técnico'!G85 -> 0
B57: =+'Análisis Técnico'!G86 -> 0
B58: =+'Análisis Técnico'!G87 -> 0
... B62: =+'Análisis Técnico'!G91 -> 0
B64: Sub Total de costos directos | M64: =+SUM(N47:N62)+M40+M32+M25+SUM(O11:O19)+M33 -> 0
B66: Costos indirectos
B68: Otros costos | E68: Costos a precios de mercado | G68: % respecto al costo directo
B70: Gestión del proyecto | G70: =IF($M$64>0,+E70/$M$64,"")
B71: Expediente técnico o documento equivalente | G71: =IF($M$64>0,+E71/$M$64,"")
B72: Supervisión | G72: =IF($M$64>0,+E72/$M$64,"")
B73: Liquidación | G73: =IF($M$64>0,+E73/$M$64,"")
B74: Gastos generales | G74: =IF($M$64>0,+E74/$M$64,"")
B76: Subtotal de otros costos de inversión | E76: =SUM(E70:F74) -> 0
B78: Costo Total de inversión | E78: =+E76+M64 -> 0
B81: 9.02 Costos de reinversión
B83: Activos | D83: UM | E83: Cantidad | F83: AÑOS (Soles)
F84: =+Brecha!E13 | G84: =+Brecha!F13 | H84: =+Brecha!G13 | I84: =+Brecha!H13 | J84: =+Brecha!I13 | K84: =+Brecha!J13 | L84: =+Brecha!K13 | M84: =+Brecha!L13 | ... O84: =+Brecha!N13
B95: 9.03 Costos de operación y mantenimiento con y sin proyecto
B97: Fecha prevista de inicio de operaciones: (mes / año): | G97: =+Horizonte!I18 -> 0
B98: Horizonte de funcionamiento (años) | G98: 10
B100: Situación sin proyecto | J100: Situación con proyecto
B101: Detalle | F101: Costos anual | J101: Detalle | N101: Costos anual
F102: Cantidad | G102: Costo | H102: Total | N102: Cantidad | O102: Costo | P102: Total
B103: a. Personal | J103: a. Personal
B104: · Actores comunales: | F104: =+'Unidad Productora'!F94 -> 0 | G104: =+'Unidad Productora'!G94 -> 0 | J104: · Actores comunales:
B105: o Madre cuidadora | F105: =+'Unidad Productora'!F95 -> 0 | G105: =+'Unidad Productora'!G95 -> 0 | H105: =+'Unidad Productora'!H95 -> 0 | J105: o Madre cuidadora | P105: =+O105*N105 -> 0
B106: o Madre guía | F106: =+'Unidad Productora'!F96 -> 0 | G106: =+'Unidad Productora'!G96 -> 0 | H106: =+'Unidad Productora'!H96 -> 0 | J106: o Madre guía | P106: =+O106*N106 -> 0
B107: o Guía de Familia | F107: =+'Unidad Productora'!F97 -> 0 | G107: =+'Unidad Productora'!G97 -> 0 | H107: =+'Unidad Productora'!H97 -> 0 | J107: o Guía de Familia | P107: =+O107*N107 -> 0
B108: o Socia de cocina | F108: =+'Unidad Productora'!F98 -> 0 | G108: =+'Unidad Productora'!G98 -> 0 | H108: =+'Unidad Productora'!H98 -> 0 | J108: o Socia de cocina | P108: =+O108*N108 -> 0
B109: o Repartidor | F109: =+'Unidad Productora'!F99 -> 0 | G109: =+'Unidad Productora'!G99 -> 0 | H109: =+'Unidad Productora'!H99 -> 0 | J109: o Repartidor | P109: =+O109*N109 -> 0
B110: o Apoyo de Limpieza y Vigilancia | F110: =+'Unidad Productora'!F100 -> 0 | G110: =+'Unidad Productora'!G100 -> 0 | H110: =+'Unidad Productora'!H100 -> 0 | J110: o Apoyo de Limpieza y Vigilancia | P110: =+O110*N110 -> 0
B111: · Equipo técnico profesional del PNCM: | F111: =+'Unidad Productora'!F101 -> 0 | G111: =+'Unidad Productora'!G101 -> 0 | H111: =+'Unidad Productora'!H101 -> 0 | J111: · Equipo técnico profesional del PNCM: | P111: =+O111*N111 -> 0
B112: o Acompañantes técnicos (AT) | F112: =+'Unidad Productora'!F102 -> 0 | G112: =+'Unidad Productora'!G102 -> 0 | H112: =+'Unidad Productora'!H102 -> 0 | J112: o Acompañantes técnicos (AT) | P112: =+O112*N112 -> 0
B113: o Especialistas integrales | F113: =+'Unidad Productora'!F103 -> 0 | G113: =+'Unidad Productora'!G103 -> 0 | H113: =+'Unidad Productora'!H103 -> 0 | J113: o Especialistas integrales | P113: =+O113*N113 -> 0
B114: o Especialistas en nutrición | F114: =+'Unidad Productora'!F104 -> 0 | G114: =+'Unidad Productora'!G104 -> 0 | H114: =+'Unidad Productora'!H104 -> 0 | J114: o Especialistas en nutrición | P114: =+O114*N114 -> 0
B115: b. Servicios | J115: b. Servicios
B116: · Servicios | F116: =+'Unidad Productora'!F110 -> 0 | G116: =+'Unidad Productora'!G110 -> 0 | J116: · Servicios
B117: o Agua | F117: =+'Unidad Productora'!F111 -> 0 | G117: =+'Unidad Productora'!G111 -> 0 | H117: =+'Unidad Productora'!H111 -> 0 | J117: o Agua | P117: =+O117*N117 -> 0
B118: o Luz | F118: =+'Unidad Productora'!F112 -> 0 | G118: =+'Unidad Productora'!G112 -> 0 | H118: =+'Unidad Productora'!H112 -> 0 | J118: o Luz | P118: =+O118*N118 -> 0
B119: o Internet | F119: =+'Unidad Productora'!F113 -> 0 | G119: =+'Unidad Productora'!G113 -> 0 | H119: =+'Unidad Productora'!H113 -> 0 | J119: o Internet | P119: =+O119*N119 -> 0
B120: o Seguridad | F120: =+'Unidad Productora'!F114 -> 0 | G120: =+'Unidad Productora'!G114 -> 0 | H120: =+'Unidad Productora'!H114 -> 0 | J120: o Seguridad | P120: =+O120*N120 -> 0
B121: o Mantenimiento | F121: =+'Unidad Productora'!F115 -> 0 | G121: =+'Unidad Productora'!G115 -> 0 | H121: =+'Unidad Productora'!H115 -> 0 | J121: o Mantenimiento | P121: =+O121*N121 -> 0
H122: =SUM(H105:H121) -> 0 | P122: =SUM(P105:P121) -> 0
B124: 9.04 Cronograma de inversión de metas financieras
B126: Fecha prevista de inicio de ejecución: | F126: =+Horizonte!I12 -> 0 | H126: (mes y año)
B127: Tipo de periodo | F127: Trimestre
B128: Número de periodos | H128: (valor)
B130: Componente | G130: Tipo de factor productivo | I130: Cronograma de inversión (trimestres) | Q130: Costo estimado de inversión a precios de mercado (Soles)
I131: Tri 1 | J131: Tri 2 | K131: Tri 3 | L131: Tri 4 | M131: Tri 5 | N131: Tri 6 | O131: Tri 7 | P131: Tri 8
B134: Componente 1:
B135: =+D6 | G135: Infraestructura | Q135: =+SUM(O11:O19) -> 0
B136: Componente 2
B137: =+D21 | G137: Equipamiento | Q137: =SUM(M25) -> 0
B138: Componente 3
B139: =+D28 | G139: Mobiliario | Q139: =SUM(M32:N33) -> 0
B140: Componente 4
B141: =+D36 | G141: Intangibles | Q141: =SUM(M40) -> 0
B142: Medidas de reducción del riesgo de desastre y mitigación ambiental
B143: Implementación de medidas | Q143: =SUM(N47:N62) -> 0
...

Sheet CostosAlt2
B2: SECCIÓN N°09: COSTOS DEL PROYECTO - ALTERNATIVA 2
B4: 9.01 Costo de ejecución física de las acciones
B6: Componente 1 | D6: =+'Problema-Objetivo'!C40
B8: Servicio de Cuidado Diurno
B9: Acción sobre el activo | D9: Tipo de factor productivo | E9: Activos | J9: Unidad Física | L9: Dimensión física | N9: Costo unitario | O9: Costo total
J10: Unidad de medida | K10: Cantidad | L10: Unidad de medida | M10: Cantidad
B11: =+'Análisis Técnico'!B110:C110 -> 0 | D11: =+'Análisis Técnico'!D110 -> Infraestructura | E11: =+'Análisis Técnico'!E110 -> Sala de cuidado diurno | F11: =+'Análisis Técnico'!F110 -> 0 | G11: =+'Análisis Técnico'!G110 -> 0 | H11: =+'Análisis Técnico'!H110 -> 0 | I11: =+'Análisis Técnico'!I110 -> 0 | J11: =+'Análisis Técnico'!K110 -> Sala | K11: =+'Análisis Técnico'!L110 -> 0 | L11: =+'Análisis Técnico'!M110 -> m2 | M11: =+'Análisis Técnico'!N110 -> 0 | O11: =+N11*M11 -> 0
B12: =+'Análisis Técnico'!B111:C111 -> 0 | D12: =+'Análisis Técnico'!D111 -> Infraestructura | E12: =+'Análisis Técnico'!E111 -> Sala de usos múltiples | F12: =+'Análisis Técnico'!F111 -> 0 | G12: =+'Análisis Técnico'!G111 -> 0 | H12: =+'Análisis Técnico'!H111 -> 0 | I12: =+'Análisis Técnico'!I111 -> 0 | J12: =+'Análisis Técnico'!K111 -> Sala | K12: =+'Análisis Técnico'!L111 -> 0 | L12: =+'Análisis Técnico'!M111 -> m2 | M12: =+'Análisis Técnico'!N111 -> 0 | O12: =+N12*M12 -> 0
B13: =+'Análisis Técnico'!B112:C112 -> 0 | D13: =+'Análisis Técnico'!D112 -> Infraestructura | E13: =+'Análisis Técnico'!E112 -> Ambiente de recreación activa | F13: =+'Análisis Técnico'!F112 -> 0 | G13: =+'Análisis Técnico'!G112 -> 0 | H13: =+'Análisis Técnico'!H112 -> 0 | I13: =+'Análisis Técnico'!I112 -> 0 | J13: =+'Análisis Técnico'!K112 -> Ambiente | K13: =+'Análisis Técnico'!L112 -> 0 | L13: =+'Análisis Técnico'!M112 -> m2 | M13: =+'Análisis Técnico'!N112 -> 0 | O13: =+N13*M13 -> 0
B14: =+'Análisis Técnico'!B113:C113 -> 0 | D14: =+'Análisis Técnico'!D113 -> Infraestructura | E14: =+'Análisis Técnico'!E113 -> Ambiente de servicios generales | F14: =+'Análisis Técnico'!F113 -> 0 | G14: =+'Análisis Técnico'!G113 -> 0 | H14: =+'Análisis Técnico'!H113 -> 0 | I14: =+'Análisis Técnico'!I113 -> 0 | J14: =+'Análisis Técnico'!K113 -> Ambiente | K14: =+'Análisis Técnico'!L113 -> 0 | L14: =+'Análisis Técnico'!M113 -> m2 | M14: =+'Análisis Técnico'!N113 -> 0 | O14: =+N14*M14 -> 0
B15: =+'Análisis Técnico'!B114:C114 -> 0 | D15: =+'Análisis Técnico'!D114 -> Infraestructura | E15: =+'Análisis Técnico'!E114 -> Ambiente de preparación y expendio de alimentos | F15: =+'Análisis Técnico'!F114 -> 0 | G15: =+'Análisis Técnico'!G114 -> 0 | H15: =+'Análisis Técnico'!H114 -> 0 | I15: =+'Análisis Técnico'!I114 -> 0 | J15: =+'Análisis Técnico'!K114 -> Ambiente | K15: =+'Análisis Técnico'!L114 -> 0 | L15: =+'Análisis Técnico'!M114 -> m2 | M15: =+'Análisis Técnico'!N114 -> 0 | O15: =+N15*M15 -> 0
B16: =+'Análisis Técnico'!B115:C115 -> 0 | D16: =+'Análisis Técnico'!D115 -> Infraestructura | E16: =+'Análisis Técnico'!E115 -> Almacén | F16: =+'Análisis Técnico'!F115 -> 0 | G16: =+'Análisis Técnico'!G115 -> 0 | H16: =+'Análisis Técnico'!H115 -> 0 | I16: =+'Análisis Técnico'!I115 -> 0 | J16: =+'Análisis Técnico'!K115 -> Almacén | K16: =+'Análisis Técnico'!L115 -> 0 | L16: =+'Análisis Técnico'!M115 -> m2 | M16: =+'Análisis Técnico'!N115 -> 0 | O16: =+N16*M16 -> 0
B17: =+'Análisis Técnico'!B116:C116 -> 0 | D17: =+'Análisis Técnico'!D116 -> Infraestructura | E17: =+'Análisis Técnico'!E116 -> Cerco perimétrico | F17: =+'Análisis Técnico'!F116 -> 0 | G17: =+'Análisis Técnico'!G116 -> 0 | H17: =+'Análisis Técnico'!H116 -> 0 | I17: =+'Análisis Técnico'!I116 -> 0 | J17: =+'Análisis Técnico'!K116 -> Unidad | K17: =+'Análisis Técnico'!L116 -> 0 | L17: =+'Análisis Técnico'!M116 -> ml | M17: =+'Análisis Técnico'!N116 -> 0 | O17: =+N17*M17 -> 0
B18: =+'Análisis Técnico'!B117:C117 -> 0 | D18: =+'Análisis Técnico'!D117 -> Infraestructura | E18: =+'Análisis Técnico'!E117 -> Muro de contención | F18: =+'Análisis Técnico'!F117 -> 0 | G18: =+'Análisis Técnico'!G117 -> 0 | H18: =+'Análisis Técnico'!H117 -> 0 | I18: =+'Análisis Técnico'!I117 -> 0 | J18: =+'Análisis Técnico'!K117 -> Unidad | K18: =+'Análisis Técnico'!L117 -> 0 | L18: =+'Análisis Técnico'!M117 -> ml o m3 | M18: =+'Análisis Técnico'!N117 -> 0 | O18: =+N18*M18 -> 0
B19: =+'Análisis Técnico'!B118:C118 -> 0 | D19: =+'Análisis Técnico'!D118 -> Infraestructura | E19: =+'Análisis Técnico'!E118 -> Otros ambientes complementarios | F19: =+'Análisis Técnico'!F118 -> 0 | G19: =+'Análisis Técnico'!G118 -> 0 | H19: =+'Análisis Técnico'!H118 -> 0 | I19: =+'Análisis Técnico'!I118 -> 0 | J19: =+'Análisis Técnico'!K118 -> Unidad | K19: =+'Análisis Técnico'!L118 -> 0 | L19: m2 | M19: =+'Análisis Técnico'!N118 -> 0 | O19: =+N19*M19 -> 0
B21: Componente 2 | D21: =+'Problema-Objetivo'!C44
B23: =+B9 -> Acción sobre el activo | D23: Tipo de factor productivo | E23: Activos | J23: Unidad Física | M23: Costo total
J24: Unidad de medida | L24: Cantidad
B25: =+'Análisis Técnico'!B124:C124 -> 0 | D25: =+'Análisis Técnico'!D124 -> Equipos | E25: =+'Análisis Técnico'!E124 -> Equipo de ambiente de preparación y expendio de alimentos - Cuna Más | F25: =+'Análisis Técnico'!F124 -> 0 | G25: =+'Análisis Técnico'!G124 -> 0 | H25: =+'Análisis Técnico'!H124 -> 0 | I25: =+'Análisis Técnico'!I124 -> 0 | J25: =+'Análisis Técnico'!J124 -> Número de equipos | K25: =+'Análisis Técnico'!K124 -> 0 | L25: =+'Análisis Técnico'!L124 -> 0
B28: Componente 3 | D28: =+'Problema-Objetivo'!C45
B30: =+B23 -> Acción sobre el activo | D30: Tipo de factor productivo | E30: Activos | J30: Unidad Física | M30: Costo total
J31: Unidad de medida | L31: Cantidad
B32: =+'Análisis Técnico'!B131 -> 0 | D32: =+'Análisis Técnico'!D131 -> Mobiliario | E32: =+'Análisis Técnico'!E131 -> Mobiliario de sala de cuidado diurno | F32: =+'Análisis Técnico'!F131 -> 0 | G32: =+'Análisis Técnico'!G131 -> 0 | H32: =+'Análisis Técnico'!H131 -> 0 | I32: =+'Análisis Técnico'!I131 -> 0 | J32: =+'Análisis Técnico'!J131 -> Número de mobiliario | K32: =+'Análisis Técnico'!K131 -> 0 | L32: =+'Análisis Técnico'!L131 -> 0
B33: =+'Análisis Técnico'!B132 -> 0 | D33: =+'Análisis Técnico'!D132 -> Mobiliario | E33: =+'Análisis Técnico'!E132 -> Mobiliario de ambiente de preparación y expendio de alimentos- Cuna Más | F33: =+'Análisis Técnico'!F132 -> 0 | G33: =+'Análisis Técnico'!G132 -> 0 | H33: =+'Análisis Técnico'!H132 -> 0 | I33: =+'Análisis Técnico'!I132 -> 0 | J33: =+'Análisis Técnico'!J132 -> Número de mobiliario | K33: =+'Análisis Técnico'!K132 -> 0 | L33: =+'Análisis Técnico'!L132 -> 0
B36: Componente 4 | D36: =+'Problema-Objetivo'!C46
B38: =+B30 -> Acción sobre el activo | D38: Tipo de factor productivo | E38: Activos | J38: Unidad Física | M38: Costo total
J39: Unidad de medida | L39: Cantidad
B40: =+'Análisis Técnico'!B138 -> 0 | D40: =+'Análisis Técnico'!D138 -> Intangibles | E40: =+'Análisis Técnico'!E138 -> Recursos humanos | F40: =+'Análisis Técnico'!F138 -> 0 | G40: =+'Análisis Técnico'!G138 -> 0 | H40: =+'Análisis Técnico'!H138 -> 0 | I40: =+'Análisis Técnico'!I138 -> 0 | J40: =+'Análisis Técnico'!J138 -> Número de eventos de capacitación | K40: =+'Análisis Técnico'!K138 -> 0 | L40: =+'Análisis Técnico'!L138 -> 0
B42: =+B46 -> Medidas de reducción del riesgo de desastre y mitigación ambiental
B44: =+B37 -> 0 | E44: Activos | J44: Unidad Física | M44: Costo unitario | N44: Costo total
J45: Unidad de medida | L45: Cantidad
B46: Medidas de reducción del riesgo de desastre y mitigación ambiental
B47: =+'Análisis Técnico'!G76 -> 0
B48: =+'Análisis Técnico'!G77 -> 0
B49: =+'Análisis Técnico'!G78 -> 0
B50: =+'Análisis Técnico'!G79 -> 0
B51: =+'Análisis Técnico'!G80 -> 0
B52: =+'Análisis Técnico'!G81 -> 0
B53: =+'Análisis Técnico'!G82 -> 0
B54: =+'Análisis Técnico'!G83 -> 0
B55: =+'Análisis Técnico'!G84 -> 0
B56: =+'Análisis Técnico'!G85 -> 0
B57: =+'Análisis Técnico'!G86 -> 0
B58: =+'Análisis Técnico'!G87 -> 0
... B62: =+'Análisis Técnico'!G91 -> 0
B64: Sub Total de costos directos | M64: =+SUM(N47:N62)+M40+M32+M25+SUM(O11:O19)+M33 -> 0
B66: Costos indirectos
B68: Otros costos | E68: Costos a precios de mercado | G68: % respecto al costo directo
B70: Gestión del proyecto | G70: =IF($M$64>0,+E70/$M$64,"")
B71: Expediente técnico o documento equivalente | G71: =IF($M$64>0,+E71/$M$64,"")
B72: Supervisión | G72: =IF($M$64>0,+E72/$M$64,"")
B73: Liquidación | G73: =IF($M$64>0,+E73/$M$64,"")
B74: Gastos generales | G74: =IF($M$64>0,+E74/$M$64,"")
B76: Subtotal de otros costos de inversión | E76: =SUM(E70:F74) -> 0
B78: Costo Total de inversión | E78: =+E76+M64 -> 0
B81: 9.02 Costos de reinversión
B83: Activos | D83: UM | E83: Cantidad | F83: AÑOS (Soles)
F84: =+Brecha!E13 | G84: =+Brecha!F13 | H84: =+Brecha!G13 | I84: =+Brecha!H13 | J84: =+Brecha!I13 | K84: =+Brecha!J13 | L84: =+Brecha!K13 | M84: =+Brecha!L13 | ... O84: =+Brecha!N13
B95: 9.03 Costos de operación y mantenimiento con y sin proyecto
B97: Fecha prevista de inicio de operaciones: (mes / año): | G97: =+Horizonte!I18 -> 0
B98: Horizonte de funcionamiento (años) | G98: 10
B100: Situación sin proyecto | J100: Situación con proyecto
B101: Detalle | F101: Costos anual | J101: Detalle | N101: Costos anual
F102: Cantidad | G102: Costo | H102: Total | N102: Cantidad | O102: Costo | P102: Total
B103: a. Personal | J103: a. Personal
B104: · Actores comunales: | F104: =+'Unidad Productora'!F94 -> 0 | G104: =+'Unidad Productora'!G94 -> 0 | J104: · Actores comunales:
B105: o Madre cuidadora | F105: =+'Unidad Productora'!F95 -> 0 | G105: =+'Unidad Productora'!G95 -> 0 | H105: =+'Unidad Productora'!H95 -> 0 | J105: o Madre cuidadora | P105: =+O105*N105 -> 0
B106: o Madre guía | F106: =+'Unidad Productora'!F96 -> 0 | G106: =+'Unidad Productora'!G96 -> 0 | H106: =+'Unidad Productora'!H96 -> 0 | J106: o Madre guía | P106: =+O106*N106 -> 0
B107: o Guía de Familia | F107: =+'Unidad Productora'!F97 -> 0 | G107: =+'Unidad Productora'!G97 -> 0 | H107: =+'Unidad Productora'!H97 -> 0 | J107: o Guía de Familia | P107: =+O107*N107 -> 0
B108: o Socia de cocina | F108: =+'Unidad Productora'!F98 -> 0 | G108: =+'Unidad Productora'!G98 -> 0 | H108: =+'Unidad Productora'!H98 -> 0 | J108: o Socia de cocina | P108: =+O108*N108 -> 0
B109: o Repartidor | F109: =+'Unidad Productora'!F99 -> 0 | G109: =+'Unidad Productora'!G99 -> 0 | H109: =+'Unidad Productora'!H99 -> 0 | J109: o Repartidor | P109: =+O109*N109 -> 0
B110: o Apoyo de Limpieza y Vigilancia | F110: =+'Unidad Productora'!F100 -> 0 | G110: =+'Unidad Productora'!G100 -> 0 | H110: =+'Unidad Productora'!H100 -> 0 | J110: o Apoyo de Limpieza y Vigilancia | P110: =+O110*N110 -> 0
B111: · Equipo técnico profesional del PNCM: | F111: =+'Unidad Productora'!F101 -> 0 | G111: =+'Unidad Productora'!G101 -> 0 | H111: =+'Unidad Productora'!H101 -> 0 | J111: · Equipo técnico profesional del PNCM: | P111: =+O111*N111 -> 0
B112: o Acompañantes técnicos (AT) | F112: =+'Unidad Productora'!F102 -> 0 | G112: =+'Unidad Productora'!G102 -> 0 | H112: =+'Unidad Productora'!H102 -> 0 | J112: o Acompañantes técnicos (AT) | P112: =+O112*N112 -> 0
B113: o Especialistas integrales | F113: =+'Unidad Productora'!F103 -> 0 | G113: =+'Unidad Productora'!G103 -> 0 | H113: =+'Unidad Productora'!H103 -> 0 | J113: o Especialistas integrales | P113: =+O113*N113 -> 0
B114: o Especialistas en nutrición | F114: =+'Unidad Productora'!F104 -> 0 | G114: =+'Unidad Productora'!G104 -> 0 | H114: =+'Unidad Productora'!H104 -> 0 | J114: o Especialistas en nutrición | P114: =+O114*N114 -> 0
B115: b. Servicios | J115: b. Servicios
B116: · Servicios | F116: =+'Unidad Productora'!F110 -> 0 | G116: =+'Unidad Productora'!G110 -> 0 | J116: · Servicios
B117: o Agua | F117: =+'Unidad Productora'!F111 -> 0 | G117: =+'Unidad Productora'!G111 -> 0 | H117: =+'Unidad Productora'!H111 -> 0 | J117: o Agua | P117: =+O117*N117 -> 0
B118: o Luz | F118: =+'Unidad Productora'!F112 -> 0 | G118: =+'Unidad Productora'!G112 -> 0 | H118: =+'Unidad Productora'!H112 -> 0 | J118: o Luz | P118: =+O118*N118 -> 0
B119: o Internet | F119: =+'Unidad Productora'!F113 -> 0 | G119: =+'Unidad Productora'!G113 -> 0 | H119: =+'Unidad Productora'!H113 -> 0 | J119: o Internet | P119: =+O119*N119 -> 0
B120: o Seguridad | F120: =+'Unidad Productora'!F114 -> 0 | G120: =+'Unidad Productora'!G114 -> 0 | H120: =+'Unidad Productora'!H114 -> 0 | J120: o Seguridad | P120: =+O120*N120 -> 0
B121: o Mantenimiento | F121: =+'Unidad Productora'!F115 -> 0 | G121: =+'Unidad Productora'!G115 -> 0 | H121: =+'Unidad Productora'!H115 -> 0 | J121: o Mantenimiento | P121: =+O121*N121 -> 0
H122: =SUM(H105:H121) -> 0 | P122: =SUM(P105:P121) -> 0
B124: 9.04 Cronograma de inversión de metas financieras
B126: Fecha prevista de inicio de ejecución: | F126: =+Horizonte!I12 -> 0 | H126: (mes y año)
B127: Tipo de periodo | F127: Trimestre
B128: Número de periodos | H128: (valor)
B130: Componente | G130: Tipo de factor productivo | I130: Cronograma de inversión (trimestres) | Q130: Costo estimado de inversión a precios de mercado (Soles)
I131: Tri 1 | J131: Tri 2 | K131: Tri 3 | L131: Tri 4 | M131: Tri 5 | N131: Tri 6 | O131: Tri 7 | P131: Tri 8
B134: Componente 1:
B135: =+D6 | G135: Infraestructura | Q135: =+SUM(O11:O19) -> 0
B136: Componente 2
B137: =+D21 | G137: Equipamiento | Q137: =SUM(M25) -> 0
B138: Componente 3
B139: =+D28 | G139: Mobiliario | Q139: =SUM(M32:N33) -> 0
B140: Componente 4
B141: =+D36 | G141: Intangibles | Q141: =SUM(M40) -> 0
B142: Medidas de reducción del riesgo de desastre y mitigación ambiental
B143: Implementación de medidas | Q143: =SUM(N47:N62) -> 0
...

Sheet CostosAlt3
B2: SECCIÓN N°09: COSTOS DEL PROYECTO - ALTERNATIVA 3
B4: 9.01 Costo de ejecución física de las acciones
B6: Componente 1 | D6: =+'Problema-Objetivo'!C40
B8: Servicio de Cuidado Diurno
B9: Acción sobre el activo | D9: Tipo de factor productivo | E9: Activos | J9: Unidad Física | L9: Dimensión física | N9: Costo unitario | O9: Costo total
J10: Unidad de medida | K10: Cantidad | L10: Unidad de medida | M10: Cantidad
B11: =+'Análisis Técnico'!B110:C110 -> 0 | D11: =+'Análisis Técnico'!D110 -> Infraestructura | E11: =+'Análisis Técnico'!E110 -> Sala de cuidado diurno | F11: =+'Análisis Técnico'!F110 -> 0 | G11: =+'Análisis Técnico'!G110 -> 0 | H11: =+'Análisis Técnico'!H110 -> 0 | I11: =+'Análisis Técnico'!I110 -> 0 | J11: =+'Análisis Técnico'!K110 -> Sala | K11: =+'Análisis Técnico'!L110 -> 0 | L11: =+'Análisis Técnico'!M110 -> m2 | M11: =+'Análisis Técnico'!N110 -> 0 | O11: =+N11*M11 -> 0
B12: =+'Análisis Técnico'!B111:C111 -> 0 | D12: =+'Análisis Técnico'!D111 -> Infraestructura | E12: =+'Análisis Técnico'!E111 -> Sala de usos múltiples | F12: =+'Análisis Técnico'!F111 -> 0 | G12: =+'Análisis Técnico'!G111 -> 0 | H12: =+'Análisis Técnico'!H111 -> 0 | I12: =+'Análisis Técnico'!I111 -> 0 | J12: =+'Análisis Técnico'!K111 -> Sala | K12: =+'Análisis Técnico'!L111 -> 0 | L12: =+'Análisis Técnico'!M111 -> m2 | M12: =+'Análisis Técnico'!N111 -> 0 | O12: =+N12*M12 -> 0
B13: =+'Análisis Técnico'!B112:C112 -> 0 | D13: =+'Análisis Técnico'!D112 -> Infraestructura | E13: =+'Análisis Técnico'!E112 -> Ambiente de recreación activa | F13: =+'Análisis Técnico'!F112 -> 0 | G13: =+'Análisis Técnico'!G112 -> 0 | H13: =+'Análisis Técnico'!H112 -> 0 | I13: =+'Análisis Técnico'!I112 -> 0 | J13: =+'Análisis Técnico'!K112 -> Ambiente | K13: =+'Análisis Técnico'!L112 -> 0 | L13: =+'Análisis Técnico'!M112 -> m2 | M13: =+'Análisis Técnico'!N112 -> 0 | O13: =+N13*M13 -> 0
B14: =+'Análisis Técnico'!B113:C113 -> 0 | D14: =+'Análisis Técnico'!D113 -> Infraestructura | E14: =+'Análisis Técnico'!E113 -> Ambiente de servicios generales | F14: =+'Análisis Técnico'!F113 -> 0 | G14: =+'Análisis Técnico'!G113 -> 0 | H14: =+'Análisis Técnico'!H113 -> 0 | I14: =+'Análisis Técnico'!I113 -> 0 | J14: =+'Análisis Técnico'!K113 -> Ambiente | K14: =+'Análisis Técnico'!L113 -> 0 | L14: =+'Análisis Técnico'!M113 -> m2 | M14: =+'Análisis Técnico'!N113 -> 0 | O14: =+N14*M14 -> 0
B15: =+'Análisis Técnico'!B114:C114 -> 0 | D15: =+'Análisis Técnico'!D114 -> Infraestructura | E15: =+'Análisis Técnico'!E114 -> Ambiente de preparación y expendio de alimentos | F15: =+'Análisis Técnico'!F114 -> 0 | G15: =+'Análisis Técnico'!G114 -> 0 | H15: =+'Análisis Técnico'!H114 -> 0 | I15: =+'Análisis Técnico'!I114 -> 0 | J15: =+'Análisis Técnico'!K114 -> Ambiente | K15: =+'Análisis Técnico'!L114 -> 0 | L15: =+'Análisis Técnico'!M114 -> m2 | M15: =+'Análisis Técnico'!N114 -> 0 | O15: =+N15*M15 -> 0
B16: =+'Análisis Técnico'!B115:C115 -> 0 | D16: =+'Análisis Técnico'!D115 -> Infraestructura | E16: =+'Análisis Técnico'!E115 -> Almacén | F16: =+'Análisis Técnico'!F115 -> 0 | G16: =+'Análisis Técnico'!G115 -> 0 | H16: =+'Análisis Técnico'!H115 -> 0 | I16: =+'Análisis Técnico'!I115 -> 0 | J16: =+'Análisis Técnico'!K115 -> Almacén | K16: =+'Análisis Técnico'!L115 -> 0 | L16: =+'Análisis Técnico'!M115 -> m2 | M16: =+'Análisis Técnico'!N115 -> 0 | O16: =+N16*M16 -> 0
B17: =+'Análisis Técnico'!B116:C116 -> 0 | D17: =+'Análisis Técnico'!D116 -> Infraestructura | E17: =+'Análisis Técnico'!E116 -> Cerco perimétrico | F17: =+'Análisis Técnico'!F116 -> 0 | G17: =+'Análisis Técnico'!G116 -> 0 | H17: =+'Análisis Técnico'!H116 -> 0 | I17: =+'Análisis Técnico'!I116 -> 0 | J17: =+'Análisis Técnico'!K116 -> Unidad | K17: =+'Análisis Técnico'!L116 -> 0 | L17: =+'Análisis Técnico'!M116 -> ml | M17: =+'Análisis Técnico'!N116 -> 0 | O17: =+N17*M17 -> 0
B18: =+'Análisis Técnico'!B117:C117 -> 0 | D18: =+'Análisis Técnico'!D117 -> Infraestructura | E18: =+'Análisis Técnico'!E117 -> Muro de contención | F18: =+'Análisis Técnico'!F117 -> 0 | G18: =+'Análisis Técnico'!G117 -> 0 | H18: =+'Análisis Técnico'!H117 -> 0 | I18: =+'Análisis Técnico'!I117 -> 0 | J18: =+'Análisis Técnico'!K117 -> Unidad | K18: =+'Análisis Técnico'!L117 -> 0 | L18: =+'Análisis Técnico'!M117 -> ml o m3 | M18: =+'Análisis Técnico'!N117 -> 0 | O18: =+N18*M18 -> 0
B19: =+'Análisis Técnico'!B118:C118 -> 0 | D19: =+'Análisis Técnico'!D118 -> Infraestructura | E19: =+'Análisis Técnico'!E118 -> Otros ambientes complementarios | F19: =+'Análisis Técnico'!F118 -> 0 | G19: =+'Análisis Técnico'!G118 -> 0 | H19: =+'Análisis Técnico'!H118 -> 0 | I19: =+'Análisis Técnico'!I118 -> 0 | J19: =+'Análisis Técnico'!K118 -> Unidad | K19: =+'Análisis Técnico'!L118 -> 0 | L19: m2 | M19: =+'Análisis Técnico'!N118 -> 0 | O19: =+N19*M19 -> 0
B21: Componente 2 | D21: =+'Problema-Objetivo'!C44
B23: =+B9 -> Acción sobre el activo | D23: Tipo de factor productivo | E23: Activos | J23: Unidad Física | M23: Costo total
J24: Unidad de medida | L24: Cantidad
B25: =+'Análisis Técnico'!B124:C124 -> 0 | D25: =+'Análisis Técnico'!D124 -> Equipos | E25: =+'Análisis Técnico'!E124 -> Equipo de ambiente de preparación y expendio de alimentos - Cuna Más | F25: =+'Análisis Técnico'!F124 -> 0 | G25: =+'Análisis Técnico'!G124 -> 0 | H25: =+'Análisis Técnico'!H124 -> 0 | I25: =+'Análisis Técnico'!I124 -> 0 | J25: =+'Análisis Técnico'!J124 -> Número de equipos | K25: =+'Análisis Técnico'!K124 -> 0 | L25: =+'Análisis Técnico'!L124 -> 0
B28: Componente 3 | D28: =+'Problema-Objetivo'!C45
B30: =+B23 -> Acción sobre el activo | D30: Tipo de factor productivo | E30: Activos | J30: Unidad Física | M30: Costo total
J31: Unidad de medida | L31: Cantidad
B32: =+'Análisis Técnico'!B131 -> 0 | D32: =+'Análisis Técnico'!D131 -> Mobiliario | E32: =+'Análisis Técnico'!E131 -> Mobiliario de sala de cuidado diurno | F32: =+'Análisis Técnico'!F131 -> 0 | G32: =+'Análisis Técnico'!G131 -> 0 | H32: =+'Análisis Técnico'!H131 -> 0 | I32: =+'Análisis Técnico'!I131 -> 0 | J32: =+'Análisis Técnico'!J131 -> Número de mobiliario | K32: =+'Análisis Técnico'!K131 -> 0 | L32: =+'Análisis Técnico'!L131 -> 0
B33: =+'Análisis Técnico'!B132 -> 0 | D33: =+'Análisis Técnico'!D132 -> Mobiliario | E33: =+'Análisis Técnico'!E132 -> Mobiliario de ambiente de preparación y expendio de alimentos- Cuna Más | F33: =+'Análisis Técnico'!F132 -> 0 | G33: =+'Análisis Técnico'!G132 -> 0 | H33: =+'Análisis Técnico'!H132 -> 0 | I33: =+'Análisis Técnico'!I132 -> 0 | J33: =+'Análisis Técnico'!J132 -> Número de mobiliario | K33: =+'Análisis Técnico'!K132 -> 0 | L33: =+'Análisis Técnico'!L132 -> 0
B36: Componente 4 | D36: =+'Problema-Objetivo'!C46
B38: =+B30 -> Acción sobre el activo | D38: Tipo de factor productivo | E38: Activos | J38: Unidad Física | M38: Costo total
J39: Unidad de medida | L39: Cantidad
B40: =+'Análisis Técnico'!B138 -> 0 | D40: =+'Análisis Técnico'!D138 -> Intangibles | E40: =+'Análisis Técnico'!E138 -> Recursos humanos | F40: =+'Análisis Técnico'!F138 -> 0 | G40: =+'Análisis Técnico'!G138 -> 0 | H40: =+'Análisis Técnico'!H138 -> 0 | I40: =+'Análisis Técnico'!I138 -> 0 | J40: =+'Análisis Técnico'!J138 -> Número de eventos de capacitación | K40: =+'Análisis Técnico'!K138 -> 0 | L40: =+'Análisis Técnico'!L138 -> 0
B42: =+B46 -> Medidas de reducción del riesgo de desastre y mitigación ambiental
B44: =+B37 -> 0 | E44: Activos | J44: Unidad Física | M44: Costo unitario | N44: Costo total
J45: Unidad de medida | L45: Cantidad
B46: Medidas de reducción del riesgo de desastre y mitigación ambiental
B47: =+'Análisis Técnico'!G76 -> 0
B48: =+'Análisis Técnico'!G77 -> 0
B49: =+'Análisis Técnico'!G78 -> 0
B50: =+'Análisis Técnico'!G79 -> 0
B51: =+'Análisis Técnico'!G80 -> 0
B52: =+'Análisis Técnico'!G81 -> 0
B53: =+'Análisis Técnico'!G82 -> 0
B54: =+'Análisis Técnico'!G83 -> 0
B55: =+'Análisis Técnico'!G84 -> 0
B56: =+'Análisis Técnico'!G85 -> 0
B57: =+'Análisis Técnico'!G86 -> 0
B58: =+'Análisis Técnico'!G87 -> 0
... B62: =+'Análisis Técnico'!G91 -> 0
B64: Sub Total de costos directos | M64: =+SUM(N47:N62)+M40+M32+M25+SUM(O11:O19)+M33 -> 0
B66: Costos indirectos
B68: Otros costos | E68: Costos a precios de mercado | G68: % respecto al costo directo
B70: Gestión del proyecto | G70: =IF($M$64>0,+E70/$M$64,"")
B71: Expediente técnico o documento equivalente | G71: =IF($M$64>0,+E71/$M$64,"")
B72: Supervisión | G72: =IF($M$64>0,+E72/$M$64,"")
B73: Liquidación | G73: =IF($M$64>0,+E73/$M$64,"")
B74: Gastos generales | G74: =IF($M$64>0,+E74/$M$64,"")
B76: Subtotal de otros costos de inversión | E76: =SUM(E70:F74) -> 0
B78: Costo Total de inversión | E78: =+E76+M64 -> 0
B81: 9.02 Costos de reinversión
B83: Activos | D83: UM | E83: Cantidad | F83: AÑOS (Soles)
F84: =+Brecha!E13 | G84: =+Brecha!F13 | H84: =+Brecha!G13 | I84: =+Brecha!H13 | J84: =+Brecha!I13 | K84: =+Brecha!J13 | L84: =+Brecha!K13 | M84: =+Brecha!L13 | ... O84: =+Brecha!N13
B95: 9.03 Costos de operación y mantenimiento con y sin proyecto
B97: Fecha prevista de inicio de operaciones: (mes / año): | G97: =+Horizonte!I18 -> 0
B98: Horizonte de funcionamiento (años) | G98: 10
B100: Situación sin proyecto | J100: Situación con proyecto
B101: Detalle | F101: Costos anual | J101: Detalle | N101: Costos anual
F102: Cantidad | G102: Costo | H102: Total | N102: Cantidad | O102: Costo | P102: Total
B103: a. Personal | J103: a. Personal
B104: · Actores comunales: | F104: =+'Unidad Productora'!F94 -> 0 | G104: =+'Unidad Productora'!G94 -> 0 | J104: · Actores comunales:
B105: o Madre cuidadora | F105: =+'Unidad Productora'!F95 -> 0 | G105: =+'Unidad Productora'!G95 -> 0 | H105: =+'Unidad Productora'!H95 -> 0 | J105: o Madre cuidadora | P105: =+O105*N105 -> 0
B106: o Madre guía | F106: =+'Unidad Productora'!F96 -> 0 | G106: =+'Unidad Productora'!G96 -> 0 | H106: =+'Unidad Productora'!H96 -> 0 | J106: o Madre guía | P106: =+O106*N106 -> 0
B107: o Guía de Familia | F107: =+'Unidad Productora'!F97 -> 0 | G107: =+'Unidad Productora'!G97 -> 0 | H107: =+'Unidad Productora'!H97 -> 0 | J107: o Guía de Familia | P107: =+O107*N107 -> 0
B108: o Socia de cocina | F108: =+'Unidad Productora'!F98 -> 0 | G108: =+'Unidad Productora'!G98 -> 0 | H108: =+'Unidad Productora'!H98 -> 0 | J108: o Socia de cocina | P108: =+O108*N108 -> 0
B109: o Repartidor | F109: =+'Unidad Productora'!F99 -> 0 | G109: =+'Unidad Productora'!G99 -> 0 | H109: =+'Unidad Productora'!H99 -> 0 | J109: o Repartidor | P109: =+O109*N109 -> 0
B110: o Apoyo de Limpieza y Vigilancia | F110: =+'Unidad Productora'!F100 -> 0 | G110: =+'Unidad Productora'!G100 -> 0 | H110: =+'Unidad Productora'!H100 -> 0 | J110: o Apoyo de Limpieza y Vigilancia | P110: =+O110*N110 -> 0
B111: · Equipo técnico profesional del PNCM: | F111: =+'Unidad Productora'!F101 -> 0 | G111: =+'Unidad Productora'!G101 -> 0 | H111: =+'Unidad Productora'!H101 -> 0 | J111: · Equipo técnico profesional del PNCM: | P111: =+O111*N111 -> 0
B112: o Acompañantes técnicos (AT) | F112: =+'Unidad Productora'!F102 -> 0 | G112: =+'Unidad Productora'!G102 -> 0 | H112: =+'Unidad Productora'!H102 -> 0 | J112: o Acompañantes técnicos (AT) | P112: =+O112*N112 -> 0
B113: o Especialistas integrales | F113: =+'Unidad Productora'!F103 -> 0 | G113: =+'Unidad Productora'!G103 -> 0 | H113: =+'Unidad Productora'!H103 -> 0 | J113: o Especialistas integrales | P113: =+O113*N113 -> 0
B114: o Especialistas en nutrición | F114: =+'Unidad Productora'!F104 -> 0 | G114: =+'Unidad Productora'!G104 -> 0 | H114: =+'Unidad Productora'!H104 -> 0 | J114: o Especialistas en nutrición | P114: =+O114*N114 -> 0
B115: b. Servicios | J115: b. Servicios
B116: · Servicios | F116: =+'Unidad Productora'!F110 -> 0 | G116: =+'Unidad Productora'!G110 -> 0 | J116: · Servicios
B117: o Agua | F117: =+'Unidad Productora'!F111 -> 0 | G117: =+'Unidad Productora'!G111 -> 0 | H117: =+'Unidad Productora'!H111 -> 0 | J117: o Agua | P117: =+O117*N117 -> 0
B118: o Luz | F118: =+'Unidad Productora'!F112 -> 0 | G118: =+'Unidad Productora'!G112 -> 0 | H118: =+'Unidad Productora'!H112 -> 0 | J118: o Luz | P118: =+O118*N118 -> 0
B119: o Internet | F119: =+'Unidad Productora'!F113 -> 0 | G119: =+'Unidad Productora'!G113 -> 0 | H119: =+'Unidad Productora'!H113 -> 0 | J119: o Internet | P119: =+O119*N119 -> 0
B120: o Seguridad | F120: =+'Unidad Productora'!F114 -> 0 | G120: =+'Unidad Productora'!G114 -> 0 | H120: =+'Unidad Productora'!H114 -> 0 | J120: o Seguridad | P120: =+O120*N120 -> 0
B121: o Mantenimiento | F121: =+'Unidad Productora'!F115 -> 0 | G121: =+'Unidad Productora'!G115 -> 0 | H121: =+'Unidad Productora'!H115 -> 0 | J121: o Mantenimiento | P121: =+O121*N121 -> 0
H122: =SUM(H105:H121) -> 0 | P122: =SUM(P105:P121) -> 0
B124: 9.04 Cronograma de inversión de metas financieras
B126: Fecha prevista de inicio de ejecución: | F126: =+Horizonte!I12 -> 0 | H126: (mes y año)
B127: Tipo de periodo | F127: Trimestre
B128: Número de periodos | H128: (valor)
B130: Componente | G130: Tipo de factor productivo | I130: Cronograma de inversión (trimestres) | Q130: Costo estimado de inversión a precios de mercado (Soles)
I131: Tri 1 | J131: Tri 2 | K131: Tri 3 | L131: Tri 4 | M131: Tri 5 | N131: Tri 6 | O131: Tri 7 | P131: Tri 8
B134: Componente 1:
B135: =+D6 | G135: Infraestructura | Q135: =+SUM(O11:O19) -> 0
B136: Componente 2
B137: =+D21 | G137: Equipamiento | Q137: =SUM(M25) -> 0
B138: Componente 3
B139: =+D28 | G139: Mobiliario | Q139: =SUM(M32:N33) -> 0
B140: Componente 4
B141: =+D36 | G141: Intangibles | Q141: =SUM(M40) -> 0
B142: Medidas de reducción del riesgo de desastre y mitigación ambiental
B143: Implementación de medidas | Q143: =SUM(N47:N62) -> 0
...

Sheet Evaluación Social Alt1
B2: SECCIÓN N°10: EVALUACIÓN SOCIAL - ALTERNATIVA 1
B4: 10.01 BENEFICIOS SOCIALES
B6: Benificios de la intervención
B8: Mayor acceso de niñas y niños de 6 a 36 meses, a raciones alimentarias y suplemento con hierro
B9: Niñas y niños de 6 a 36 meses reciben suficiente seguimiento al control CRED
B10: Adecuado desarrollo cognitivo de niñas y niños de 6 a 36 meses
B11: Ingesta adecuada de nutrientes por parte de niñas y niños de 6 a 36 meses
B12: Mayor nivel de desarrollo infantil temprano de los niños y niñas menores de 36 meses que viven en situación de pobreza y pobreza extrema
B15: 10.02 COSTOS SOCIALES
B17: Transformación de costos de inversión a precios sociales
B19: Detalle | F19: Costo a precios de mercado | G19: Factor de corrección | H19: Costo a precios sociales
B21: =+CostosAlt1!B134 -> Componente 1:
B22: =+CostosAlt1!B135 | F22: =+CostosAlt1!Q135 -> 0 | G22: =1/(1.18) -> 0.84745763 | H22: =+G22*F22 -> 0
B23: =+CostosAlt1!B136 -> Componente 2
B24: =+CostosAlt1!B137 | F24: =+CostosAlt1!Q137 -> 0 | G24: =1/(1.18) -> 0.84745763 | H24: =+G24*F24 -> 0
B25: =+CostosAlt1!B138 -> Componente 3
B26: =+CostosAlt1!B139 | F26: =+CostosAlt1!Q139 -> 0 | G26: =1/(1.18) -> 0.84745763 | H26: =+G26*F26 -> 0
B27: =+CostosAlt1!B140 -> Componente 4
B28: =+CostosAlt1!B141 | F28: =+CostosAlt1!Q141 -> 0 | G28: =1/(1.08) -> 0.92592593 | H28: =+G28*F28 -> 0
B29: =+CostosAlt1!B142 -> Medidas de reducción del riesgo de desastre y mitigación ambiental
B30: =+CostosAlt1!B143 -> Implementación de medidas | F30: =+CostosAlt1!Q143 -> 0 | G30: 0.79 | H30: =+G30*F30 -> 0
B31: =+CostosAlt1!B148 -> Gestión del proyecto | F31: =+CostosAlt1!L148 -> 0 | G31: =+G30 -> 0.79 | H31: =+G31*F31 -> 0
B32: =+CostosAlt1!B149 -> Expediente técnico o documento equivalente | F32: =+CostosAlt1!L149 -> 0 | G32: =+G31 -> 0.79 | H32: =+G32*F32 -> 0
B33: =+CostosAlt1!B150 -> Supervisión | F33: =+CostosAlt1!L150 -> 0 | G33: =+G32 -> 0.79 | H33: =+G33*F33 -> 0
B34: =+CostosAlt1!B151 -> Liquidación | F34: =+CostosAlt1!L151 -> 0 | G34: =+G33 -> 0.79 | H34: =+G34*F34 -> 0
B35: =+CostosAlt1!B152 -> Gastos generales | F35: =+CostosAlt1!L152 -> 0 | G35: =+G34 -> 0.79 | H35: =+G35*F35 -> 0
B36: Total | F36: =SUM(F22:F35) -> 0 | H36: =SUM(H22:H35) -> 0
B39: Transformación de costos de operación y mantenimiento a precios sociales
B41: Detalle | F41: Costo a precios de mercado | G41: Factor de corrección | H41: Costo a precios sociales
B43: Costos de operación incremental
B44: =+CostosAlt1!B103 -> a. Personal
B45: =+CostosAlt1!B104 -> · Actores comunales: | F45: =SUM(CostosAlt1!P104:P110)-SUM(CostosAlt1!H104:H110)*-1 -> 0 | G45: =+G34 -> 0.79 | H45: =+G45*F45 -> 0
B46: =+CostosAlt1!B111 -> · Equipo técnico profesional del PNCM: | F46: =SUM(CostosAlt1!P112:P114)-SUM(CostosAlt1!H112:H114) -> 0 | G46: =+G34 -> 0.79 | H46: =+G46*F46 -> 0
B47: =+CostosAlt1!B115 -> b. Servicios | F47: =SUM(CostosAlt1!P116:P121)-SUM(CostosAlt1!H116:H121)*-1 -> 0 | G47: =+G24 -> 0.84745763 | H47: =+G47*F47 -> 0
B48: Total | F48: =SUM(F43:F47) -> 0 | H48: =SUM(H43:H47) -> 0
B51: 10.03 FLUJO DE COSTOS A PRECIOS SOCIALES (EVALUACIÓN SOCIAL)
B53: Años | C53: =+Brecha!D13 | D53: =+Brecha!E13 | E53: =+Brecha!F13 | F53: =+Brecha!G13 | G53: =+Brecha!H13 | H53: =+Brecha!I13 | I53: =+Brecha!J13 | J53: =+Brecha!K13 | ... M53: =+Brecha!N13
B54: Costos de inversión, operación y mantenimiento a precios sociales
B55: 1. Costos de inversión | C55: =+H36 -> 0 | M55: =-H22*0.1 -> 0 | N55: *
B56: 2. Costos de reinversión | D56: =+SUM(CostosAlt1!F86:F93)*'Evaluación Social Alt1'!$G$24 -> 0 | E56: =+SUM(CostosAlt1!G86:G93)*'Evaluación Social Alt1'!$G$24 -> 0 | F56: =+SUM(CostosAlt1!H86:H93)*'Evaluación Social Alt1'!$G$24 -> 0 | G56: =+SUM(CostosAlt1!I86:I93)*'Evaluación Social Alt1'!$G$24 -> 0 | H56: =+SUM(CostosAlt1!J86:J93)*'Evaluación Social Alt1'!$G$24 -> 0 | I56: =+SUM(CostosAlt1!K86:K93)*'Evaluación Social Alt1'!$G$24 -> 0 | J56: =+SUM(CostosAlt1!L86:L93)*'Evaluación Social Alt1'!$G$24 -> 0 | K56: =+SUM(CostosAlt1!M86:M93)*'Evaluación Social Alt1'!$G$24 -> 0 | ... M56: =+SUM(CostosAlt1!O86:O93)*'Evaluación Social Alt1'!$G$24 -> 0
B57: 3. Costos de operación y mantenimiento incremental | D57: =+H48 -> 0 | E57: =+D57 -> 0 | F57: =+E57 -> 0 | G57: =+F57 -> 0 | H57: =+G57 -> 0 | I57: =+H57 -> 0 | J57: =+I57 -> 0 | K57: =+J57 -> 0 | L57: =+K57 -> 0 | M57: =+L57 -> 0
B58: Total Costos | C58: =SUM(C55:C57) -> 0 | D58: =SUM(D55:D57) -> 0 | E58: =SUM(E55:E57) -> 0 | F58: =SUM(F55:F57) -> 0 | G58: =SUM(G55:G57) -> 0 | H58: =SUM(H55:H57) -> 0 | I58: =SUM(I55:I57) -> 0 | J58: =SUM(J55:J57) -> 0 | ... M58: =SUM(M55:M57) -> 0
B59: * Se considera el 10% como valor de recuperación de la inversión en infraestructura
B61: 10.04 INDICADORES DE RENTABILIDAD SOCIAL
B63: Tipo | C63: Criterio de elección** | F63: Alternativa 1
B64: Costo / Eficacia a precios sociales | C64: Valor Actual de los Costos (VAC) | F64: =+NPV(0.08,D58:M58)+C58 -> 0
C65: Costo por beneficiario directo | F65: =+IF($F$64>0,F64/SUM(Brecha!D19:N19),"")
B68: 10.05 ANÁLISIS DE SENSIBILIDAD
B70: ANALISIS DE SENSIBILIDAD BIDIMENSIONAL
B71: ICE (S/) | D71: Variación % de los costos del proyecto
D72: 20 | E72: 15 | F72: 10 | G72: 0 | H72: -10 | I72: -15 | J72: -20
B73: Variación % del total de beneficiarios | C73: 35 | D73: =+IF($F$64>0,($F$64*(1+(D$72/100)))/(SUM(Brecha!$D$19:$N$19)*(1+($C73/100))),"") | E73: =+IF($F$64>0,($F$64*(1+(E$72/100)))/(SUM(Brecha!$D$19:$N$19)*(1+($C73/100))),"") | F73: =+IF($F$64>0,($F$64*(1+(F$72/100)))/(SUM(Brecha!$D$19:$N$19)*(1+($C73/100))),"") | G73: =+IF($F$64>0,($F$64*(1+(G$72/100)))/(SUM(Brecha!$D$19:$N$19)*(1+($C73/100))),"") | H73: =+IF($F$64>0,($F$64*(1+(H$72/100)))/(SUM(Brecha!$D$19:$N$19)*(1+($C73/100))),"") | I73: =+IF($F$64>0,($F$64*(1+(I$72/100)))/(SUM(Brecha!$D$19:$N$19)*(1+($C73/100))),"") | J73: =+IF($F$64>0,($F$64*(1+(J$72/100)))/(SUM(Brecha!$D$19:$N$19)*(1+($C73/100))),"")
C74: 25 | D74: =+IF($F$64>0,($F$64*(1+(D$72/100)))/(SUM(Brecha!$D$19:$N$19)*(1+($C74/100))),"") | E74: =+IF($F$64>0,($F$64*(1+(E$72/100)))/(SUM(Brecha!$D$19:$N$19)*(1+($C74/100))),"") | F74: =+IF($F$64>0,($F$64*(1+(F$72/100)))/(SUM(Brecha!$D$19:$N$19)*(1+($C74/100))),"") | G74: =+IF($F$64>0,($F$64*(1+(G$72/100)))/(SUM(Brecha!$D$19:$N$19)*(1+($C74/100))),"") | H74: =+IF($F$64>0,($F$64*(1+(H$72/100)))/(SUM(Brecha!$D$19:$N$19)*(1+($C74/100))),"") | I74: =+IF($F$64>0,($F$64*(1+(I$72/100)))/(SUM(Brecha!$D$19:$N$19)*(1+($C74/100))),"") | J74: =+IF($F$64>0,($F$64*(1+(J$72/100)))/(SUM(Brecha!$D$19:$N$19)*(1+($C74/100))),"")
C75: 15 | D75: =+IF($F$64>0,($F$64*(1+(D$72/100)))/(SUM(Brecha!$D$19:$N$19)*(1+($C75/100))),"") | E75: =+IF($F$64>0,($F$64*(1+(E$72/100)))/(SUM(Brecha!$D$19:$N$19)*(1+($C75/100))),"") | F75: =+IF($F$64>0,($F$64*(1+(F$72/100)))/(SUM(Brecha!$D$19:$N$19)*(1+($C75/100))),"") | G75: =+IF($F$64>0,($F$64*(1+(G$72/100)))/(SUM(Brecha!$D$19:$N$19)*(1+($C75/100))),"") | H75: =+IF($F$64>0,($F$64*(1+(H$72/100)))/(SUM(Brecha!$D$19:$N$19)*(1+($C75/100))),"") | I75: =+IF($F$64>0,($F$64*(1+(I$72/100)))/(SUM(Brecha!$D$19:$N$19)*(1+($C75/100))),"") | J75: =+IF($F$64>0,($F$64*(1+(J$72/100)))/(SUM(Brecha!$D$19:$N$19)*(1+($C75/100))),"")
C76: 0 | D76: =+IF($F$64>0,($F$64*(1+(D$72/100)))/(SUM(Brecha!$D$19:$N$19)*(1+($C76/100))),"") | E76: =+IF($F$64>0,($F$64*(1+(E$72/100)))/(SUM(Brecha!$D$19:$N$19)*(1+($C76/100))),"") | F76: =+IF($F$64>0,($F$64*(1+(F$72/100)))/(SUM(Brecha!$D$19:$N$19)*(1+($C76/100))),"") | G76: =+IF($F$64>0,($F$64*(1+(G$72/100)))/(SUM(Brecha!$D$19:$N$19)*(1+($C76/100))),"") | H76: =+IF($F$64>0,($F$64*(1+(H$72/100)))/(SUM(Brecha!$D$19:$N$19)*(1+($C76/100))),"") | I76: =+IF($F$64>0,($F$64*(1+(I$72/100)))/(SUM(Brecha!$D$19:$N$19)*(1+($C76/100))),"") | J76: =+IF($F$64>0,($F$64*(1+(J$72/100)))/(SUM(Brecha!$D$19:$N$19)*(1+($C76/100))),"")
C77: -15 | D77: =+IF($F$64>0,($F$64*(1+(D$72/100)))/(SUM(Brecha!$D$19:$N$19)*(1+($C77/100))),"") | E77: =+IF($F$64>0,($F$64*(1+(E$72/100)))/(SUM(Brecha!$D$19:$N$19)*(1+($C77/100))),"") | F77: =+IF($F$64>0,($F$64*(1+(F$72/100)))/(SUM(Brecha!$D$19:$N$19)*(1+($C77/100))),"") | G77: =+IF($F$64>0,($F$64*(1+(G$72/100)))/(SUM(Brecha!$D$19:$N$19)*(1+($C77/100))),"") | H77: =+IF($F$64>0,($F$64*(1+(H$72/100)))/(SUM(Brecha!$D$19:$N$19)*(1+($C77/100))),"") | I77: =+IF($F$64>0,($F$64*(1+(I$72/100)))/(SUM(Brecha!$D$19:$N$19)*(1+($C77/100))),"") | J77: =+IF($F$64>0,($F$64*(1+(J$72/100)))/(SUM(Brecha!$D$19:$N$19)*(1+($C77/100))),"")
C78: -25 | D78: =+IF($F$64>0,($F$64*(1+(D$72/100)))/(SUM(Brecha!$D$19:$N$19)*(1+($C78/100))),"") | E78: =+IF($F$64>0,($F$64*(1+(E$72/100)))/(SUM(Brecha!$D$19:$N$19)*(1+($C78/100))),"") | F78: =+IF($F$64>0,($F$64*(1+(F$72/100)))/(SUM(Brecha!$D$19:$N$19)*(1+($C78/100))),"") | G78: =+IF($F$64>0,($F$64*(1+(G$72/100)))/(SUM(Brecha!$D$19:$N$19)*(1+($C78/100))),"") | H78: =+IF($F$64>0,($F$64*(1+(H$72/100)))/(SUM(Brecha!$D$19:$N$19)*(1+($C78/100))),"") | I78: =+IF($F$64>0,($F$64*(1+(I$72/100)))/(SUM(Brecha!$D$19:$N$19)*(1+($C78/100))),"") | J78: =+IF($F$64>0,($F$64*(1+(J$72/100)))/(SUM(Brecha!$D$19:$N$19)*(1+($C78/100))),"")
C79: -35 | D79: =+IF($F$64>0,($F$64*(1+(D$72/100)))/(SUM(Brecha!$D$19:$N$19)*(1+($C79/100))),"") | E79: =+IF($F$64>0,($F$64*(1+(E$72/100)))/(SUM(Brecha!$D$19:$N$19)*(1+($C79/100))),"") | F79: =+IF($F$64>0,($F$64*(1+(F$72/100)))/(SUM(Brecha!$D$19:$N$19)*(1+($C79/100))),"") | G79: =+IF($F$64>0,($F$64*(1+(G$72/100)))/(SUM(Brecha!$D$19:$N$19)*(1+($C79/100))),"") | H79: =+IF($F$64>0,($F$64*(1+(H$72/100)))/(SUM(Brecha!$D$19:$N$19)*(1+($C79/100))),"") | I79: =+IF($F$64>0,($F$64*(1+(I$72/100)))/(SUM(Brecha!$D$19:$N$19)*(1+($C79/100))),"") | J79: =+IF($F$64>0,($F$64*(1+(J$72/100)))/(SUM(Brecha!$D$19:$N$19)*(1+($C79/100))),"")

Sheet Evaluación Social Alt2
B2: SECCIÓN N°10: EVALUACIÓN SOCIAL - ALTERNATIVA 2
B4: 10.01 BENEFICIOS SOCIALES
B6: Benificios de la intervención
B8: Mayor acceso de niñas y niños de 6 a 36 meses, a raciones alimentarias y suplemento con hierro
B9: Niñas y niños de 6 a 36 meses reciben suficiente seguimiento al control CRED
B10: Adecuado desarrollo cognitivo de niñas y niños de 6 a 36 meses
B11: Ingesta adecuada de nutrientes por parte de niñas y niños de 6 a 36 meses
B12: Mayor nivel de desarrollo infantil temprano de los niños y niñas menores de 36 meses que viven en situación de pobreza y pobreza extrema
B15: 10.02 COSTOS SOCIALES
B17: Transformación de costos de inversión a precios sociales
B19: Detalle | F19: Costo a precios de mercado | G19: Factor de corrección | H19: Costo a precios sociales
B21: =+CostosAlt2!B134 -> Componente 1:
B22: =+CostosAlt2!B135 | F22: =+CostosAlt2!Q135 -> 0 | G22: =1/(1.18) -> 0.84745763 | H22: =+G22*F22 -> 0
B23: =+CostosAlt2!B136 -> Componente 2
B24: =+CostosAlt2!B137 | F24: =+CostosAlt2!Q137 -> 0 | G24: =1/(1.18) -> 0.84745763 | H24: =+G24*F24 -> 0
B25: =+CostosAlt2!B138 -> Componente 3
B26: =+CostosAlt2!B139 | F26: =+CostosAlt2!Q139 -> 0 | G26: =1/(1.18) -> 0.84745763 | H26: =+G26*F26 -> 0
B27: =+CostosAlt2!B140 -> Componente 4
B28: =+CostosAlt2!B141 | F28: =+CostosAlt2!Q141 -> 0 | G28: =1/(1.08) -> 0.92592593 | H28: =+G28*F28 -> 0
B29: =+CostosAlt2!B142 -> Medidas de reducción del riesgo de desastre y mitigación ambiental
B30: =+CostosAlt2!B143 -> Implementación de medidas | F30: =+CostosAlt2!Q143 -> 0 | G30: 0.79 | H30: =+G30*F30 -> 0
B31: =+CostosAlt2!B148 -> Gestión del proyecto | F31: =+CostosAlt2!L148 -> 0 | G31: =+G30 -> 0.79 | H31: =+G31*F31 -> 0
B32: =+CostosAlt2!B149 -> Expediente técnico o documento equivalente | F32: =+CostosAlt2!L149 -> 0 | G32: =+G31 -> 0.79 | H32: =+G32*F32 -> 0
B33: =+CostosAlt2!B150 -> Supervisión | F33: =+CostosAlt2!L150 -> 0 | G33: =+G32 -> 0.79 | H33: =+G33*F33 -> 0
B34: =+CostosAlt2!B151 -> Liquidación | F34: =+CostosAlt2!L151 -> 0 | G34: =+G33 -> 0.79 | H34: =+G34*F34 -> 0
B35: =+CostosAlt2!B152 -> Gastos generales | F35: =+CostosAlt2!L152 -> 0 | G35: =+G34 -> 0.79 | H35: =+G35*F35 -> 0
B36: Total | F36: =SUM(F22:F35) -> 0 | H36: =SUM(H22:H35) -> 0
B39: Transformación de costos de operación y mantenimiento a precios sociales
B41: Detalle | F41: Costo a precios de mercado | G41: Factor de corrección | H41: Costo a precios sociales
B43: Costos de operación incremental
B44: =+CostosAlt2!B103 -> a. Personal
B45: =+CostosAlt2!B104 -> · Actores comunales: | F45: =SUM(CostosAlt2!P104:P110)-SUM(CostosAlt2!H104:H110) -> 0 | G45: =+'Evaluación Social Alt1'!G45 -> 0.79 | H45: =+G45*F45 -> 0
B46: =+CostosAlt2!B111 -> · Equipo técnico profesional del PNCM: | F46: =SUM(CostosAlt2!P112:P114)-SUM(CostosAlt2!H112:H114) -> 0 | G46: =+'Evaluación Social Alt1'!G46 -> 0.79 | H46: =+G46*F46 -> 0
B47: =+CostosAlt2!B115 -> b. Servicios | F47: =SUM(CostosAlt2!P116:P121)-SUM(CostosAlt2!H116:H121) -> 0 | G47: =+'Evaluación Social Alt1'!G47 -> 0.84745763 | H47: =+G47*F47 -> 0
B48: Total | F48: =SUM(F43:F47) -> 0 | H48: =SUM(H43:H47) -> 0
B51: 10.03 FLUJO DE COSTOS A PRECIOS SOCIALES (EVALUACIÓN SOCIAL)
B53: Años | C53: =+Brecha!D13 | D53: =+Brecha!E13 | E53: =+Brecha!F13 | F53: =+Brecha!G13 | G53: =+Brecha!H13 | H53: =+Brecha!I13 | I53: =+Brecha!J13 | J53: =+Brecha!K13 | ... M53: =+Brecha!N13
B54: Costos de inversión, operación y mantenimiento a precios sociales
B55: 1. Costos de inversión | C55: =+H36 -> 0 | M55: =-H22*0.1 -> 0 | N55: *
B56: 2. Costos de reinversión | D56: =+SUM(CostosAlt2!F86:F93)*'Evaluación Social Alt2'!$G$24 -> 0 | E56: =+SUM(CostosAlt2!G86:G93)*'Evaluación Social Alt2'!$G$24 -> 0 | F56: =+SUM(CostosAlt2!H86:H93)*'Evaluación Social Alt2'!$G$24 -> 0 | G56: =+SUM(CostosAlt2!I86:I93)*'Evaluación Social Alt2'!$G$24 -> 0 | H56: =+SUM(CostosAlt2!J86:J93)*'Evaluación Social Alt2'!$G$24 -> 0 | I56: =+SUM(CostosAlt2!K86:K93)*'Evaluación Social Alt2'!$G$24 -> 0 | J56: =+SUM(CostosAlt2!L86:L93)*'Evaluación Social Alt2'!$G$24 -> 0 | K56: =+SUM(CostosAlt2!M86:M93)*'Evaluación Social Alt2'!$G$24 -> 0 | ... M56: =+SUM(CostosAlt2!O86:O93)*'Evaluación Social Alt2'!$G$24 -> 0
B57: 3. Costos de operación y mantenimiento incremental | D57: =+H48 -> 0 | E57: =+D57 -> 0 | F57: =+E57 -> 0 | G57: =+F57 -> 0 | H57: =+G57 -> 0 | I57: =+H57 -> 0 | J57: =+I57 -> 0 | K57: =+J57 -> 0 | L57: =+K57 -> 0 | M57: =+L57 -> 0
B58: Total Costos | C58: =SUM(C55:C57) -> 0 | D58: =SUM(D55:D57) -> 0 | E58: =SUM(E55:E57) -> 0 | F58: =SUM(F55:F57) -> 0 | G58: =SUM(G55:G57) -> 0 | H58: =SUM(H55:H57) -> 0 | I58: =SUM(I55:I57) -> 0 | J58: =SUM(J55:J57) -> 0 | ... M58: =SUM(M55:M57) -> 0
B59: * Se considera el 10% como valor de recuperación de la inversión en infraestructura
B61: 10.04 INDICADORES DE RENTABILIDAD SOCIAL
B63: Tipo | C63: Criterio de elección** | F63: Alternativa 1
B64: Costo / Eficacia a precios sociales | C64: Valor Actual de los Costos (VAC) | F64: =+NPV(0.08,D58:M58)+C58 -> 0
C65: Costo por beneficiario directo | F65: =+IF($F$64>0,F64/SUM(Brecha!D19:N19),"")
B68: 10.05 ANÁLISIS DE SENSIBILIDAD
B70: ANALISIS DE SENSIBILIDAD BIDIMENSIONAL
B71: ICE / VAN | D71: Variación % de los costos del proyecto
D72: 20 | E72: 15 | F72: 10 | G72: 0 | H72: -10 | I72: -15 | J72: -20
B73: Variación % del total de beneficiarios | C73: 35 | D73: =+IF($F$64>0,($F$64*(1+(D$72/100)))/(SUM(Brecha!$D$19:$N$19)*(1+($C73/100))),"") | E73: =+IF($F$64>0,($F$64*(1+(E$72/100)))/(SUM(Brecha!$D$19:$N$19)*(1+($C73/100))),"") | F73: =+IF($F$64>0,($F$64*(1+(F$72/100)))/(SUM(Brecha!$D$19:$N$19)*(1+($C73/100))),"") | G73: =+IF($F$64>0,($F$64*(1+(G$72/100)))/(SUM(Brecha!$D$19:$N$19)*(1+($C73/100))),"") | H73: =+IF($F$64>0,($F$64*(1+(H$72/100)))/(SUM(Brecha!$D$19:$N$19)*(1+($C73/100))),"") | I73: =+IF($F$64>0,($F$64*(1+(I$72/100)))/(SUM(Brecha!$D$19:$N$19)*(1+($C73/100))),"") | J73: =+IF($F$64>0,($F$64*(1+(J$72/100)))/(SUM(Brecha!$D$19:$N$19)*(1+($C73/100))),"")
C74: 25 | D74: =+IF($F$64>0,($F$64*(1+(D$72/100)))/(SUM(Brecha!$D$19:$N$19)*(1+($C74/100))),"") | E74: =+IF($F$64>0,($F$64*(1+(E$72/100)))/(SUM(Brecha!$D$19:$N$19)*(1+($C74/100))),"") | F74: =+IF($F$64>0,($F$64*(1+(F$72/100)))/(SUM(Brecha!$D$19:$N$19)*(1+($C74/100))),"") | G74: =+IF($F$64>0,($F$64*(1+(G$72/100)))/(SUM(Brecha!$D$19:$N$19)*(1+($C74/100))),"") | H74: =+IF($F$64>0,($F$64*(1+(H$72/100)))/(SUM(Brecha!$D$19:$N$19)*(1+($C74/100))),"") | I74: =+IF($F$64>0,($F$64*(1+(I$72/100)))/(SUM(Brecha!$D$19:$N$19)*(1+($C74/100))),"") | J74: =+IF($F$64>0,($F$64*(1+(J$72/100)))/(SUM(Brecha!$D$19:$N$19)*(1+($C74/100))),"")
C75: 15 | D75: =+IF($F$64>0,($F$64*(1+(D$72/100)))/(SUM(Brecha!$D$19:$N$19)*(1+($C75/100))),"") | E75: =+IF($F$64>0,($F$64*(1+(E$72/100)))/(SUM(Brecha!$D$19:$N$19)*(1+($C75/100))),"") | F75: =+IF($F$64>0,($F$64*(1+(F$72/100)))/(SUM(Brecha!$D$19:$N$19)*(1+($C75/100))),"") | G75: =+IF($F$64>0,($F$64*(1+(G$72/100)))/(SUM(Brecha!$D$19:$N$19)*(1+($C75/100))),"") | H75: =+IF($F$64>0,($F$64*(1+(H$72/100)))/(SUM(Brecha!$D$19:$N$19)*(1+($C75/100))),"") | I75: =+IF($F$64>0,($F$64*(1+(I$72/100)))/(SUM(Brecha!$D$19:$N$19)*(1+($C75/100))),"") | J75: =+IF($F$64>0,($F$64*(1+(J$72/100)))/(SUM(Brecha!$D$19:$N$19)*(1+($C75/100))),"")
C76: 0 | D76: =+IF($F$64>0,($F$64*(1+(D$72/100)))/(SUM(Brecha!$D$19:$N$19)*(1+($C76/100))),"") | E76: =+IF($F$64>0,($F$64*(1+(E$72/100)))/(SUM(Brecha!$D$19:$N$19)*(1+($C76/100))),"") | F76: =+IF($F$64>0,($F$64*(1+(F$72/100)))/(SUM(Brecha!$D$19:$N$19)*(1+($C76/100))),"") | G76: =+IF($F$64>0,($F$64*(1+(G$72/100)))/(SUM(Brecha!$D$19:$N$19)*(1+($C76/100))),"") | H76: =+IF($F$64>0,($F$64*(1+(H$72/100)))/(SUM(Brecha!$D$19:$N$19)*(1+($C76/100))),"") | I76: =+IF($F$64>0,($F$64*(1+(I$72/100)))/(SUM(Brecha!$D$19:$N$19)*(1+($C76/100))),"") | J76: =+IF($F$64>0,($F$64*(1+(J$72/100)))/(SUM(Brecha!$D$19:$N$19)*(1+($C76/100))),"")
C77: -15 | D77: =+IF($F$64>0,($F$64*(1+(D$72/100)))/(SUM(Brecha!$D$19:$N$19)*(1+($C77/100))),"") | E77: =+IF($F$64>0,($F$64*(1+(E$72/100)))/(SUM(Brecha!$D$19:$N$19)*(1+($C77/100))),"") | F77: =+IF($F$64>0,($F$64*(1+(F$72/100)))/(SUM(Brecha!$D$19:$N$19)*(1+($C77/100))),"") | G77: =+IF($F$64>0,($F$64*(1+(G$72/100)))/(SUM(Brecha!$D$19:$N$19)*(1+($C77/100))),"") | H77: =+IF($F$64>0,($F$64*(1+(H$72/100)))/(SUM(Brecha!$D$19:$N$19)*(1+($C77/100))),"") | I77: =+IF($F$64>0,($F$64*(1+(I$72/100)))/(SUM(Brecha!$D$19:$N$19)*(1+($C77/100))),"") | J77: =+IF($F$64>0,($F$64*(1+(J$72/100)))/(SUM(Brecha!$D$19:$N$19)*(1+($C77/100))),"")
C78: -25 | D78: =+IF($F$64>0,($F$64*(1+(D$72/100)))/(SUM(Brecha!$D$19:$N$19)*(1+($C78/100))),"") | E78: =+IF($F$64>0,($F$64*(1+(E$72/100)))/(SUM(Brecha!$D$19:$N$19)*(1+($C78/100))),"") | F78: =+IF($F$64>0,($F$64*(1+(F$72/100)))/(SUM(Brecha!$D$19:$N$19)*(1+($C78/100))),"") | G78: =+IF($F$64>0,($F$64*(1+(G$72/100)))/(SUM(Brecha!$D$19:$N$19)*(1+($C78/100))),"") | H78: =+IF($F$64>0,($F$64*(1+(H$72/100)))/(SUM(Brecha!$D$19:$N$19)*(1+($C78/100))),"") | I78: =+IF($F$64>0,($F$64*(1+(I$72/100)))/(SUM(Brecha!$D$19:$N$19)*(1+($C78/100))),"") | J78: =+IF($F$64>0,($F$64*(1+(J$72/100)))/(SUM(Brecha!$D$19:$N$19)*(1+($C78/100))),"")
C79: -35 | D79: =+IF($F$64>0,($F$64*(1+(D$72/100)))/(SUM(Brecha!$D$19:$N$19)*(1+($C79/100))),"") | E79: =+IF($F$64>0,($F$64*(1+(E$72/100)))/(SUM(Brecha!$D$19:$N$19)*(1+($C79/100))),"") | F79: =+IF($F$64>0,($F$64*(1+(F$72/100)))/(SUM(Brecha!$D$19:$N$19)*(1+($C79/100))),"") | G79: =+IF($F$64>0,($F$64*(1+(G$72/100)))/(SUM(Brecha!$D$19:$N$19)*(1+($C79/100))),"") | H79: =+IF($F$64>0,($F$64*(1+(H$72/100)))/(SUM(Brecha!$D$19:$N$19)*(1+($C79/100))),"") | I79: =+IF($F$64>0,($F$64*(1+(I$72/100)))/(SUM(Brecha!$D$19:$N$19)*(1+($C79/100))),"") | J79: =+IF($F$64>0,($F$64*(1+(J$72/100)))/(SUM(Brecha!$D$19:$N$19)*(1+($C79/100))),"")

Sheet Evaluación Social Alt3
B2: SECCIÓN N°10: EVALUACIÓN SOCIAL - ALTERNATIVA 3
B4: 10.01 BENEFICIOS SOCIALES
B6: Benificios de la intervención
B8: Mayor acceso de niñas y niños de 6 a 36 meses, a raciones alimentarias y suplemento con hierro
B9: Niñas y niños de 6 a 36 meses reciben suficiente seguimiento al control CRED
B10: Adecuado desarrollo cognitivo de niñas y niños de 6 a 36 meses
B11: Ingesta adecuada de nutrientes por parte de niñas y niños de 6 a 36 meses
B12: Mayor nivel de desarrollo infantil temprano de los niños y niñas menores de 36 meses que viven en situación de pobreza y pobreza extrema
B15: 10.02 COSTOS SOCIALES
B17: Transformación de costos de inversión a precios sociales
B19: Detalle | F19: Costo a precios de mercado | G19: Factor de corrección | H19: Costo a precios sociales
B21: =+CostosAlt3!B133 -> 0
B22: =+CostosAlt3!B134 -> Componente 1: | F22: =+CostosAlt3!Q134 -> 0 | G22: =1/(1.18) -> 0.84745763 | H22: =+G22*F22 -> 0
B23: =+CostosAlt3!B135
B24: =+CostosAlt3!B136 -> Componente 2 | F24: =+CostosAlt3!Q136 -> 0 | G24: =1/(1.18) -> 0.84745763 | H24: =+G24*F24 -> 0
B25: =+CostosAlt3!B137
B26: =+CostosAlt3!B138 -> Componente 3 | F26: =+CostosAlt3!Q138 -> 0 | G26: =1/(1.18) -> 0.84745763 | H26: =+G26*F26 -> 0
B27: =+CostosAlt3!B139
B28: =+CostosAlt3!B140 -> Componente 4 | F28: =+CostosAlt3!Q140 -> 0 | G28: =1/(1.08) -> 0.92592593 | H28: =+G28*F28 -> 0
B29: =+CostosAlt3!B141
B30: =+CostosAlt3!B142 -> Medidas de reducción del riesgo de desastre y mitigación ambiental | F30: =+CostosAlt3!Q142 -> 0 | G30: 0.79 | H30: =+G30*F30 -> 0
B31: =+CostosAlt3!B147 -> 0 | F31: =+CostosAlt3!L147 -> 0 | G31: =+G30 -> 0.79 | H31: =+G31*F31 -> 0
B32: =+CostosAlt3!B148 -> Gestión del proyecto | F32: =+CostosAlt3!L148 -> 0 | G32: =+G31 -> 0.79 | H32: =+G32*F32 -> 0
B33: =+CostosAlt3!B149 -> Expediente técnico o documento equivalente | F33: =+CostosAlt3!L149 -> 0 | G33: =+G32 -> 0.79 | H33: =+G33*F33 -> 0
B34: =+CostosAlt3!B150 -> Supervisión | F34: =+CostosAlt3!L150 -> 0 | G34: =+G33 -> 0.79 | H34: =+G34*F34 -> 0
B35: =+CostosAlt3!B151 -> Liquidación | F35: =+CostosAlt3!L151 -> 0 | G35: =+G34 -> 0.79 | H35: =+G35*F35 -> 0
B36: Total | F36: =SUM(F22:F35) -> 0 | H36: =SUM(H22:H35) -> 0
B39: Transformación de costos de operación y mantenimiento a precios sociales
B41: Detalle | F41: Costo a precios de mercado | G41: Factor de corrección | H41: Costo a precios sociales
B43: Costos de operación incremental
B44: =+CostosAlt3!B102 -> 0
B45: =+CostosAlt3!B103 -> a. Personal | F45: =SUM(CostosAlt3!P103:P109)-SUM(CostosAlt3!H103:H109) -> 0 | G45: =+'Evaluación Social Alt2'!G45 -> 0.79 | H45: =+G45*F45 -> 0
B46: =+CostosAlt3!B110 -> o Apoyo de Limpieza y Vigilancia | F46: =SUM(CostosAlt3!P111:P113)-SUM(CostosAlt3!H111:H113) -> 0 | G46: =+'Evaluación Social Alt2'!G46 -> 0.79 | H46: =+G46*F46 -> 0
B47: =+CostosAlt3!B114 -> o Especialistas en nutrición | F47: =SUM(CostosAlt3!P115:P120)-SUM(CostosAlt3!H115:H120) -> 0 | G47: =+'Evaluación Social Alt2'!G47 -> 0.84745763 | H47: =+G47*F47 -> 0
B48: Total | F48: =SUM(F43:F47) -> 0 | H48: =SUM(H43:H47) -> 0
B51: 10.03 FLUJO DE COSTOS A PRECIOS SOCIALES (EVALUACIÓN SOCIAL)
B53: Años | C53: =+Brecha!D13 | D53: =+Brecha!E13 | E53: =+Brecha!F13 | F53: =+Brecha!G13 | G53: =+Brecha!H13 | H53: =+Brecha!I13 | I53: =+Brecha!J13 | J53: =+Brecha!K13 | ... M53: =+Brecha!N13
B54: Costos de inversión, operación y mantenimiento a precios sociales
B55: 1. Costos de inversión | C55: =+H36 -> 0 | M55: =-H22*0.1 -> 0 | N55: *
B56: 2. Costos de reinversión | D56: =+SUM(CostosAlt3!F85:F92)*'Evaluación Social Alt3'!$G$24 -> 0 | E56: =+SUM(CostosAlt3!G85:G92)*'Evaluación Social Alt3'!$G$24 -> 0 | F56: =+SUM(CostosAlt3!H85:H92)*'Evaluación Social Alt3'!$G$24 -> 0 | G56: =+SUM(CostosAlt3!I85:I92)*'Evaluación Social Alt3'!$G$24 -> 0 | H56: =+SUM(CostosAlt3!J85:J92)*'Evaluación Social Alt3'!$G$24 -> 0 | I56: =+SUM(CostosAlt3!K85:K92)*'Evaluación Social Alt3'!$G$24 -> 0 | J56: =+SUM(CostosAlt3!L85:L92)*'Evaluación Social Alt3'!$G$24 -> 0 | K56: =+SUM(CostosAlt3!M85:M92)*'Evaluación Social Alt3'!$G$24 -> 0 | ... M56: =+SUM(CostosAlt3!O85:O92)*'Evaluación Social Alt3'!$G$24 -> 0
B57: 3. Costos de operación y mantenimiento incremental | D57: =+H48 -> 0 | E57: =+D57 -> 0 | F57: =+E57 -> 0 | G57: =+F57 -> 0 | H57: =+G57 -> 0 | I57: =+H57 -> 0 | J57: =+I57 -> 0 | K57: =+J57 -> 0 | L57: =+K57 -> 0 | M57: =+L57 -> 0
B58: Total Costos | C58: =SUM(C55:C57) -> 0 | D58: =SUM(D55:D57) -> 0 | E58: =SUM(E55:E57) -> 0 | F58: =SUM(F55:F57) -> 0 | G58: =SUM(G55:G57) -> 0 | H58: =SUM(H55:H57) -> 0 | I58: =SUM(I55:I57) -> 0 | J58: =SUM(J55:J57) -> 0 | ... M58: =SUM(M55:M57) -> 0
B59: * Se considera el 10% como valor de recuperación de la inversión en infraestructura
B61: 10.04 INDICADORES DE RENTABILIDAD SOCIAL
B63: Tipo | C63: Criterio de elección** | F63: Alternativa 1
B64: Costo / Eficacia a precios sociales | C64: Valor Actual de los Costos (VAC) | F64: =+NPV(0.08,D58:M58)+C58 -> 0
C65: Costo por beneficiario directo | F65: =+IF($F$64>0,F64/SUM(Brecha!D19:N19),"")
B68: 10.05 ANÁLISIS DE SENSIBILIDAD
B70: ANALISIS DE SENSIBILIDAD BIDIMENSIONAL
B71: ICE / VAN | D71: Variación % de los costos del proyecto
D72: 20 | E72: 15 | F72: 10 | G72: 0 | H72: -10 | I72: -15 | J72: -20
B73: Variación % del total de beneficiarios | C73: 35 | D73: =+IF($F$64>0,($F$64*(1+(D$72/100)))/(SUM(Brecha!$D$19:$N$19)*(1+($C73/100))),"") | E73: =+IF($F$64>0,($F$64*(1+(E$72/100)))/(SUM(Brecha!$D$19:$N$19)*(1+($C73/100))),"") | F73: =+IF($F$64>0,($F$64*(1+(F$72/100)))/(SUM(Brecha!$D$19:$N$19)*(1+($C73/100))),"") | G73: =+IF($F$64>0,($F$64*(1+(G$72/100)))/(SUM(Brecha!$D$19:$N$19)*(1+($C73/100))),"") | H73: =+IF($F$64>0,($F$64*(1+(H$72/100)))/(SUM(Brecha!$D$19:$N$19)*(1+($C73/100))),"") | I73: =+IF($F$64>0,($F$64*(1+(I$72/100)))/(SUM(Brecha!$D$19:$N$19)*(1+($C73/100))),"") | J73: =+IF($F$64>0,($F$64*(1+(J$72/100)))/(SUM(Brecha!$D$19:$N$19)*(1+($C73/100))),"")
C74: 25 | D74: =+IF($F$64>0,($F$64*(1+(D$72/100)))/(SUM(Brecha!$D$19:$N$19)*(1+($C74/100))),"") | E74: =+IF($F$64>0,($F$64*(1+(E$72/100)))/(SUM(Brecha!$D$19:$N$19)*(1+($C74/100))),"") | F74: =+IF($F$64>0,($F$64*(1+(F$72/100)))/(SUM(Brecha!$D$19:$N$19)*(1+($C74/100))),"") | G74: =+IF($F$64>0,($F$64*(1+(G$72/100)))/(SUM(Brecha!$D$19:$N$19)*(1+($C74/100))),"") | H74: =+IF($F$64>0,($F$64*(1+(H$72/100)))/(SUM(Brecha!$D$19:$N$19)*(1+($C74/100))),"") | I74: =+IF($F$64>0,($F$64*(1+(I$72/100)))/(SUM(Brecha!$D$19:$N$19)*(1+($C74/100))),"") | J74: =+IF($F$64>0,($F$64*(1+(J$72/100)))/(SUM(Brecha!$D$19:$N$19)*(1+($C74/100))),"")
C75: 15 | D75: =+IF($F$64>0,($F$64*(1+(D$72/100)))/(SUM(Brecha!$D$19:$N$19)*(1+($C75/100))),"") | E75: =+IF($F$64>0,($F$64*(1+(E$72/100)))/(SUM(Brecha!$D$19:$N$19)*(1+($C75/100))),"") | F75: =+IF($F$64>0,($F$64*(1+(F$72/100)))/(SUM(Brecha!$D$19:$N$19)*(1+($C75/100))),"") | G75: =+IF($F$64>0,($F$64*(1+(G$72/100)))/(SUM(Brecha!$D$19:$N$19)*(1+($C75/100))),"") | H75: =+IF($F$64>0,($F$64*(1+(H$72/100)))/(SUM(Brecha!$D$19:$N$19)*(1+($C75/100))),"") | I75: =+IF($F$64>0,($F$64*(1+(I$72/100)))/(SUM(Brecha!$D$19:$N$19)*(1+($C75/100))),"") | J75: =+IF($F$64>0,($F$64*(1+(J$72/100)))/(SUM(Brecha!$D$19:$N$19)*(1+($C75/100))),"")
C76: 0 | D76: =+IF($F$64>0,($F$64*(1+(D$72/100)))/(SUM(Brecha!$D$19:$N$19)*(1+($C76/100))),"") | E76: =+IF($F$64>0,($F$64*(1+(E$72/100)))/(SUM(Brecha!$D$19:$N$19)*(1+($C76/100))),"") | F76: =+IF($F$64>0,($F$64*(1+(F$72/100)))/(SUM(Brecha!$D$19:$N$19)*(1+($C76/100))),"") | G76: =+IF($F$64>0,($F$64*(1+(G$72/100)))/(SUM(Brecha!$D$19:$N$19)*(1+($C76/100))),"") | H76: =+IF($F$64>0,($F$64*(1+(H$72/100)))/(SUM(Brecha!$D$19:$N$19)*(1+($C76/100))),"") | I76: =+IF($F$64>0,($F$64*(1+(I$72/100)))/(SUM(Brecha!$D$19:$N$19)*(1+($C76/100))),"") | J76: =+IF($F$64>0,($F$64*(1+(J$72/100)))/(SUM(Brecha!$D$19:$N$19)*(1+($C76/100))),"")
C77: -15 | D77: =+IF($F$64>0,($F$64*(1+(D$72/100)))/(SUM(Brecha!$D$19:$N$19)*(1+($C77/100))),"") | E77: =+IF($F$64>0,($F$64*(1+(E$72/100)))/(SUM(Brecha!$D$19:$N$19)*(1+($C77/100))),"") | F77: =+IF($F$64>0,($F$64*(1+(F$72/100)))/(SUM(Brecha!$D$19:$N$19)*(1+($C77/100))),"") | G77: =+IF($F$64>0,($F$64*(1+(G$72/100)))/(SUM(Brecha!$D$19:$N$19)*(1+($C77/100))),"") | H77: =+IF($F$64>0,($F$64*(1+(H$72/100)))/(SUM(Brecha!$D$19:$N$19)*(1+($C77/100))),"") | I77: =+IF($F$64>0,($F$64*(1+(I$72/100)))/(SUM(Brecha!$D$19:$N$19)*(1+($C77/100))),"") | J77: =+IF($F$64>0,($F$64*(1+(J$72/100)))/(SUM(Brecha!$D$19:$N$19)*(1+($C77/100))),"")
C78: -25 | D78: =+IF($F$64>0,($F$64*(1+(D$72/100)))/(SUM(Brecha!$D$19:$N$19)*(1+($C78/100))),"") | E78: =+IF($F$64>0,($F$64*(1+(E$72/100)))/(SUM(Brecha!$D$19:$N$19)*(1+($C78/100))),"") | F78: =+IF($F$64>0,($F$64*(1+(F$72/100)))/(SUM(Brecha!$D$19:$N$19)*(1+($C78/100))),"") | G78: =+IF($F$64>0,($F$64*(1+(G$72/100)))/(SUM(Brecha!$D$19:$N$19)*(1+($C78/100))),"") | H78: =+IF($F$64>0,($F$64*(1+(H$72/100)))/(SUM(Brecha!$D$19:$N$19)*(1+($C78/100))),"") | I78: =+IF($F$64>0,($F$64*(1+(I$72/100)))/(SUM(Brecha!$D$19:$N$19)*(1+($C78/100))),"") | J78: =+IF($F$64>0,($F$64*(1+(J$72/100)))/(SUM(Brecha!$D$19:$N$19)*(1+($C78/100))),"")
C79: -35 | D79: =+IF($F$64>0,($F$64*(1+(D$72/100)))/(SUM(Brecha!$D$19:$N$19)*(1+($C79/100))),"") | E79: =+IF($F$64>0,($F$64*(1+(E$72/100)))/(SUM(Brecha!$D$19:$N$19)*(1+($C79/100))),"") | F79: =+IF($F$64>0,($F$64*(1+(F$72/100)))/(SUM(Brecha!$D$19:$N$19)*(1+($C79/100))),"") | G79: =+IF($F$64>0,($F$64*(1+(G$72/100)))/(SUM(Brecha!$D$19:$N$19)*(1+($C79/100))),"") | H79: =+IF($F$64>0,($F$64*(1+(H$72/100)))/(SUM(Brecha!$D$19:$N$19)*(1+($C79/100))),"") | I79: =+IF($F$64>0,($F$64*(1+(I$72/100)))/(SUM(Brecha!$D$19:$N$19)*(1+($C79/100))),"") | J79: =+IF($F$64>0,($F$64*(1+(J$72/100)))/(SUM(Brecha!$D$19:$N$19)*(1+($C79/100))),"")

Sheet Sostenibilidad
B2: SECCIÓN N°11: SOSTENIBILIDAD (de la alternativa seleccionada)
B4: 11.01 Descripción de la capacidad institucional en la sostenibilidad del proyecto
B6: Ítem | G6: Descripción | M6: Documento de opinión favorable del PNCM
B8: Órgano técnico responsable de la operación y mantenimiento del CIAI
B9: Análisis de la disponibilidad oportuna de recursos para la operación y mantenimiento del CIAI
B10: Descripción de los arreglos institucionales para la fase de Funcionamiento
B13: 11.02 Gestión integral de los riesgos
B15: Tipo de riesgo | E15: Descripción del riesgo | J15: Probabilidad de ocurrencia | K15: Impacto | L15: Estimación de riesgo | M15: Medidas de mitigación del riesgo
B17: A | C17: Saneamiento físico legal o arreglo institucional | E17: Para el inicio de la ejecución del proyecto de inversión de CIAI, aún no se tendrá resuelto el saneamiento físico legal o arreglo institucional (que corresponda) y se tendrá libre disponibilidad del terreno donde se ejecutará el proyecto de inversión | L17: =+K17*J17 -> 0 | M17: =+IF(L17=0,"",IF(U17=1,X17,IF(V17=1,Y17,IF(W17=1,Z17,"")))) | U17: =+IF(L17>0.179,1,0) -> 0 | V17: =+IF(U17+W17=0,1,0) -> 0 | W17: =+IF(L17<0.051,1,0) -> 1 | X17: ="Profundizar el nivel de información de "&C17&", antes de elaborar el expediente técnico y proponer medidas de reducción de probabilidad o impacto sobre el costo, alcance o cronograma del proyecto" -> Profundizar el nivel de información de Saneamiento físico legal o arreglo institucional, antes de elaborar el expediente técnico y proponer medidas de reducción de probabilidad o impacto sobre el costo, alcance o cronograma del proyecto | Y17: ="Profundizar el nivel de información de "&C17&", en la etapa de ejecución. De corresponder, proponer medidas de reducción de probabilidad o impacto sobre el costo, alcance o cronograma del proyecto" -> Profundizar el nivel de información de Saneamiento físico legal o arreglo institucional, en la etapa de ejecución. De corresponder, proponer medidas de reducción de probabilidad o impacto sobre el costo, alcance o cronograma del proyecto | Z17: ="Monitorear la condición de "&C17&", en la etapa de ejecución" -> Monitorear la condición de Saneamiento físico legal o arreglo institucional, en la etapa de ejecución
B18: B | C18: Ubicación de activos de la UP | E18: Los activos que se generarán o intervendrán con el proyecto de inversión de CIAI, tendrá más de una ubicación | L18: =+K18*J18 -> 0 | M18: =+IF(L18=0,"",IF(U18=1,X18,IF(V18=1,Y18,IF(W18=1,Z18,"")))) | U18: =+IF(L18>0.179,1,0) -> 0 | V18: =+IF(U18+W18=0,1,0) -> 0 | W18: =+IF(L18<0.051,1,0) -> 1 | X18: ="Profundizar el nivel de información de "&C18&", antes de elaborar el expediente técnico y proponer medidas de reducción de probabilidad o impacto sobre el costo, alcance o cronograma del proyecto" -> Profundizar el nivel de información de Ubicación de activos de la UP, antes de elaborar el expediente técnico y proponer medidas de reducción de probabilidad o impacto sobre el costo, alcance o cronograma del proyecto | Y18: ="Profundizar el nivel de información de "&C18&", en la etapa de ejecución. De corresponder, proponer medidas de reducción de probabilidad o impacto sobre el costo, alcance o cronograma del proyecto" -> Profundizar el nivel de información de Ubicación de activos de la UP, en la etapa de ejecución. De corresponder, proponer medidas de reducción de probabilidad o impacto sobre el costo, alcance o cronograma del proyecto | Z18: ="Monitorear la condición de "&C18&", en la etapa de ejecución" -> Monitorear la condición de Ubicación de activos de la UP, en la etapa de ejecución
B19: C | C19: Impactos ambientales del PI | E19: El proyecto de inversión de CIAI, durante la fase de ejecución o funcionamiento, generará importantes impactos negativos en el medio ambiente o conflictos sociales | L19: =+K19*J19 -> 0 | M19: =+IF(L19=0,"",IF(U19=1,X19,IF(V19=1,Y19,IF(W19=1,Z19,"")))) | U19: =+IF(L19>0.179,1,0) -> 0 | V19: =+IF(U19+W19=0,1,0) -> 0 | W19: =+IF(L19<0.051,1,0) -> 1 | X19: ="Profundizar el nivel de información de "&C19&", antes de elaborar el expediente técnico y proponer medidas de reducción de probabilidad o impacto sobre el costo, alcance o cronograma del proyecto" -> Profundizar el nivel de información de Impactos ambientales del PI, antes de elaborar el expediente técnico y proponer medidas de reducción de probabilidad o impacto sobre el costo, alcance o cronograma del proyecto | Y19: ="Profundizar el nivel de información de "&C19&", en la etapa de ejecución. De corresponder, proponer medidas de reducción de probabilidad o impacto sobre el costo, alcance o cronograma del proyecto" -> Profundizar el nivel de información de Impactos ambientales del PI, en la etapa de ejecución. De corresponder, proponer medidas de reducción de probabilidad o impacto sobre el costo, alcance o cronograma del proyecto | Z19: ="Monitorear la condición de "&C19&", en la etapa de ejecución" -> Monitorear la condición de Impactos ambientales del PI, en la etapa de ejecución
B20: D | C20: Organización y experiencia de la UEI | E20: La Unidad Ejecutora de Inversiones propuesta como responsable de la fase de ejecución del proyecto de inversión de CIAI no cuenta con experiencia en la ejecución de inversiones de esta tipología | L20: =+K20*J20 -> 0 | M20: =+IF(L20=0,"",IF(U20=1,X20,IF(V20=1,Y20,IF(W20=1,Z20,"")))) | U20: =+IF(L20>0.179,1,0) -> 0 | V20: =+IF(U20+W20=0,1,0) -> 0 | W20: =+IF(L20<0.051,1,0) -> 1 | X20: ="Profundizar el nivel de información de "&C20&", antes de elaborar el expediente técnico y proponer medidas de reducción de probabilidad o impacto sobre el costo, alcance o cronograma del proyecto" -> Profundizar el nivel de información de Organización y experiencia de la UEI, antes de elaborar el expediente técnico y proponer medidas de reducción de probabilidad o impacto sobre el costo, alcance o cronograma del proyecto | Y20: ="Profundizar el nivel de información de "&C20&", en la etapa de ejecución. De corresponder, proponer medidas de reducción de probabilidad o impacto sobre el costo, alcance o cronograma del proyecto" -> Profundizar el nivel de información de Organización y experiencia de la UEI, en la etapa de ejecución. De corresponder, proponer medidas de reducción de probabilidad o impacto sobre el costo, alcance o cronograma del proyecto | Z20: ="Monitorear la condición de "&C20&", en la etapa de ejecución" -> Monitorear la condición de Organización y experiencia de la UEI, en la etapa de ejecución
B21: E | C21: Modalidad de ejecución del proyecto de inversión | E21: Se propondrá ejecutar el proyecto de inversión de CIAI bajo la modalidad de núcleos ejecutores | L21: =+K21*J21 -> 0 | M21: =+IF(L21=0,"",IF(U21=1,X21,IF(V21=1,Y21,IF(W21=1,Z21,"")))) | U21: =+IF(L21>0.179,1,0) -> 0 | V21: =+IF(U21+W21=0,1,0) -> 0 | W21: =+IF(L21<0.051,1,0) -> 1 | X21: ="Profundizar el nivel de información de "&C21&", antes de elaborar el expediente técnico y proponer medidas de reducción de probabilidad o impacto sobre el costo, alcance o cronograma del proyecto" -> Profundizar el nivel de información de Modalidad de ejecución del proyecto de inversión, antes de elaborar el expediente técnico y proponer medidas de reducción de probabilidad o impacto sobre el costo, alcance o cronograma del proyecto | Y21: ="Profundizar el nivel de información de "&C21&", en la etapa de ejecución. De corresponder, proponer medidas de reducción de probabilidad o impacto sobre el costo, alcance o cronograma del proyecto" -> Profundizar el nivel de información de Modalidad de ejecución del proyecto de inversión, en la etapa de ejecución. De corresponder, proponer medidas de reducción de probabilidad o impacto sobre el costo, alcance o cronograma del proyecto | Z21: ="Monitorear la condición de "&C21&", en la etapa de ejecución" -> Monitorear la condición de Modalidad de ejecución del proyecto de inversión, en la etapa de ejecución
B22: F | C22: Exposición a peligros naturales, socionaturales o antrópicos | E22: Uno o varios activos del CIAI, en la situación con proyecto, se encontrarán expuestos a peligros naturales, socio-naturales o antrópicos | L22: =+K22*J22 -> 0 | M22: =+IF(L22=0,"",IF(U22=1,X22,IF(V22=1,Y22,IF(W22=1,Z22,"")))) | U22: =+IF(L22>0.179,1,0) -> 0 | V22: =+IF(U22+W22=0,1,0) -> 0 | W22: =+IF(L22<0.051,1,0) -> 1 | X22: ="Profundizar el nivel de información de "&C22&", antes de elaborar el expediente técnico y proponer medidas de reducción de probabilidad o impacto sobre el costo, alcance o cronograma del proyecto" -> Profundizar el nivel de información de Exposición a peligros naturales, socionaturales o antrópicos, antes de elaborar el expediente técnico y proponer medidas de reducción de probabilidad o impacto sobre el costo, alcance o cronograma del proyecto | Y22: ="Profundizar el nivel de información de "&C22&", en la etapa de ejecución. De corresponder, proponer medidas de reducción de probabilidad o impacto sobre el costo, alcance o cronograma del proyecto" -> Profundizar el nivel de información de Exposición a peligros naturales, socionaturales o antrópicos, en la etapa de ejecución. De corresponder, proponer medidas de reducción de probabilidad o impacto sobre el costo, alcance o cronograma del proyecto | Z22: ="Monitorear la condición de "&C22&", en la etapa de ejecución" -> Monitorear la condición de Exposición a peligros naturales, socionaturales o antrópicos, en la etapa de ejecución
B23: G | C23: Ubicación en zonas arqueológicas o declaradas como patrimonio cultural | E23: Uno o varios de los activos del CIAI, en la situación con proyecto, se encontrarán ubicados en zonas arqueológicas o declaradas como patrimonio cultural | L23: =+K23*J23 -> 0 | M23: =+IF(L23=0,"",IF(U23=1,X23,IF(V23=1,Y23,IF(W23=1,Z23,"")))) | U23: =+IF(L23>0.179,1,0) -> 0 | V23: =+IF(U23+W23=0,1,0) -> 0 | W23: =+IF(L23<0.051,1,0) -> 1 | X23: ="Profundizar el nivel de información de "&C23&", antes de elaborar el expediente técnico y proponer medidas de reducción de probabilidad o impacto sobre el costo, alcance o cronograma del proyecto" -> Profundizar el nivel de información de Ubicación en zonas arqueológicas o declaradas como patrimonio cultural, antes de elaborar el expediente técnico y proponer medidas de reducción de probabilidad o impacto sobre el costo, alcance o cronograma del proyecto | Y23: ="Profundizar el nivel de información de "&C23&", en la etapa de ejecución. De corresponder, proponer medidas de reducción de probabilidad o impacto sobre el costo, alcance o cronograma del proyecto" -> Profundizar el nivel de información de Ubicación en zonas arqueológicas o declaradas como patrimonio cultural, en la etapa de ejecución. De corresponder, proponer medidas de reducción de probabilidad o impacto sobre el costo, alcance o cronograma del proyecto | Z23: ="Monitorear la condición de "&C23&", en la etapa de ejecución" -> Monitorear la condición de Ubicación en zonas arqueológicas o declaradas como patrimonio cultural, en la etapa de ejecución
B24: H | C24: Identificación de interferencias | E24: En la ubicación del CIAI o de algunos de sus activos se presentarán interferencias (redes de agua, alcantarillado, gas, telefonía o similar), al momento de su ejecución | L24: =+K24*J24 -> 0 | M24: =+IF(L24=0,"",IF(U24=1,X24,IF(V24=1,Y24,IF(W24=1,Z24,"")))) | U24: =+IF(L24>0.179,1,0) -> 0 | V24: =+IF(U24+W24=0,1,0) -> 0 | W24: =+IF(L24<0.051,1,0) -> 1 | X24: ="Profundizar el nivel de información de "&C24&", antes de elaborar el expediente técnico y proponer medidas de reducción de probabilidad o impacto sobre el costo, alcance o cronograma del proyecto" -> Profundizar el nivel de información de Identificación de interferencias, antes de elaborar el expediente técnico y proponer medidas de reducción de probabilidad o impacto sobre el costo, alcance o cronograma del proyecto | Y24: ="Profundizar el nivel de información de "&C24&", en la etapa de ejecución. De corresponder, proponer medidas de reducción de probabilidad o impacto sobre el costo, alcance o cronograma del proyecto" -> Profundizar el nivel de información de Identificación de interferencias, en la etapa de ejecución. De corresponder, proponer medidas de reducción de probabilidad o impacto sobre el costo, alcance o cronograma del proyecto | Z24: ="Monitorear la condición de "&C24&", en la etapa de ejecución" -> Monitorear la condición de Identificación de interferencias, en la etapa de ejecución
B25: Debe ser llenado por la Unidad Formuladora, al culminar la formulación y evaluación del proyecto | U25: =SUM(U17:U24) -> 0 | V25: =SUM(V17:V24) -> 0 | W25: =SUM(W17:W24) -> 8

Sheet Gestión
B2: SECCIÓN N°12: GESTIÓN DEL PROYECTO (de la alternativa seleccionada)
B4: 12.01 Plan de implementación
B6: Actividades del Plan de Implementación | F6: Fecha | H6: Órgano Responsable | J6: Periodo (trimestre)
F7: Inicio | G7: Fin | J7: 1 | K7: 2 | L7: 3 | M7: 4 | N7: 5 | O7: 6 | P7: 7 | Q7: 8
B9: Expediente Técnico (ET) o Estudio Definitivo (ED)
B19: Supervisión
B29: Ejecución
B40: 12.02 Modalidad de ejecución de proyecto
B42: Tipo de ejecución
B44: Administración directa
B46: 12.03 Requerimientos institucionales y normativos en la fase de Ejecución y fase de Funcionamiento
B48: Condiciones previas relevantes para la fase de ejecución
B50: Condición o requerimiento | G50: Marcar | H50: Estado situacional
B51: Saneamiento técnico legal o arreglo institucional
B52: Factibilidad de servicios de agua, desagüe y electricidad
B53: Certificado de parámetros urbanísticos
B54: Licencia de construcción
B56: 12.04 Entidad que estará a cargo de la operación y mantenimiento
B58: Programa Nacional Cuna Más
B60: 12.05 Fuente de financiamiento
B62: Fuente de Financiamiento | C62: Marcar

Sheet Impacto ambiental
B2: SECCIÓN N°13: IMPACTO AMBIENTAL (de la alternativa seleccionada)
B4: 13.01 Impacto ambiental
B6: IMPACTOS NEGATIVOS | F6: MEDIDAS DE MITIGACIÓN | I6: COSTO (S/)
B8: Durante la Ejecución
B12: Durante el Funcionamiento
B16: Nota: los costos deben formar parte del costo de inversión del proyecto

Sheet Marco Lógico
B2: SECCIÓN N°14: MARCO LÓGICO (de la alternativa seleccionada)
B4: 14.01 RESUMEN DEL PROYECTO: MATRIZ DEL MARCO LÓGICO
B6: Nivel de objetivo | E6: Indicador | H6: Valor | I6: Medios de verificación | L6: Supuestos
B8: Fin
B9: =+"Mayor nivel de desarrollo infantil temprano de los niños y niñas menores de 36 meses que viven en situación de pobreza y pobreza extrema, en la localidad de "&'Unidad Productora'!L20&", distrito de "&'Unidad Productora'!J20&", provincia de "&'Unidad Productora'!H20&", departamento de "&'Unidad Productora'!E20 -> Mayor nivel de desarrollo infantil temprano de los niños y niñas menores de 36 meses que viven en situación de pobreza y pobreza extrema, en la localidad de , distrito de , provincia de , departamento de | E9: Porcentaje de niños/as menores de 36 meses que logran los hitos de desarrollo infantil temprano esperados para su edad, a partir del tercer año del inicio de la fase de funcionamiento | I9: Encuesta de Salud y Desarrollo en la Primera Infancia
B10: Propósito
B11: =+'Problema-Objetivo'!B33:E33 | E11: Porcentaje de niños y niñas con un mínimo de permanencia de 6 meses atendidos en el CIAI, que cumplen con los estándares de calidad definidos por el PNCM, a partir del primer año del inicio de la fase de funcionamiento | I11: Ficha de seguimiento del Servicio de Cuidado Diurno | L11: Padres toman conciencia de la importancia del cuidado y aprendizaje de las niñas y niños para su desarrollo Actores comunales comprometidos en el cuidado y atención a la niña y el niño menor de 3 años
B12: Componentes
B13: =+CostosAlt1!B6&": "&CostosAlt1!D6 -> Componente 1: | E13: Número de m2 de infraestructura del CIAI, implementados con el proyecto, que cumplen con los requerimientos normativos del PNCM, al concluir la fase de ejecución del proyecto | H13: =+CostosAlt1!S165 -> 0 | I13: Registro del Formato N° 09 - Registro del Cierre de Inversiones, en el Banco de Inversiones del SNPMGI | L13: Se asigna recursos necesarios para el adecuado mantenimiento disponibles durante el horizonte de evaluación
B14: =+CostosAlt1!B21&": "&CostosAlt1!D21 -> Componente 2: | E14: Número de equipos del CIAI, implementados con el proyecto, que cumplen con los requerimientos normativos del PNCM, al concluir la fase de ejecución del proyecto | H14: =+CostosAlt1!S167 -> 0
B15: =+CostosAlt1!B28&": "&CostosAlt1!D28 -> Componente 3: | E15: Número de mobiliarios del CIAI, implementados con el proyecto, que cumplen con los requerimientos normativos del PNCM, al concluir la fase de ejecución del proyecto | H15: =+CostosAlt1!S169 -> 0
B16: =+CostosAlt1!B36&": "&CostosAlt1!D36 -> Componente 4: | E16: Número de sesiones de capacitación desarrolladas, dirigidas de actores comunitarios, en el marco del proyecto, al concluir la fase de ejecución del proyecto | H16: =+CostosAlt1!S171 -> 0
B17: Acciones
B18: Componente 1: | E18: …
B19: Construcción, habilitación y/o adecuación de infraestructura del CIAI | E19: Ejecución del componente del proyecto, por un monto de: | H19: =+CostosAlt1!Q135 -> 0 | I19: Recepción y conformidad de construcción, habilitación y/o adecuación de infraestructura del CIAI Recepción y conformidad de equipamiento adquirido. Recepción y conformidad de mobiliario adquirido. Conformidad de servicio de capacitación realziado. | L19: Se cumple con la asignación presupuestal oportuna para la ejecución del proyecto.
B20: Componente 2
B21: Adquisición de equipamiento del CIAI | E21: Ejecución del componente del proyecto, por un monto de: | H21: =+CostosAlt1!Q137 -> 0
B22: Componente 3
B23: Adquisición de mobiliario del CIAI | E23: Ejecución del componente del proyecto, por un monto de: | H23: =+CostosAlt1!Q139 -> 0
B24: Componente 4
B25: Capacitación de recursos humanos que operan en el CIAI | E25: Ejecución del componente del proyecto, por un monto de: | H25: =+CostosAlt1!Q141 -> 0
B26: Implementación de medidas de reducción del riesgo de desastre y mitigación ambiental | E26: Ejecución de las medidas, por un monto de: | H26: =+CostosAlt1!Q143 -> 0

Sheet Conclusiones
B2: SECCIÓN N°15: CONCLUSIONES Y RECOMENDACIONES
B4: 15.01 CONCLUSIONES Y RECOMENDACIONES

Sheet Firmas
B2: SECCIÓN N°16: FIRMAS
B4: 16.01 FIRMAS
B10: Preparado o supervisado por: | E10: ……………………………………………………………………………. | I10: Fecha: | J10: …………………………………………………………………………….
E11: Especialista de la UF o Responsable de la UF
B17: Declarado viable por: | E17: ……………………………………………………………………………. | I17: Fecha: | J17: …………………………………………………………………………….
E18: Responsable de la UF

Sheet Anexos
B1: SECCIÓN N°17: ANEXOS
B3: 17.01 ANEXOS
B5: Nro. | C5: Descripción del anexo | P5: ¿Se presenta el anexo como parte de la Ficha Técnica Estándar?
B7: A | C7: Resumen ejecutivo.
B8: B | C8: Informe técnico de la situación actual de la unidad productora (infraestructura, mobiliario, equipamiento y capacitación), suscrito por el equipo responsable de la formulación
B9: C | C9: Evidencias de la realización de talleres, reuniones y actividades similares, tales como fotografías, listas firmadas de participantes y documentos de acuerdos como actas, entre otros.
B10: D | C10: Informe técnico de la propuesta de intervención (en infraestructura, mobiliario, equipamiento y capacitación), suscrito por el equipo responsable de la formulación
B11: E | C11: Opinión favorable a la propuesta técnica por parte Programa Nacional Cuna Más, a la propuesta de intervención.
B12: F | C12: Detalle del costo de inversión de las alternativas técnicas, suscrito por el equipo responsable de la formulación
B13: G | C13: Documento de opinión favorable del Programa Nacional Cuna Más, para la sostenibilidad del proyecto de inversión del CIAI.
B14: H | C14: Documento de sustento del saneamiento físico legal o arreglo institucional que corresponda.
B16: Importante: Se debe presentar TODOS los anexos requeridos, como parte de la Ficha Técnica Estándar

Sheet UBIGEO
A2: Ubigeo | B2: Distrito | C2: Provincia | D2: Departamento
A3: 010101 | B3: Chachapoyas | C3: Chachapoyas | D3: Amazonas
A4: 010102 | B4: Asuncion | C4: Chachapoyas | D4: Amazonas
A5: 010103 | B5: Balsas | C5: Chachapoyas | D5: Amazonas
A6: 010104 | B6: Cheto | C6: Chachapoyas | D6: Amazonas
A7: 010105 | B7: Chiliquin | C7: Chachapoyas | D7: Amazonas
A8: 010106 | B8: Chuquibamba | C8: Chachapoyas | D8: Amazonas
A9: 010107 | B9: Granada | C9: Chachapoyas | D9: Amazonas
A10: 010108 | B10: Huancas | C10: Chachapoyas | D10: Amazonas
A11: 010109 | B11: La Jalca | C11: Chachapoyas | D11: Amazonas
A12: 010110 | B12: Leimebamba | C12: Chachapoyas | D12: Amazonas
A13: 010111 | B13: Levanto | C13: Chachapoyas | D13: Amazonas
... A1876: 250401 | B1876: Purus | C1876: Purus | D1876: Ucayali
